Workbook

Sheet Read Me
A1: Appropriations Pilot — CJS Title III (Science) + Labor-HHS Title II (HHS), Loaded Against the Schema
A2: Built from your filled-in CJS_Title_III_Science_Pilot_Schema_Loaded workbook. Five tabs, matching the Data Dictionary in the scoping doc.
A4: v37: verified links; how each year was enacted
A5: • Links: 45 links (source documents and Bill Report Reference bill_url / report_jes_url) now point at the file whose sha256 matches the document we ingested (Claude Code link check, link_results_v36.csv). Older reports (FY2017–FY2023) use govinfo, since Congress.gov serves a re-stamped copy; 118th–119th reports use Congress.gov. The 12 Labor-HHS bill_url landing pages are now PDFs. The FY2023 Senate Labor-HHS statement uses its direct PDF. Links that could not be checked (no stored file) are unchanged. The build now also stops on a landing-page bill_url.
A6: • Bill Report Reference: four new columns on Enacted rows: vehicle_bill_id (the bill the law was enacted as), division, enactment_date and funding_type (standalone / minibus / omnibus / full_year_cr). Values for the 14 enacted rows are from the National Taxpayers Union Foundation's Definitive Congressional Appropriations History Database; every public law matched our bill_id. FY2025 (CJS and Labor-HHS) is full_year_cr (P.L. 119-4).
A7: • Page check: 140 of the cited figures were not found by text search on their cited page; nearly all are on image pages (OCR), and no document shows a consistent page offset, so no page was changed. They are listed in the repo (page_check_misses_v36.csv) for review. No figure, page or ID changed.
A9: v36: link corrections
A10: • H.Rpt. 118-585: govinfo files this report as CRPT-118hrpt585-pt1, so the v35 package URL returned a web page, not the PDF. It now links the Congress.gov PDF, whose sha256 matches the ingested file. The eight Bill Report Reference report_jes_url values that were still govinfo landing pages now carry the same PDF links as their Source Documents. The build now stops on any govinfo landing-page link in either place. No figure, page or ID changed.
A12: v35: source links open the PDF
A13: • Nine govinfo sources were stored as their landing pages (govinfo.gov/app/details/...), which cannot open at a page. They now point to the PDF itself (govinfo.gov/content/pkg/<package>/pdf/<file>.pdf): S.Rpt. 118-84, 118-207, 119-55; H.Rpt. 118-585, 119-271, 119-696, 117-403; the FY2026 Labor-HHS explanatory statement (Congressional Record, 2026-01-22); P.L. 119-4. No figure, page or ID changed.
A15: v34: verification rule enforced, AHA relationships
A16: • One rule now sets verification_status everywhere: 'auto-validated' only with confidence >= 0.90, every check passing, and at least one check that confirms the figure (a sum or cross-document match); 'flagged' when a check fails or a person deliberately flagged it; otherwise 'unverified'. 382 Labor-HHS rows moved from auto-validated to unverified, 2 the other way. No auto-validated row is below 0.90.
... A65: • Your 9 already-filled Bill Report Reference rows carried forward untouched, just with subcommittee = CJS added and their reference_id/lookup_key updated to match.

Sheet Account
A1: canonical_account_id | B1: canonical_name | C1: agency | D1: bureau | E1: treasury_account_symbol | F1: status | G1: historical_names | H1: historical_identifiers | I1: fund_type | J1: subcommittee | K1: notes | L1: title | M1: display_order | N1: total_scope | O1: parent_account_id
A2: ACC-OSTP | B2: Office of Science and Technology Policy | C2: Executive Office of the President | D2: Office of Science and Technology Policy | F2: active | I2: general | J2: CJS | L2: Title III | M2: 1
A3: ACC-NSC | B3: National Space Council | C3: Executive Office of the President | D3: National Space Council | F3: active | I3: general | J3: CJS | L3: Title III | M3: 2
A4: ACC-NASA-TOTAL | B4: National Aeronautics and Space Administration (agency total) | C4: National Aeronautics and Space Administration | D4: (Agency Total) | F4: active | I4: general | J4: CJS | K4: Derived rollup — equals the sum of NASA's 9 program accounts below; kept as a reference row, not an independent funding decision. | L4: Title III | M4: 12 | N4: agency
A5: ACC-NASA-SCIENCE | B5: Science | C5: National Aeronautics and Space Administration | D5: Science Mission Directorate | F5: active | I5: general | J5: CJS | L5: Title III | M5: 3
A6: ACC-NASA-AERONAUTICS | B6: Aeronautics | C6: National Aeronautics and Space Administration | D6: Aeronautics Research Mission Directorate | F6: active | I6: general | J6: CJS | L6: Title III | M6: 4
A7: ACC-NASA-SPACETECH | B7: Space Technology | C7: National Aeronautics and Space Administration | D7: Space Technology Mission Directorate | F7: active | G7: Exploration Research and Technology; Exploration Technology | I7: general | J7: CJS | L7: Title III | M7: 5
A8: ACC-NASA-EXPLORATION | B8: Exploration | C8: National Aeronautics and Space Administration | D8: Exploration Systems Development | F8: active | G8: Deep Space Exploration Systems | I8: general | J8: CJS | L8: Title III | M8: 6
A9: ACC-NASA-SPACEOPS | B9: Space Operations | C9: National Aeronautics and Space Administration | D9: Space Operations Mission Directorate | F9: active | G9: LEO and Spaceflight Operations | I9: general | J9: CJS | L9: Title III | M9: 7
A10: ACC-NASA-STEM-ENGAGEMENT | B10: Science, Technology, Engineering, and Mathematics Engagement | C10: National Aeronautics and Space Administration | D10: STEM Engagement | F10: active | G10: Education; STEM Opportunities formerly Education | I10: general | J10: CJS | L10: Title III | M10: 8
A11: ACC-NASA-SAFETY-SECURITY | B11: Safety, Security and Mission Services | C11: National Aeronautics and Space Administration | D11: Mission Support Directorate | F11: active | I11: general | J11: CJS | L11: Title III | M11: 9
A12: ACC-NASA-CONSTRUCTION | B12: Construction and Environmental Compliance and Restoration | C12: National Aeronautics and Space Administration | D12: Mission Support Directorate | F12: active | I12: general | J12: CJS | L12: Title III | M12: 10
A13: ACC-NASA-OIG | B13: Office of Inspector General | C13: National Aeronautics and Space Administration | D13: Office of Inspector General | F13: active | I13: general | J13: CJS | L13: Title III | M13: 11
A14: ACC-NSF-TOTAL | B14: National Science Foundation (agency total) | C14: National Science Foundation | D14: (Agency Total) | F14: active | I14: general | J14: CJS | K14: Derived rollup — equals the sum of NSF's 6 program accounts below; kept as a reference row, not an independent funding decision. | L14: Title III | M14: 19 | N14: agency
A15: ACC-NSF-RRA | B15: Research and Related Activities | C15: National Science Foundation | D15: Research and Related Activities | F15: active | I15: general | J15: CJS | L15: Title III | M15: 13
A16: ACC-NSF-MREFC | B16: Major Research Equipment and Facilities Construction | C16: National Science Foundation | D16: Major Research Equipment and Facilities Construction | F16: active | I16: general | J16: CJS | L16: Title III | M16: 14
A17: ACC-NSF-STEM-EDUCATION | B17: STEM Education | C17: National Science Foundation | D17: STEM Education | F17: active | G17: Education and Human Resources | I17: general | J17: CJS | L17: Title III | M17: 15
A18: ACC-NSF-AGENCY-OPS | B18: Agency Operations and Award Management | C18: National Science Foundation | D18: Agency Operations and Award Management | F18: active | I18: general | J18: CJS | L18: Title III | M18: 16
A19: ACC-NSF-NSB | B19: Office of the National Science Board | C19: National Science Foundation | D19: National Science Board | F19: active | I19: general | J19: CJS | L19: Title III | M19: 17
A20: ACC-NSF-OIG | B20: Office of Inspector General | C20: National Science Foundation | D20: Office of Inspector General | F20: active | I20: general | J20: CJS | L20: Title III | M20: 18
A21: ACC-DOJ-CVF | B21: Crime Victims Fund | C21: Department of Justice | D21: State, Local, and Tribal Justice Assistance | F21: active | I21: trust | J21: CJS | K21: Appears across multiple bill titles as a transfer-out source (to OVW, to OIG) and carries the FY27 CHIMP / CHIMP Pop-Up mandatory-program adjustment.
A22: ACC-DOJ-AFF | B22: Assets Forfeiture Fund | C22: Department of Justice | D22: Legal Activities and U.S. Marshals | F22: active | I22: trust | J22: CJS | L22: Title II | M22: 23
A23: ACC-DOJ-WCF | B23: Working Capital Fund | C23: Department of Justice | D23: Justice Operations, Management, and Accountability | F23: active | I23: working_capital | J23: CJS | K23: Subject to a Sec. 521(c)(1) rescission in the FY2027 bill. Title placement (Title V) is tentative -- derived only from a transfer or rescission line, not the account's own budget-authority line. A general provision can touch an account whose own appropriation sits in a different title. | L23: Title V | M23: 27
A24: ACC-USPTO-SE | B24: Salaries and Expenses | C24: Department of Commerce | D24: U.S. Patent and Trademark Office | F24: active | I24: general | J24: CJS | K24: Fully fee-funded: gross spending is offset almost entirely by fee collections. | L24: Title I | M24: 21
A25: ACC-DOJ-ANTITRUST-SE | B25: Salaries and Expenses, Antitrust Division | C25: Department of Justice | D25: Legal Activities and U.S. Marshals | F25: active | I25: general | J25: CJS | K25: Offset by Hart-Scott-Rodino fee collections, netting to $0 in FY2027 House Reported. | L25: Title II | M25: 24
A26: ACC-DOJ-USTSF | B26: United States Trustee System Fund | C26: Department of Justice | D26: Legal Activities and U.S. Marshals | F26: active | I26: general | J26: CJS | K26: Offsetting fee collections exceed the account's own direct appropriation. | L26: Title II | M26: 25
A27: ACC-NOAA-ORF | B27: Operations, Research, and Facilities | C27: Department of Commerce | D27: National Oceanic and Atmospheric Administration | F27: active | I27: general | J27: CJS | K27: Receives a transfer from the Promote and Develop Fisheries account; also carries a Sec. 521(a)(1) rescission in FY2027. | L27: Title I | M27: 20
A28: ACC-NOAA-PDF | B28: Promote and Develop Fishery Products and Research | C28: Department of Commerce | D28: National Oceanic and Atmospheric Administration | F28: active | I28: general | J28: CJS | K28: Transfers its full balance to Operations, Research, and Facilities every year in this series. Title placement (Title I) is tentative -- derived only from a transfer or rescission line, not the account's own budget-authority line. A general provision can touch an account whose own appropriation sits in a different title. | L28: Title I | M28: 22
A29: ACC-DOJ-OJP-RESC | B29: Office of Justice Programs Rescission | C29: Department of Justice | D29: State, Local, and Tribal Justice Assistance | F29: active | I29: general | J29: CJS | K29: A rescission-only line (Sec. 521(b)(2)), not a standing program account. Title placement (Title V) is tentative -- derived only from a transfer or rescission line, not the account's own budget-authority line. A general provision can touch an account whose own appropriation sits in a different title. | L29: Title V | M29: 28
A30: ACC-DOJ-VAWA | B30: Violence Against Women Prevention and Prosecution Programs | C30: Department of Justice | D30: State, Local, and Tribal Justice Assistance | F30: active | I30: general | J30: CJS | K30: Receives a transfer from the Crime Victims Fund. Title placement (Title II) is tentative -- derived only from a transfer or rescission line, not the account's own budget-authority line. A general provision can touch an account whose own appropriation sits in a different title. | L30: Title II | M30: 26
A31: ACC-DOJ-OIG | B31: Office of Inspector General | C31: Department of Justice | D31: Justice Operations, Management, and Accountability | F31: active | I31: general | J31: CJS | K31: Receives a transfer from the Crime Victims Fund. Title placement (Title V) is tentative -- derived only from a transfer or rescission line, not the account's own budget-authority line. A general provision can touch an account whose own appropriation sits in a different title. | L31: Title V | M31: 29
A32: ACC-HHS-AHA-TOTAL | B32: Administration for a Healthy America (agency total) | C32: Administration for a Healthy America | D32: (Agency Total) | F32: proposed | I32: general | J32: LHHS | K32: Proposed in the FY2026 and FY2027 budget requests only; never reported by a committee or enacted (P.L. 119-75 has no such heading). The committee tables print it only in the request column, as the request's funding 'not displayed under other HHS accounts below' (H.Rept. 119-271 p.334 footnote 1/): the tables show most of the proposed AHA under HRSA, SAMHSA and the other legacy lines. Derived rollup (agency). H.Rept. 119-696 prints no plain total, only 'Administration for a Healthy America, Discretionary 1/', recorded as the headline there. | L32: Title II | M32: 1 | N32: agency
A33: ACC-HHS-HRSA-HEALTH-CENTERS | B33: Health Centers | C33: Health Resources and Services Administration | D33: Primary Health Care | F33: active | I33: general | J33: LHHS | K33: A program line under Primary Health Care (with Free Clinics Medical Malpractice). | L33: Title II | M33: 2 | O33: ACC-HHS-HRSA-PRIMARY-CARE
A34: ACC-HHS-HRSA-PRIMARY-CARE | B34: Primary Health Care | C34: Health Resources and Services Administration | D34: Primary Health Care | F34: active | I34: general | J34: LHHS | K34: The appropriation heading 'Primary Health Care' (the law's dollar figure); printed as 'Total, Primary Health Care'. | L34: Title II | M34: 3
A35: ACC-HHS-HRSA-VICTF | B35: Vaccine Injury Compensation Program Trust Fund | C35: Health Resources and Services Administration | D35: Vaccine Injury Compensation Program | F35: active | I35: trust | J35: LHHS | K35: Trust fund, mandatory. The law appropriates 'such sums as may be necessary' for claims plus a fixed HRSA administrative-expenses amount (15,200); the tables' claims figure is an estimate, not a law figure. | L35: Title II | M35: 4
A36: ACC-HHS-HRSA-TOTAL | B36: Health Resources and Services Administration (agency total) | C36: Health Resources and Services Administration | D36: (Agency Total) | F36: active | I36: general | J36: LHHS | K36: Derived rollup -- HRSA's agency total as the Title II table prints it; kept as a reference row, not an independent funding decision. Includes the Vaccine Injury Compensation trust fund and the Covered Countermeasures Process Fund; 'Total, Health Resources and Services' (no 'Administration') is a smaller subtotal. | L36: Title II | M36: 5 | N36: agency
A37: ACC-HHS-CDC-TOTAL | B37: Centers for Disease Control and Prevention (agency total) | C37: Centers for Disease Control and Prevention | D37: (Agency Total) | F37: active | I37: general | J37: LHHS | K37: Derived rollup -- CDC's agency total as the Title II table prints it; kept as a reference row, not an independent funding decision. | L37: Title II | M37: 6 | N37: agency
A38: ACC-HHS-NIH-NCI | B38: National Cancer Institute | C38: National Institutes of Health | D38: National Cancer Institute | F38: active | I38: general | J38: LHHS | L38: Title II | M38: 7
A39: ACC-HHS-NIH-TOTAL | B39: National Institutes of Health (agency total) | C39: National Institutes of Health | D39: (Agency Total) | F39: active | I39: general | J39: LHHS | K39: Derived rollup (agency) -- NIH's agency total as the Title II table prints it: 'Total, National Institutes of Health (with CURES Act funding)' (decision 2026-09-27); kept as a reference row, not an independent funding decision. Since v33 the CURES Act money is its own account (ACC-HHS-NIH-CURES), one of the NIH accounts this total adds up; the Title II total subtracts the CURES line (inside NIH's total, outside the title's). | L39: Title II | M39: 8 | N39: agency
A40: ACC-HHS-SAMHSA-TOTAL | B40: Substance Abuse and Mental Health Services Administration (agency total) | C40: Substance Abuse and Mental Health Services Administration | D40: (Agency Total) | F40: active | I40: general | J40: LHHS | K40: Derived rollup -- SAMHSA's agency total as the Title II table prints it; kept as a reference row, not an independent funding decision. | L40: Title II | M40: 9 | N40: agency
A41: ACC-HHS-AHRQ-TOTAL | B41: Agency for Healthcare Research and Quality (agency total) | C41: Agency for Healthcare Research and Quality | D41: (Agency Total) | F41: active | I41: general | J41: LHHS | K41: Derived rollup -- AHRQ's agency total as the Title II table prints it; kept as a reference row, not an independent funding decision. | L41: Title II | M41: 10 | N41: agency
A42: ACC-HHS-CMS-MEDICAID | B42: Grants to States for Medicaid | C42: Centers for Medicare & Medicaid Services | D42: Grants to States for Medicaid | F42: active | I42: general | J42: LHHS | K42: Mandatory. Three printed totals, each its own observation (decision 2026-09-27): the current-year 'Total, Grants to States for Medicaid' (headline); 'Total, Medicaid[,] program level, available this fiscal year' (component program_level_available_this_fiscal_year); '..., appropriated in this bill' (component appropriated_in_this_bill). The new first-quarter advance is amount_type 'advance' and 'Less appropriations provided in prior years' amount_type 'prior_year_advance' (negative, as printed). S.Rept. 118-84 prints no current-year total. | L42: Title II | M42: 11
A43: ACC-HHS-CMS-TRUST-FUND-PAYMENTS | B43: Payments to the Health Care Trust Funds | C43: Centers for Medicare & Medicaid Services | D43: Payments to the Health Care Trust Funds | F43: active | I43: general | J43: LHHS | K43: Mandatory general-fund payments into the Medicare trust funds. | L43: Title II | M43: 12
A44: ACC-HHS-CMS-PROGRAM-MANAGEMENT | B44: Program Management | C44: Centers for Medicare & Medicaid Services | D44: Program Management | F44: active | I44: trust | J44: LHHS | K44: Funded by transfer from the Medicare trust funds (it sits in CMS's 'Trust Funds' memo line). | L44: Title II | M44: 13
A45: ACC-HHS-CMS-TOTAL | B45: Centers for Medicare & Medicaid Services (agency total) | C45: Centers for Medicare & Medicaid Services | D45: (Agency Total) | F45: active | I45: general | J45: LHHS | K45: Derived rollup -- CMS's agency total as the Title II table prints it; kept as a reference row, not an independent funding decision. Sums Medicaid 'appropriated in this bill' (advance included). | L45: Title II | M45: 14 | N45: agency
A46: ACC-HHS-ACF-LIHEAP | B46: Low Income Home Energy Assistance | C46: Administration for Children and Families | D46: Low Income Home Energy Assistance | F46: active | I46: general | J46: LHHS | K46: No stable total row: 'Total, LIHEAP' where printed; S.Rept. 118-207 and H.Rept. 118-585 print only 'Total, LIHEAP, program level' (recorded as the headline there); the FY2026 JES prints only 'Formula Grants'. | L46: Title II | M46: 15
A47: ACC-HHS-ACF-HEAD-START | B47: Head Start | C47: Administration for Children and Families | D47: Children and Families Services Programs | F47: active | I47: general | J47: LHHS | K47: The line item; an 'Additional funding (emergency)' line under it is a separate supplemental line, not in scope. | L47: Title II | M47: 16 | O47: ACC-HHS-ACF-CFSP
A48: ACC-HHS-ACF-TOTAL | B48: Administration for Children and Families (agency total) | C48: Administration for Children and Families | D48: (Agency Total) | F48: active | I48: general | J48: LHHS | K48: Derived rollup -- ACF's agency total as the Title II table prints it; kept as a reference row, not an independent funding decision. | L48: Title II | M48: 17 | N48: agency
A49: ACC-HHS-ACL-TOTAL | B49: Administration for Community Living (agency total) | C49: Administration for Community Living | D49: (Agency Total) | F49: active | I49: general | J49: LHHS | K49: Derived rollup -- ACL's agency total as the Title II table prints it; kept as a reference row, not an independent funding decision. | L49: Title II | M49: 18 | N49: agency
A50: ACC-HHS-ASPR-TOTAL | B50: Administration for Strategic Preparedness and Response (agency total) | C50: Administration for Strategic Preparedness and Response | D50: (Agency Total) | F50: active | I50: general | J50: LHHS | K50: Derived rollup -- ASPR's agency total as the Title II table prints it; kept as a reference row, not an independent funding decision. A separate operating division in these tables, outside the Office of the Secretary total. | L50: Title II | M50: 19 | N50: agency
A51: ACC-HHS-OS-TOTAL | B51: Office of the Secretary (agency total) | C51: Office of the Secretary | D51: (Agency Total) | F51: active | I51: general | J51: LHHS | K51: Derived rollup -- the Office of the Secretary's agency total as the Title II table prints it; kept as a reference row, not an independent funding decision. | L51: Title II | M51: 20 | N51: agency
A52: ACC-HHS-GP-MEDICARE-OPERATIONS | B52: Medicare Operations (Title II general provision) | C52: Department of Health and Human Services | D52: General Provisions | F52: active | I52: trust | J52: LHHS | K52: A Title II general-provision line, not an operating division's account: the section number varies by bill (House Sec. 226, Senate Sec. 227; P.L. 119-75 Sec. 227). The law lets the Secretary transfer up to $455,000,000 to 'Centers for Medicare & Medicaid Services, Program Management' from the Federal Hospital Insurance and Federal Supplementary Medical Insurance Trust Funds for Medicare program management. The tables print it under General Provisions, outside the CMS total, and count it in the Title II total; recorded as printed (budget authority). | L52: Title II | M52: 21
A53: ACC-HHS-GP-NEF-RESCISSION | B53: Nonrecurring Expenses Fund, HHS (rescission) | C53: Department of Health and Human Services | D53: General Provisions | F53: active | I53: general | J53: LHHS | K53: A rescission-only general-provision line (House Sec. 234/235, P.L. 119-75 Sec. 237: 'Of the unobligated balances in the Nonrecurring Expenses Fund ... are hereby rescinded'), not a standing program account. Recorded as printed (negative). H.Rept. 118-585 also prints a separate '(rescission) (emergency)' line: component 'emergency'. The Senate reports print no such line. | L53: Title II | M53: 22
A54: ACC-HHS-GP-ADOPTION-INCENTIVES-RESCISSION | B54: Adoption Incentives (rescission) | C54: Department of Health and Human Services | D54: General Provisions | F54: active | I54: general | J54: LHHS | K54: A rescission-only line printed only by H.Rept. 118-585, under Title II General Provisions and outside the ACF total, though Adoption Incentives is an ACF program. Recorded as printed (negative). | L54: Title II | M54: 23
A55: ACC-HHS-GP-MEDICARE-LIMITATION | B55: Limitation for Title XVIII of the Social Security Act | C55: Department of Health and Human Services | D55: General Provisions | F55: active | I55: general | J55: LHHS | K55: A general-provision line printed only for FY2026 Enacted (the JES and H.Rept. 119-696 p.392, 2,000; '---' in the FY2027 columns). The provision of P.L. 119-75 it reflects is not identified here -- the Title II general provisions carry no section naming title XVIII with that figure; to be confirmed. Vision read H.Rept. 119-696's label as 'mitation ...' (the page image prints 'Limitation ...'). | L55: Title II | M55: 24
A56: ACC-HHS-TITLE-II-TOTAL | B56: Title II, Department of Health and Human Services (title total) | C56: Department of Health and Human Services | D56: (Title Total) | F56: active | I56: general | J56: LHHS | K56: Derived rollup -- the Title II title total as printed. Reconciles as the ten agency totals (eleven in the FY2026-27 requests, with AHA) + General Provisions lines (signed) - the CURES Act line, in all 16 printed columns (reference/review/lhhs/title_ii_totals.py); in the store, through the agency-total rollups and the four General Provisions accounts, in all 13 recorded cells. The House counts the HHS rescissions (NEF, Adoption Incentives) in Title II's general provisions; the Senate prints them after the grand total, outside Title II -- so the two FY2024 figures differ by 1,320,000 as printed. | L56: Title II | M56: 25 | N56: title
A57: ACC-HHS-HRSA-HEALTH-WORKFORCE | B57: Health Workforce | C57: Health Resources and Services Administration | D57: Health Workforce | F57: active | I57: general | J57: LHHS | L57: Title II | M57: 26
A58: ACC-HHS-HRSA-MCH | B58: Maternal and Child Health | C58: Health Resources and Services Administration | D58: Maternal and Child Health | F58: active | I58: general | J58: LHHS | L58: Title II | M58: 27
A59: ACC-HHS-HRSA-RYAN-WHITE | B59: Ryan White HIV/AIDS Program | C59: Health Resources and Services Administration | D59: Ryan White HIV/AIDS Program | F59: active | I59: general | J59: LHHS | L59: Title II | M59: 28
A60: ACC-HHS-HRSA-HEALTH-SYSTEMS | B60: Health Systems | C60: Health Resources and Services Administration | D60: Health Systems | F60: active | I60: general | J60: LHHS | L60: Title II | M60: 29
A61: ACC-HHS-HRSA-RURAL-HEALTH | B61: Rural Health | C61: Health Resources and Services Administration | D61: Rural Health | F61: active | I61: general | J61: LHHS | L61: Title II | M61: 30
A62: ACC-HHS-HRSA-FAMILY-PLANNING | B62: Family Planning | C62: Health Resources and Services Administration | D62: Family Planning | F62: active | I62: general | J62: LHHS | K62: No heading in the FY2027 House bill (the House proposes no Title X funding); enacted every year FY2023-FY2026. | L62: Title II | M62: 31
A63: ACC-HHS-HRSA-PROGRAM-SUPPORT | B63: HRSA-Wide Activities and Program Support | C63: Health Resources and Services Administration | D63: HRSA-Wide Activities and Program Support | F63: active | I63: general | J63: LHHS | L63: Title II | M63: 32
A64: ACC-HHS-HRSA-CCPF | B64: Covered Countermeasures Process Fund | C64: Health Resources and Services Administration | D64: Covered Countermeasures Process Fund | F64: inactive | I64: general | J64: LHHS | K64: Heading in P.L. 117-328 (FY2023) and P.L. 118-47 (FY2024) only (FY2025 continued by P.L. 119-4); none in P.L. 119-75 or the FY2027 House bill. The FY2023 tables print it as 'Countermeasures Injury Compensation Trust Fund'. | L64: Title II | M64: 33
A65: ACC-HHS-CDC-IMMUNIZATION | B65: Immunization and Respiratory Diseases | C65: Centers for Disease Control and Prevention | D65: Immunization and Respiratory Diseases | F65: active | I65: general | J65: LHHS | L65: Title II | M65: 34
A66: ACC-HHS-CDC-HIV-HEPATITIS-STD-TB | B66: HIV/AIDS, Viral Hepatitis, Sexually Transmitted Diseases, and Tuberculosis Prevention | C66: Centers for Disease Control and Prevention | D66: HIV/AIDS, Viral Hepatitis, Sexually Transmitted Diseases, and Tuberculosis Prevention | F66: active | I66: general | J66: LHHS | L66: Title II | M66: 35
A67: ACC-HHS-CDC-EMERGING-ZOONOTIC | B67: Emerging and Zoonotic Infectious Diseases | C67: Centers for Disease Control and Prevention | D67: Emerging and Zoonotic Infectious Diseases | F67: active | I67: general | J67: LHHS | L67: Title II | M67: 36
A68: ACC-HHS-CDC-CHRONIC-DISEASE | B68: Chronic Disease Prevention and Health Promotion | C68: Centers for Disease Control and Prevention | D68: Chronic Disease Prevention and Health Promotion | F68: active | I68: general | J68: LHHS | L68: Title II | M68: 37
A69: ACC-HHS-CDC-BIRTH-DEFECTS | B69: Birth Defects, Developmental Disabilities, Disabilities and Health | C69: Centers for Disease Control and Prevention | D69: Birth Defects, Developmental Disabilities, Disabilities and Health | F69: active | I69: general | J69: LHHS | L69: Title II | M69: 38
A70: ACC-HHS-CDC-SCIENTIFIC-SERVICES | B70: Public Health Scientific Services | C70: Centers for Disease Control and Prevention | D70: Public Health Scientific Services | F70: active | I70: general | J70: LHHS | L70: Title II | M70: 39
A71: ACC-HHS-CDC-ENVIRONMENTAL-HEALTH | B71: Environmental Health | C71: Centers for Disease Control and Prevention | D71: Environmental Health | F71: active | I71: general | J71: LHHS | L71: Title II | M71: 40
A72: ACC-HHS-CDC-INJURY-PREVENTION | B72: Injury Prevention and Control | C72: Centers for Disease Control and Prevention | D72: Injury Prevention and Control | F72: active | I72: general | J72: LHHS | L72: Title II | M72: 41
A73: ACC-HHS-CDC-NIOSH | B73: National Institute for Occupational Safety and Health | C73: Centers for Disease Control and Prevention | D73: National Institute for Occupational Safety and Health | F73: active | I73: general | J73: LHHS | L73: Title II | M73: 42
A74: ACC-HHS-CDC-EEOICP | B74: Energy Employees Occupational Illness Compensation Program | C74: Centers for Disease Control and Prevention | D74: Energy Employees Occupational Illness Compensation Program | F74: active | I74: general | J74: LHHS | L74: Title II | M74: 43
A75: ACC-HHS-CDC-GLOBAL-HEALTH | B75: Global Health | C75: Centers for Disease Control and Prevention | D75: Global Health | F75: active | I75: general | J75: LHHS | L75: Title II | M75: 44
A76: ACC-HHS-CDC-PREPAREDNESS | B76: Public Health Preparedness and Response | C76: Centers for Disease Control and Prevention | D76: Public Health Preparedness and Response | F76: active | I76: general | J76: LHHS | L76: Title II | M76: 45
... A86: ACC-HHS-NIH-NEI | B86: National Eye Institute | C86: National Institutes of Health | D86: National Eye Institute | F86: active | I86: general | J86: LHHS | L86: Title II | M86: 55
A87: ACC-HHS-NIH-NIEHS | B87: National Institute of Environmental Health Sciences | C87: National Institutes of Health | D87: National Institute of Environmental Health Sciences | F87: active | I87: general | J87: LHHS | K87: FY2026 request moves it to the Administration for a Healthy America (REL-LHHS-0011: FY2026 AHA Congressional Justification p.13, 'National Institute of Environmental Health Sciences (NIEHS): $594.1 million' = H.Rept. 119-271 p.344 FY 2026 Request 594,086; with its Superfund-related activities, $51.8M, p.14). FY2027 request moves it to CDC (FY2027 Budget Appendix) -- a placement note only: no specific receiving account. Neither move enacted; P.L. 119-75 keeps NIEHS under NIH. | L87: Title II | M87: 56
A88: ACC-HHS-NIH-NIA | B88: National Institute on Aging | C88: National Institutes of Health | D88: National Institute on Aging | F88: active | I88: general | J88: LHHS | L88: Title II | M88: 57
A89: ACC-HHS-NIH-NIAMS | B89: National Institute of Arthritis and Musculoskeletal and Skin Diseases | C89: National Institutes of Health | D89: National Institute of Arthritis and Musculoskeletal and Skin Diseases | F89: active | I89: general | J89: LHHS | L89: Title II | M89: 58
A90: ACC-HHS-NIH-NIDCD | B90: National Institute on Deafness and Other Communication Disorders | C90: National Institutes of Health | D90: National Institute on Deafness and Other Communication Disorders | F90: active | I90: general | J90: LHHS | L90: Title II | M90: 59
A91: ACC-HHS-NIH-NINR | B91: National Institute of Nursing Research | C91: National Institutes of Health | D91: National Institute of Nursing Research | F91: active | I91: general | J91: LHHS | L91: Title II | M91: 60
A92: ACC-HHS-NIH-NIAAA | B92: National Institute on Alcohol Abuse and Alcoholism | C92: National Institutes of Health | D92: National Institute on Alcohol Abuse and Alcoholism | F92: active | G92: National Institute on Alcohol Effects and Alcohol-Related Disorders | I92: general | J92: LHHS | K92: FY2027 request consolidates it with NIDA into the National Institute of Substance Use and Addiction Research (relationship below). FY2023 House bill renamed it; not enacted. | L92: Title II | M92: 61
A93: ACC-HHS-NIH-NIDA | B93: National Institute on Drug Abuse | C93: National Institutes of Health | D93: National Institute on Drug Abuse | F93: active | G93: National Institute on Drugs and Addiction | I93: general | J93: LHHS | K93: As NIAAA. | L93: Title II | M93: 62
A94: ACC-HHS-NIH-NIMH | B94: National Institute of Mental Health | C94: National Institutes of Health | D94: National Institute of Mental Health | F94: active | I94: general | J94: LHHS | L94: Title II | M94: 63
A95: ACC-HHS-NIH-NHGRI | B95: National Human Genome Research Institute | C95: National Institutes of Health | D95: National Human Genome Research Institute | F95: active | I95: general | J95: LHHS | L95: Title II | M95: 64
A96: ACC-HHS-NIH-NIBIB | B96: National Institute of Biomedical Imaging and Bioengineering | C96: National Institutes of Health | D96: National Institute of Biomedical Imaging and Bioengineering | F96: active | I96: general | J96: LHHS | L96: Title II | M96: 65
A97: ACC-HHS-NIH-NCCIH | B97: National Center for Complementary and Integrative Health | C97: National Institutes of Health | D97: National Center for Complementary and Integrative Health | F97: active | I97: general | J97: LHHS | L97: Title II | M97: 66
A98: ACC-HHS-NIH-NIMHD | B98: National Institute on Minority Health and Health Disparities | C98: National Institutes of Health | D98: National Institute on Minority Health and Health Disparities | F98: active | I98: general | J98: LHHS | L98: Title II | M98: 67
A99: ACC-HHS-NIH-FIC | B99: John E. Fogarty International Center | C99: National Institutes of Health | D99: John E. Fogarty International Center | F99: active | I99: general | J99: LHHS | L99: Title II | M99: 68
A100: ACC-HHS-NIH-NLM | B100: National Library of Medicine | C100: National Institutes of Health | D100: National Library of Medicine | F100: active | I100: general | J100: LHHS | L100: Title II | M100: 69
A101: ACC-HHS-NIH-NCATS | B101: National Center for Advancing Translational Sciences | C101: National Institutes of Health | D101: National Center for Advancing Translational Sciences | F101: active | I101: general | J101: LHHS | L101: Title II | M101: 70
A102: ACC-HHS-NIH-OD | B102: Office of the Director | C102: National Institutes of Health | D102: Office of the Director | F102: active | I102: general | J102: LHHS | L102: Title II | M102: 71
A103: ACC-HHS-NIH-BUILDINGS-FACILITIES | B103: Buildings and Facilities | C103: National Institutes of Health | D103: Buildings and Facilities | F103: active | I103: general | J103: LHHS | L103: Title II | M103: 72
A104: ACC-HHS-NIH-ARPA-H | B104: Advanced Research Projects Agency for Health | C104: National Institutes of Health | D104: Advanced Research Projects Agency for Health | F104: active | I104: general | J104: LHHS | K104: One account under NIH. P.L. 117-328 (FY2023) places the heading under the Office of the Secretary (p.420), and H.Rept. 117-403's Bill column prints it there ('Advanced Research Projects', OS); from P.L. 118-47 (FY2024, p.202) it is under NIH. Each document is reconciled by its own printed grouping. NIH's printed totals include it (v32's view 'program_level_excluding_arpa_h' was NIH's total less it). | L104: Title II | M104: 73
A105: ACC-HHS-NIH-BODY-SYSTEMS | B105: National Institute on Body Systems Research | C105: National Institutes of Health | D105: National Institute on Body Systems Research | F105: proposed | I105: general | J105: LHHS | K105: FY2026 request only: H.Rept. 119-271 p.343 request column 4,152,062 (FY 2025 Estimate '---'); FY2026 Budget Appendix line 0032 'National Institute on Body Systems' 4,152 (BUDGET-2026-APP HHS chapter PDF p.26). | L105: Title II | M105: 74
A106: ACC-HHS-NIH-NEUROSCIENCE | B106: National Institute on Neuroscience and Brain Research | C106: National Institutes of Health | D106: National Institute on Neuroscience and Brain Research | F106: proposed | I106: general | J106: LHHS | K106: FY2026 request only: H.Rept. 119-271 request column 2,347,472; Appendix line 0033 2,445. | L106: Title II | M106: 75
A107: ACC-HHS-NIH-CHILD-WOMEN-SENSORY | B107: National Institute for Child and Women's Health, Sensory Disorders and Communication | C107: National Institutes of Health | D107: National Institute for Child and Women's Health, Sensory Disorders and Communication | F107: proposed | I107: general | J107: LHHS | K107: FY2026 request only: H.Rept. 119-271 request column 1,413,630; Appendix line 0035 1,414. | L107: Title II | M107: 76
A108: ACC-HHS-NIH-BEHAVIORAL-HEALTH | B108: National Institute of Behavioral Health | C108: National Institutes of Health | D108: National Institute of Behavioral Health | F108: proposed | I108: general | J108: LHHS | K108: FY2026 request only: H.Rept. 119-271 request column 2,687,238; Appendix line 0036 2,785. | L108: Title II | M108: 77
A109: ACC-HHS-NIH-SUBSTANCE-USE | B109: National Institute of Substance Use and Addiction Research | C109: National Institutes of Health | D109: National Institute of Substance Use and Addiction Research | F109: proposed | I109: general | J109: LHHS | K109: FY2027 request only: H.Rept. 119-696 p.375 request column 2,097,238 (NIDA and NIAAA '---'); FY2027 Budget Appendix line 0032. | L109: Title II | M109: 78
...

Sheet Historical Name
A1: historical_name_id | B1: canonical_account_id | C1: former_name | D1: evidence | E1: approved_date | F1: confidence | G1: human_reviewed
A2: HN-0001 | B2: ACC-NASA-EXPLORATION | C2: Deep Space Exploration Systems | D2: Printed for this account in S.Rept. 118-62 (FY2024 Senate Reported) p.219 and the FY2024 CJS conference JES Title III table; the pilot records those FY2024 figures under ACC-NASA-EXPLORATION. Also printed as the Budget Estimate column label (not the chamber's own recommendation) in H.Rept. 115-704 p.128 (FY2019), S.Rept. 115-275 p.157 (FY2019), H.Rept. 116-101 p.148 (FY2020), S.Rept. 116-127 p.191 (FY2020), and S.Rept. 118-198 p.227 (which also prints the '(emergency)' line). | E2: 2026-09-25 | F2: 1 | G2: TRUE
A3: HN-0002 | B3: ACC-NSF-STEM-EDUCATION | C3: Education and Human Resources | D3: Printed for this account in S.Rept. 118-62 (FY2024 Senate Reported) p.220 and the FY2024 CJS conference JES Title III table; the pilot records those FY2024 figures under ACC-NSF-STEM-EDUCATION. | E3: 2026-09-25 | F3: 1 | G3: TRUE
A4: HN-0003 | B4: ACC-NASA-SPACEOPS | C4: LEO and Spaceflight Operations | D4: Printed in place of 'Space Operations' in H.Rept. 115-704 p.128 (FY2019 House Reported and President's Budget columns) and, in the Budget Estimate column only (never as the chamber's own recommendation), in S.Rept. 115-275 p.157 (FY2019) and S.Rept. 116-127 p.191 (FY2020, alongside H.Rept. 116-101 p.148). Never adopted as any chamber's own committee recommendation or in Enacted. | E4: 2026-09-25 | F4: 1 | G4: TRUE
A5: HN-0005 | B5: ACC-NASA-STEM-ENGAGEMENT | C5: Education | D5: The account's own name through FY2018, not a FY2019 variant. Printed in S.Rept. 114-239 p.139 (FY2017), S.Rept. 115-139 p.140 (FY2018), H.Rept. 115-231 p.121 (FY2018: 100,000 / 37,300 / 90,000), and H.Rept. 115-704 p.128 (FY2019 table's prior-year-enacted column: 100,000). | E5: 2026-09-25 | F5: 1 | G5: TRUE
A6: HN-0006 | B6: ACC-NASA-STEM-ENGAGEMENT | C6: STEM Opportunities formerly Education | D6: Printed in S.Rept. 115-275 p.157 (FY2019: 2018 appropriation 100,000 / budget estimate blank / committee recommendation 110,000). | E6: 2026-09-25 | F6: 1 | G6: TRUE
A7: HN-0007 | B7: ACC-NASA-SPACETECH | C7: Exploration Research and Technology | D7: FY2019 Budget Appendix: the FY2019 budget request 'renames the Space Operations, Exploration, and Space Technology accounts as LEO and Spaceflight Operations, Deep Space Exploration Systems, and Exploration Research and Technology' -- account code 080-0131 matches Space Technology's own code. Printed for this account in H.Rept. 115-704 p.128 and S.Rept. 115-275 p.157 (FY2019). | E7: 2026-09-25 | F7: 1 | G7: TRUE
A8: HN-0008 | B8: ACC-NASA-SPACETECH | C8: Exploration Technology | D8: Same FY2019 rename proposal, FY2020 printed form. H.Rept. 116-101 p.148, S.Rept. 116-127 p.191 (FY2020). | E8: 2026-09-25 | F8: 1 | G8: TRUE
A9: HN-LHHS-0001 | B9: ACC-HHS-NIH-NIAAA | C9: National Institute on Alcohol Effects and Alcohol-Related Disorders | D9: FY2023 House: H.R. 8295 (reported) Title II heading and H.Rept. 117-403 Title II table p.815 (PDF), 'National Institute on Alcohol Effects and Alcohol-Related Disorders (NIAAA)'; also the FY2023 Senate draft explanatory statement's table. A proposed rename, not enacted: P.L. 117-328 and later laws keep 'National Institute on Alcohol Abuse and Alcoholism'. | F9: 0.95 | G9: FALSE
A10: HN-LHHS-0002 | B10: ACC-HHS-NIH-NIDA | C10: National Institute on Drugs and Addiction | D10: FY2023 House: H.R. 8295 (reported) Title II heading and H.Rept. 117-403 p.815 (PDF), 'National Institute on Drugs and Addiction (NIDA)'. A proposed rename, not enacted: P.L. 117-328 and later laws keep 'National Institute on Drug Abuse'. | F10: 0.95 | G10: FALSE
A11: HN-LHHS-0003 | B11: ACC-HHS-SAMHSA-TREATMENT | C11: Substance Use Services | D11: FY2023 House: H.Rept. 117-403 p.818 (PDF) section 'Substance Use Services' and 'Subtotal, Substance Use Services, appropriation'; the FY2023 Senate draft prints the same. P.L. 117-328 and later laws keep the heading 'Substance Abuse Treatment'. | F11: 0.95 | G11: FALSE
A12: HN-LHHS-0004 | B12: ACC-HHS-SAMHSA-PREVENTION | C12: Substance Use Prevention Services | D12: FY2023 House: H.Rept. 117-403 p.819 (PDF) 'Total, Substance Use Prevention Services, appropriation'; the FY2023 Senate draft prints the same. P.L. 117-328 and later laws keep the heading 'Substance Abuse Prevention'. | F12: 0.95 | G12: FALSE

Sheet Confirmed Absence
A1: confirmed_absence_id | B1: canonical_account_id | C1: fiscal_year | D1: stage | E1: amount_type | F1: component | G1: source_document_id | H1: evidence | I1: confirmed_date
A2: CA-0001 | B2: ACC-NASA-CONSTRUCTION | C2: 2017 | D2: President's Budget | E2: supplemental | G2: SRC-CRPT-114HRPT605 | H2: No Construction and environmental compliance and restoration (emergency) line anywhere in the comparative table (pp.106-118: Title III, Title V General Provisions and any Other Appropriations sections) for FY2017 President's Budget; read by OCR of every table page; Title III pp.114-115 read from the page images | I2: 2026-09-25
A3: CA-0002 | B3: ACC-NASA-CONSTRUCTION | C3: 2017 | D3: House Reported | E3: supplemental | G3: SRC-CRPT-114HRPT605 | H3: No Construction and environmental compliance and restoration (emergency) line anywhere in the comparative table (pp.106-118: Title III, Title V General Provisions and any Other Appropriations sections) for FY2017 House Reported; read by OCR of every table page; Title III pp.114-115 read from the page images | I3: 2026-09-25
A4: CA-0003 | B4: ACC-NASA-CONSTRUCTION | C4: 2017 | D4: Senate Reported | E4: supplemental | G4: SRC-CRPT-114SRPT239 | H4: No Construction and environmental compliance and restoration (emergency) line anywhere in the comparative table (pp.134-141: Title III, Title V General Provisions and any Other Appropriations sections) for FY2017 Senate Reported; read by text layer | I4: 2026-09-25
A5: CA-0004 | B5: ACC-NASA-CONSTRUCTION | C5: 2018 | D5: President's Budget | E5: supplemental | G5: SRC-CRPT-115HRPT231 | H5: No Construction and environmental compliance and restoration (emergency) line anywhere in the comparative table (pp.111-124: Title III, Title V General Provisions and any Other Appropriations sections) for FY2018 President's Budget; read by OCR of every table page; Title III pp.120-121 read from the page images | I5: 2026-09-25
A6: CA-0005 | B6: ACC-NASA-CONSTRUCTION | C6: 2018 | D6: House Reported | E6: supplemental | G6: SRC-CRPT-115HRPT231 | H6: No Construction and environmental compliance and restoration (emergency) line anywhere in the comparative table (pp.111-124: Title III, Title V General Provisions and any Other Appropriations sections) for FY2018 House Reported; read by OCR of every table page; Title III pp.120-121 read from the page images | I6: 2026-09-25
A7: CA-0006 | B7: ACC-NASA-CONSTRUCTION | C7: 2018 | D7: Senate Reported | E7: supplemental | G7: SRC-CRPT-115SRPT139 | H7: No Construction and environmental compliance and restoration (emergency) line anywhere in the comparative table (pp.135-143: Title III, Title V General Provisions and any Other Appropriations sections) for FY2018 Senate Reported; read by text layer | I7: 2026-09-25
A8: CA-0007 | B8: ACC-NASA-CONSTRUCTION | C8: 2019 | D8: President's Budget | E8: supplemental | G8: SRC-CRPT-115HRPT704 | H8: No Construction and environmental compliance and restoration (emergency) line anywhere in the comparative table (pp.120-135: Title III, Title V General Provisions and any Other Appropriations sections) for FY2019 President's Budget; read by OCR of every table page; Title III pp.128-129 read from the page images | I8: 2026-09-25
A9: CA-0008 | B9: ACC-NASA-CONSTRUCTION | C9: 2019 | D9: House Reported | E9: supplemental | G9: SRC-CRPT-115HRPT704 | H9: No Construction and environmental compliance and restoration (emergency) line anywhere in the comparative table (pp.120-135: Title III, Title V General Provisions and any Other Appropriations sections) for FY2019 House Reported; read by OCR of every table page; Title III pp.128-129 read from the page images | I9: 2026-09-25
A10: CA-0009 | B10: ACC-NASA-CONSTRUCTION | C10: 2019 | D10: Senate Reported | E10: supplemental | G10: SRC-CRPT-115SRPT275 | H10: the only Construction and Environmental Compliance and Restoration (emergency) line (p.161, P.L. 115-123 section) prints a figure in the 2018 appropriation column only; its Committee recommendation cell is blank (text layer); no other Construction and environmental compliance and restoration (emergency) line in the table (pp.152-161) | I10: 2026-09-25
A11: CA-0010 | B11: ACC-NASA-CONSTRUCTION | C11: 2019 | D11: Enacted | E11: supplemental | G11: SRC-CRPT-116HRPT101 | H11: No Construction and environmental compliance and restoration (emergency) line anywhere in the comparative table (pp.139-152: Title III, Title V General Provisions and any Other Appropriations sections) for FY2019 Enacted; read by OCR of every table page; Title III pp.148-149 read from the page images | I11: 2026-09-25
A12: CA-0011 | B12: ACC-NASA-CONSTRUCTION | C12: 2020 | D12: President's Budget | E12: supplemental | G12: SRC-CRPT-116HRPT101 | H12: No Construction and environmental compliance and restoration (emergency) line anywhere in the comparative table (pp.139-152: Title III, Title V General Provisions and any Other Appropriations sections) for FY2020 President's Budget; read by OCR of every table page; Title III pp.148-149 read from the page images | I12: 2026-09-25
A13: CA-0012 | B13: ACC-NASA-CONSTRUCTION | C13: 2020 | D13: House Reported | E13: supplemental | G13: SRC-CRPT-116HRPT101 | H13: No Construction and environmental compliance and restoration (emergency) line anywhere in the comparative table (pp.139-152: Title III, Title V General Provisions and any Other Appropriations sections) for FY2020 House Reported; read by OCR of every table page; Title III pp.148-149 read from the page images | I13: 2026-09-25
... A222: CA-LHHS-0024 | B222: ACC-HHS-GP-ADOPTION-INCENTIVES-RESCISSION | C222: 2025 | D222: Enacted | E222: rescission | G222: SRC-PLAW-119PUBL4 | H222: P.L. 119-4 (Full-Year Continuing Appropriations Act, 2025, division A) provides no Adoption Incentives rescission for FY2025. Deciding text, sec. 1101(a)(8) (139 Stat. 11; PDF p. 3; text layer): it continues 'The Departments of Labor, Health and Human Services, and Education, and Related Agencies Appropriations Act, 2024 (division D of Public Law 118-47), except section 240 shall be applied by substituting "$1,471,000,000" for "$1,250,000,000" ..., except sections 241 and 310, ...'. Section 241 of that division (P.L. 118-47, 138 Stat. 681) is the FY2024 rescission of $70,000,000 of P.L. 117-328 Children and Families Services Programs funds 'for grants to States for incentive payments, as defined by section 473A of the Social Security Act' -- the line the FY2024 tables print as 'Adoption Incentives (rescission)' -70,000. Sec. 1105 continues the referenced Acts' provisions only 'Except as otherwise expressly provided in this division'. The Labor-HHS title of the CR (title IX, secs. 1901-1912, 139 Stat. 31-33) adds no such rescission, and the whole law's text layer has no 'adoption', '473A' or 'incentive payments'. No committee table covers FY2025 Enacted (H.Rept. 119-271's 'FY 2025 Estimate' column is operating plans, held back). | I222: 2026-10-06
A223: CA-LHHS-0025 | B223: ACC-HHS-GP-NEF-RESCISSION | C223: 2025 | D223: Enacted | E223: rescission | F223: emergency | G223: SRC-CRPT-119HRPT271 | H223: No 'Nonrecurring expenses fund, HHS (rescission) (emergency)' line in H.Rept. 119-271's FY 2025 Estimate column. Searched: the whole Title II comparative table, PDF pp. 334-366 (printed pp. 330-362); the table pages have no text layer and were read from the page images (every row transcribed by vision). Title II General Provisions, PDF p. 365 (printed p. 361), FY 2025 Estimate column: Medicare Operations (Sec. 226) 455,000 and Nonrecurring expenses fund, HHS (rescission) (Sec. 234) -1,471,000, with 'Total, Title II General Provisions' -1,016,000 equal to those two lines. P.L. 119-4 sec. 1101(a)(8) continues Div. D sec. 240 except for 'amounts that were previously designated by the Congress as being for an emergency requirement'. The column is the report's 'FY 2025 Operating Plans and other available information' (pp.319-320); FY2025 was a full-year CR (P.L. 119-4). | I223: 2026-10-07
A224: CA-LHHS-0028 | B224: ACC-HHS-CMS-MEDICAID | C224: 2023 | D224: President's Budget | E224: budget authority | G224: SRC-CRPT-117HRPT403 | H224: No row for this account's headline figure ('Total, Grants to States for Medicaid') in H.Rept.117-403 Title II table pp. 802-838 (PDF; printed pp. 798-834, read by vision) for FY2023 President's Budget. The document prints only 'Total, Grants to States for Medicaid, appropriated in this bill' 564,937,564 (p.821); 'Total, Medicaid Program Level, available this fiscal year' 533,079,108 (p.821) -- not recorded: each is another scope of the headline (component kind 'view'), which needs the headline it is a view of. | I224: 2026-10-06
A225: CA-LHHS-0029 | B225: ACC-HHS-CMS-MEDICAID | C225: 2023 | D225: House Reported | E225: budget authority | G225: SRC-CRPT-117HRPT403 | H225: No row for this account's headline figure ('Total, Grants to States for Medicaid') in H.Rept.117-403 Title II table pp. 802-838 (PDF; printed pp. 798-834, read by vision) for FY2023 House Reported. The document prints only 'Total, Grants to States for Medicaid, appropriated in this bill' 564,937,564 (p.821); 'Total, Medicaid Program Level, available this fiscal year' 533,079,108 (p.821) -- not recorded: each is another scope of the headline (component kind 'view'), which needs the headline it is a view of. | I225: 2026-10-06
A226: CA-LHHS-0030 | B226: ACC-HHS-ASPR-TOTAL | C226: 2023 | D226: President's Budget | E226: budget authority | G226: SRC-CRPT-117HRPT403 | H226: No row for this account's headline figure ('Total, Administration for Strategic Preparedness and Response') in H.Rept.117-403 Title II table pp. 802-838 (PDF; printed pp. 798-834, read by vision) for FY2023 President's Budget. The report has no ASPR operating division: the preparedness programs (BARDA, Strategic National Stockpile, Project BioShield, Pandemic Influenza) print under the Office of the Secretary's Public Health and Social Services Emergency Fund, whose total also holds non-ASPR lines (Cybersecurity, Office of National Security, OASH): 'Total, PHSSEF' 3,814,610 (p.836) -- a different scope, not recorded. | I226: 2026-10-06
A227: CA-LHHS-0031 | B227: ACC-HHS-ASPR-TOTAL | C227: 2023 | D227: House Reported | E227: budget authority | G227: SRC-CRPT-117HRPT403 | H227: No row for this account's headline figure ('Total, Administration for Strategic Preparedness and Response') in H.Rept.117-403 Title II table pp. 802-838 (PDF; printed pp. 798-834, read by vision) for FY2023 House Reported. The report has no ASPR operating division: the preparedness programs (BARDA, Strategic National Stockpile, Project BioShield, Pandemic Influenza) print under the Office of the Secretary's Public Health and Social Services Emergency Fund, whose total also holds non-ASPR lines (Cybersecurity, Office of National Security, OASH): 'Total, PHSSEF' 3,699,356 (p.836) -- a different scope, not recorded. | I227: 2026-10-06
A228: CA-LHHS-0032 | B228: ACC-HHS-CMS-MEDICAID | C228: 2023 | D228: Senate Reported | E228: budget authority | G228: SRC-EXPL-LHHS-FY2023-SENATE | H228: No row for this account's headline figure ('Total, Grants to States for Medicaid') in the Senate draft explanatory statement's Title II table pp. 399-419 (text layer) for FY2023 Senate Reported. The document prints only 'Total, Medicaid Program Level, available this fiscal year' 533,079,108 (p.409); 'Total, Grants to States for Medicaid, appropriated in this bill' 564,937,564 (p.409) -- not recorded: each is another scope of the headline (component kind 'view'), which needs the headline it is a view of. | I228: 2026-10-06
A229: CA-LHHS-0033 | B229: ACC-HHS-ASPR-TOTAL | C229: 2023 | D229: Senate Reported | E229: budget authority | G229: SRC-EXPL-LHHS-FY2023-SENATE | H229: No row for this account's headline figure ('Total, Administration for Strategic Preparedness and Response') in the Senate draft explanatory statement's Title II table pp. 399-419 (text layer) for FY2023 Senate Reported. The document prints only no ASPR operating division: the preparedness programs (BARDA, Strategic National Stockpile, Project BioShield, Pandemic Influenza) print under the Office of the Secretary's Public Health and Social Services Emergency Fund ('Total, PHSSEF' 3,639,479, p.419), whose total also holds non-ASPR lines -- a different scope, not recorded. | I229: 2026-10-06
A230: CA-LHHS-0034 | B230: ACC-HHS-GP-MEDICARE-OPERATIONS | C230: 2023 | D230: Senate Reported | E230: budget authority | G230: SRC-EXPL-LHHS-FY2023-SENATE | H230: No 'Medicare Operations (Sec. nnn)' line anywhere in the Senate draft explanatory statement for FY2023 (whole text layer, 437 pages, searched for /Medicare Operations|Traditional Medicare Program/; the Title II table pp. 399-419 and the table's end p.437 included). | I230: 2026-10-06
A231: CA-LHHS-0035 | B231: ACC-HHS-GP-ADOPTION-INCENTIVES-RESCISSION | C231: 2023 | D231: Senate Reported | E231: rescission | G231: SRC-EXPL-LHHS-FY2023-SENATE | H231: No 'Adoption Incentives (rescission)' line anywhere in the Senate draft explanatory statement for FY2023 (whole text layer, 437 pages, searched for /Adoption Incentives \(rescission/; the Title II table pp. 399-419 and the table's end p.437 included). | I231: 2026-10-06
A232: CA-LHHS-0036 | B232: ACC-HHS-GP-MEDICARE-LIMITATION | C232: 2023 | D232: Senate Reported | E232: budget authority | G232: SRC-EXPL-LHHS-FY2023-SENATE | H232: No 'Limitation for Title XVIII of the Social Security Act' line anywhere in the Senate draft explanatory statement for FY2023 (whole text layer, 437 pages, searched for /Title XVIII/; the Title II table pp. 399-419 and the table's end p.437 included). | I232: 2026-10-06
A233: CA-LHHS-0037 | B233: ACC-HHS-CDC-PROGRAM-SUPPORT | C233: 2023 | D233: President's Budget | E233: budget authority | G233: SRC-CRPT-117HRPT403 | H233: No budget-authority row for 'CDC-Wide Activities and Program Support' in the Title II table (PDF p.813) for FY2023 President's Budget: the section prints its lines and a parenthesized 'Subtotal' that includes the Prevention and Public Health Fund transfer (program level) -- not recorded. | I233: 2026-10-06
A234: CA-LHHS-0038 | B234: ACC-HHS-CDC-PROGRAM-SUPPORT | C234: 2023 | D234: House Reported | E234: budget authority | G234: SRC-CRPT-117HRPT403 | H234: No budget-authority row for 'CDC-Wide Activities and Program Support' in the Title II table (PDF p.813) for FY2023 House Reported: the section prints its lines and a parenthesized 'Subtotal' that includes the Prevention and Public Health Fund transfer (program level) -- not recorded. | I234: 2026-10-06
A235: CA-LHHS-0039 | B235: ACC-HHS-CDC-PROGRAM-SUPPORT | C235: 2023 | D235: Senate Reported | E235: budget authority | G235: SRC-EXPL-LHHS-FY2023-SENATE | H235: No budget-authority row for 'CDC-Wide Activities and Program Support' in the Title II table (PDF p.405) for FY2023 Senate Reported: the section prints its lines and a parenthesized 'Subtotal' that includes the Prevention and Public Health Fund transfer (program level) -- not recorded. | I235: 2026-10-06

Sheet Appropriations Observation
A1: observation_id | B1: canonical_account_id | C1: fiscal_year | D1: stage | E1: chamber | F1: bill_id | G1: report_id | H1: amount | I1: amount_type | J1: component | K1: offsetting_collections | L1: transfer_link_account_id | M1: source_document_id | N1: source_page | O1: source_table_or_section | P1: extraction_method | Q1: confidence | R1: verification_status | S1: bill_url | T1: report_jes_url | U1: headline_observation_id
A2: OBS-0001 | B2: ACC-OSTP | C2: 2026 | D2: Enacted | E2: N/A | F2: =IFERROR(""&INDEX('Bill Report Reference'!$E$2:$E$59,MATCH(INDEX(Account!$J$2:$J$131,MATCH($B2,Account!$A$2:$A$131,0))&"-"&$C2&"-"&$D2,'Bill Report Reference'!$I$2:$I$59,0)),"") -> P.L.119-74 | G2: =IFERROR(""&INDEX('Bill Report Reference'!$F$2:$F$59,MATCH(INDEX(Account!$J$2:$J$131,MATCH($B2,Account!$A$2:$A$131,0))&"-"&$C2&"-"&$D2,'Bill Report Reference'!$I$2:$I$59,0)),"") -> JES_CJS_P.L.119-74 | H2: 7965000 | I2: budget authority | K2: FALSE | M2: SRC-EXPL-FY2026-PB | N2: 128-130 | O2: Title III, Executive Office of the President, Office of Science and Technology Policy | P2: human-entered | Q2: 1 | R2: human-verified | S2: =IFERROR(""&INDEX('Bill Report Reference'!$G$2:$G$59,MATCH(INDEX(Account!$J$2:$J$131,MATCH($B2,Account!$A$2:$A$131,0))&"-"&$C2&"-"&$D2,'Bill Report Reference'!$I$2:$I$59,0)),"") -> https://www.govinfo.gov/content/pkg/PLAW-119publ74/pdf/PLAW-119publ74.pdf | T2: =IFERROR(""&INDEX('Bill Report Reference'!$H$2:$H$59,MATCH(INDEX(Account!$J$2:$J$131,MATCH($B2,Account!$A$2:$A$131,0))&"-"&$C2&"-"&$D2,'Bill Report Reference'!$I$2:$I$59,0)),"") -> https://rules.house.gov/sites/evo-subsites/rules.house.gov/files/documents/division-a-commerce-justice-science_0.pdf
A3: OBS-0002 | B3: ACC-OSTP | C3: 2026 | D3: Senate Reported | E3: Senate | F3: =IFERROR(""&INDEX('Bill Report Reference'!$E$2:$E$59,MATCH(INDEX(Account!$J$2:$J$131,MATCH($B3,Account!$A$2:$A$131,0))&"-"&$C3&"-"&$D3,'Bill Report Reference'!$I$2:$I$59,0)),"") -> S.2354 | G3: =IFERROR(""&INDEX('Bill Report Reference'!$F$2:$F$59,MATCH(INDEX(Account!$J$2:$J$131,MATCH($B3,Account!$A$2:$A$131,0))&"-"&$C3&"-"&$D3,'Bill Report Reference'!$I$2:$I$59,0)),"") -> S.Rept.119-44 | H3: 7965000 | I3: budget authority | K3: FALSE | M3: SRC-CRPT-119SRPT44 | N3: 217-219 | O3: Title III, Executive Office of the President, Office of Science and Technology Policy | P3: human-entered | Q3: 1 | R3: human-verified | S3: =IFERROR(""&INDEX('Bill Report Reference'!$G$2:$G$59,MATCH(INDEX(Account!$J$2:$J$131,MATCH($B3,Account!$A$2:$A$131,0))&"-"&$C3&"-"&$D3,'Bill Report Reference'!$I$2:$I$59,0)),"") -> https://www.congress.gov/119/bills/s2354/BILLS-119s2354rs.pdf | T3: =IFERROR(""&INDEX('Bill Report Reference'!$H$2:$H$59,MATCH(INDEX(Account!$J$2:$J$131,MATCH($B3,Account!$A$2:$A$131,0))&"-"&$C3&"-"&$D3,'Bill Report Reference'!$I$2:$I$59,0)),"") -> https://www.congress.gov/119/crpt/srpt44/CRPT-119srpt44.pdf
A4: OBS-0003 | B4: ACC-OSTP | C4: 2026 | D4: House Reported | E4: House | F4: =IFERROR(""&INDEX('Bill Report Reference'!$E$2:$E$59,MATCH(INDEX(Account!$J$2:$J$131,MATCH($B4,Account!$A$2:$A$131,0))&"-"&$C4&"-"&$D4,'Bill Report Reference'!$I$2:$I$59,0)),"") -> H.R.5342 | G4: =IFERROR(""&INDEX('Bill Report Reference'!$F$2:$F$59,MATCH(INDEX(Account!$J$2:$J$131,MATCH($B4,Account!$A$2:$A$131,0))&"-"&$C4&"-"&$D4,'Bill Report Reference'!$I$2:$I$59,0)),"") -> H.Rept.119-272 | H4: 7965000 | I4: budget authority | K4: FALSE | M4: SRC-CRPT-119HRPT272 | N4: 256-257 | O4: Title III, Executive Office of the President, Office of Science and Technology Policy | P4: human-entered | Q4: 1 | R4: human-verified | S4: =IFERROR(""&INDEX('Bill Report Reference'!$G$2:$G$59,MATCH(INDEX(Account!$J$2:$J$131,MATCH($B4,Account!$A$2:$A$131,0))&"-"&$C4&"-"&$D4,'Bill Report Reference'!$I$2:$I$59,0)),"") -> https://www.govinfo.gov/content/pkg/BILLS-119hr5342rh/pdf/BILLS-119hr5342rh.pdf | T4: =IFERROR(""&INDEX('Bill Report Reference'!$H$2:$H$59,MATCH(INDEX(Account!$J$2:$J$131,MATCH($B4,Account!$A$2:$A$131,0))&"-"&$C4&"-"&$D4,'Bill Report Reference'!$I$2:$I$59,0)),"") -> https://www.congress.gov/119/crpt/hrpt272/CRPT-119hrpt272.pdf
A5: OBS-0004 | B5: ACC-OSTP | C5: 2026 | D5: President's Budget | E5: N/A | F5: =IFERROR(""&INDEX('Bill Report Reference'!$E$2:$E$59,MATCH(INDEX(Account!$J$2:$J$131,MATCH($B5,Account!$A$2:$A$131,0))&"-"&$C5&"-"&$D5,'Bill Report Reference'!$I$2:$I$59,0)),"") -> PREX 2.8:2026/APP | G5: =IFERROR(""&INDEX('Bill Report Reference'!$F$2:$F$59,MATCH(INDEX(Account!$J$2:$J$131,MATCH($B5,Account!$A$2:$A$131,0))&"-"&$C5&"-"&$D5,'Bill Report Reference'!$I$2:$I$59,0)),"") -> N/A | H5: 7965000 | I5: budget authority | K5: FALSE | M5: SRC-EXPL-FY2026-PB | N5: 128-130 | O5: Title III, Executive Office of the President, Office of Science and Technology Policy | P5: human-entered | Q5: 1 | R5: human-verified | S5: =IFERROR(""&INDEX('Bill Report Reference'!$G$2:$G$59,MATCH(INDEX(Account!$J$2:$J$131,MATCH($B5,Account!$A$2:$A$131,0))&"-"&$C5&"-"&$D5,'Bill Report Reference'!$I$2:$I$59,0)),"") -> https://www.govinfo.gov/content/pkg/BUDGET-2026-APP/pdf/BUDGET-2026-APP.pdf | T5: =IFERROR(""&INDEX('Bill Report Reference'!$H$2:$H$59,MATCH(INDEX(Account!$J$2:$J$131,MATCH($B5,Account!$A$2:$A$131,0))&"-"&$C5&"-"&$D5,'Bill Report Reference'!$I$2:$I$59,0)),"") -> N/A
A6: OBS-0005 | B6: ACC-OSTP | C6: 2025 | D6: Enacted | E6: N/A | F6: =IFERROR(""&INDEX('Bill Report Reference'!$E$2:$E$59,MATCH(INDEX(Account!$J$2:$J$131,MATCH($B6,Account!$A$2:$A$131,0))&"-"&$C6&"-"&$D6,'Bill Report Reference'!$I$2:$I$59,0)),"") -> P.L.119-4 | G6: =IFERROR(""&INDEX('Bill Report Reference'!$F$2:$F$59,MATCH(INDEX(Account!$J$2:$J$131,MATCH($B6,Account!$A$2:$A$131,0))&"-"&$C6&"-"&$D6,'Bill Report Reference'!$I$2:$I$59,0)),"") -> N/A | H6: 7965000 | I6: budget authority | K6: FALSE | M6: SRC-CRPT-119HRPT272 | N6: 256-257 | O6: Title III, Executive Office of the President, Office of Science and Technology Policy | P6: human-entered | Q6: 1 | R6: human-verified | S6: =IFERROR(""&INDEX('Bill Report Reference'!$G$2:$G$59,MATCH(INDEX(Account!$J$2:$J$131,MATCH($B6,Account!$A$2:$A$131,0))&"-"&$C6&"-"&$D6,'Bill Report Reference'!$I$2:$I$59,0)),"") -> https://www.govinfo.gov/content/pkg/PLAW-119publ4/pdf/PLAW-119publ4.pdf | T6: =IFERROR(""&INDEX('Bill Report Reference'!$H$2:$H$59,MATCH(INDEX(Account!$J$2:$J$131,MATCH($B6,Account!$A$2:$A$131,0))&"-"&$C6&"-"&$D6,'Bill Report Reference'!$I$2:$I$59,0)),"") -> N/A
A7: OBS-0006 | B7: ACC-OSTP | C7: 2025 | D7: Senate Reported | E7: Senate | F7: =IFERROR(""&INDEX('Bill Report Reference'!$E$2:$E$59,MATCH(INDEX(Account!$J$2:$J$131,MATCH($B7,Account!$A$2:$A$131,0))&"-"&$C7&"-"&$D7,'Bill Report Reference'!$I$2:$I$59,0)),"") -> S.4795 | G7: =IFERROR(""&INDEX('Bill Report Reference'!$F$2:$F$59,MATCH(INDEX(Account!$J$2:$J$131,MATCH($B7,Account!$A$2:$A$131,0))&"-"&$C7&"-"&$D7,'Bill Report Reference'!$I$2:$I$59,0)),"") -> S.Rept.118-198 | H7: 7965000 | I7: budget authority | K7: FALSE | M7: SRC-CRPT-118SRPT198 | N7: 227-228 | O7: Title III, Executive Office of the President, Office of Science and Technology Policy | P7: human-entered | Q7: 1 | R7: human-verified | S7: =IFERROR(""&INDEX('Bill Report Reference'!$G$2:$G$59,MATCH(INDEX(Account!$J$2:$J$131,MATCH($B7,Account!$A$2:$A$131,0))&"-"&$C7&"-"&$D7,'Bill Report Reference'!$I$2:$I$59,0)),"") -> https://www.congress.gov/118/bills/s4795/BILLS-118s4795rs.pdf | T7: =IFERROR(""&INDEX('Bill Report Reference'!$H$2:$H$59,MATCH(INDEX(Account!$J$2:$J$131,MATCH($B7,Account!$A$2:$A$131,0))&"-"&$C7&"-"&$D7,'Bill Report Reference'!$I$2:$I$59,0)),"") -> https://www.congress.gov/118/crpt/srpt198/CRPT-118srpt198.pdf
A8: OBS-0007 | B8: ACC-OSTP | C8: 2025 | D8: House Reported | E8: House | F8: =IFERROR(""&INDEX('Bill Report Reference'!$E$2:$E$59,MATCH(INDEX(Account!$J$2:$J$131,MATCH($B8,Account!$A$2:$A$131,0))&"-"&$C8&"-"&$D8,'Bill Report Reference'!$I$2:$I$59,0)),"") -> H.R.9026 | G8: =IFERROR(""&INDEX('Bill Report Reference'!$F$2:$F$59,MATCH(INDEX(Account!$J$2:$J$131,MATCH($B8,Account!$A$2:$A$131,0))&"-"&$C8&"-"&$D8,'Bill Report Reference'!$I$2:$I$59,0)),"") -> H.Rept.118-582 | H8: 5544000 | I8: budget authority | K8: FALSE | M8: SRC-CRPT-118HRPT582 | N8: 247-248 | O8: Title III, Executive Office of the President, Office of Science and Technology Policy | P8: human-entered | Q8: 1 | R8: human-verified | S8: =IFERROR(""&INDEX('Bill Report Reference'!$G$2:$G$59,MATCH(INDEX(Account!$J$2:$J$131,MATCH($B8,Account!$A$2:$A$131,0))&"-"&$C8&"-"&$D8,'Bill Report Reference'!$I$2:$I$59,0)),"") -> https://www.govinfo.gov/content/pkg/BILLS-118hr9026rh/pdf/BILLS-118hr9026rh.pdf | T8: =IFERROR(""&INDEX('Bill Report Reference'!$H$2:$H$59,MATCH(INDEX(Account!$J$2:$J$131,MATCH($B8,Account!$A$2:$A$131,0))&"-"&$C8&"-"&$D8,'Bill Report Reference'!$I$2:$I$59,0)),"") -> https://www.congress.gov/118/crpt/hrpt582/CRPT-118hrpt582.pdf
A9: OBS-0008 | B9: ACC-OSTP | C9: 2025 | D9: President's Budget | E9: N/A | F9: =IFERROR(""&INDEX('Bill Report Reference'!$E$2:$E$59,MATCH(INDEX(Account!$J$2:$J$131,MATCH($B9,Account!$A$2:$A$131,0))&"-"&$C9&"-"&$D9,'Bill Report Reference'!$I$2:$I$59,0)),"") -> PREX 2.8:2025/APP | G9: =IFERROR(""&INDEX('Bill Report Reference'!$F$2:$F$59,MATCH(INDEX(Account!$J$2:$J$131,MATCH($B9,Account!$A$2:$A$131,0))&"-"&$C9&"-"&$D9,'Bill Report Reference'!$I$2:$I$59,0)),"") -> N/A | H9: 7965000 | I9: budget authority | K9: FALSE | M9: SRC-CRPT-118HRPT582 | N9: 247-248 | O9: Title III, Executive Office of the President, Office of Science and Technology Policy | P9: human-entered | Q9: 1 | R9: human-verified | S9: =IFERROR(""&INDEX('Bill Report Reference'!$G$2:$G$59,MATCH(INDEX(Account!$J$2:$J$131,MATCH($B9,Account!$A$2:$A$131,0))&"-"&$C9&"-"&$D9,'Bill Report Reference'!$I$2:$I$59,0)),"") -> https://www.govinfo.gov/content/pkg/BUDGET-2025-APP/pdf/BUDGET-2025-APP.pdf | T9: =IFERROR(""&INDEX('Bill Report Reference'!$H$2:$H$59,MATCH(INDEX(Account!$J$2:$J$131,MATCH($B9,Account!$A$2:$A$131,0))&"-"&$C9&"-"&$D9,'Bill Report Reference'!$I$2:$I$59,0)),"") -> N/A
A10: OBS-0009 | B10: ACC-OSTP | C10: 2024 | D10: Enacted | E10: N/A | F10: =IFERROR(""&INDEX('Bill Report Reference'!$E$2:$E$59,MATCH(INDEX(Account!$J$2:$J$131,MATCH($B10,Account!$A$2:$A$131,0))&"-"&$C10&"-"&$D10,'Bill Report Reference'!$I$2:$I$59,0)),"") -> P.L.118-42 | G10: =IFERROR(""&INDEX('Bill Report Reference'!$F$2:$F$59,MATCH(INDEX(Account!$J$2:$J$131,MATCH($B10,Account!$A$2:$A$131,0))&"-"&$C10&"-"&$D10,'Bill Report Reference'!$I$2:$I$59,0)),"") -> JES_CJS_P.L.118-42 | H10: 7965000 | I10: budget authority | K10: FALSE | M10: SRC-CRPT-118HRPT582 | N10: 247-248 | O10: Title III, Executive Office of the President, Office of Science and Technology Policy | P10: human-entered | Q10: 1 | R10: human-verified | S10: =IFERROR(""&INDEX('Bill Report Reference'!$G$2:$G$59,MATCH(INDEX(Account!$J$2:$J$131,MATCH($B10,Account!$A$2:$A$131,0))&"-"&$C10&"-"&$D10,'Bill Report Reference'!$I$2:$I$59,0)),"") -> https://www.govinfo.gov/content/pkg/PLAW-118publ42/pdf/PLAW-118publ42.pdf | T10: =IFERROR(""&INDEX('Bill Report Reference'!$H$2:$H$59,MATCH(INDEX(Account!$J$2:$J$131,MATCH($B10,Account!$A$2:$A$131,0))&"-"&$C10&"-"&$D10,'Bill Report Reference'!$I$2:$I$59,0)),"") -> https://docs.house.gov/billsthisweek/20240304/FY24%20CJS%20Conference%20JES%20scan%203.3.24.pdf
A11: OBS-0010 | B11: ACC-OSTP | C11: 2024 | D11: Senate Reported | E11: Senate | F11: =IFERROR(""&INDEX('Bill Report Reference'!$E$2:$E$59,MATCH(INDEX(Account!$J$2:$J$131,MATCH($B11,Account!$A$2:$A$131,0))&"-"&$C11&"-"&$D11,'Bill Report Reference'!$I$2:$I$59,0)),"") -> S.2321 | G11: =IFERROR(""&INDEX('Bill Report Reference'!$F$2:$F$59,MATCH(INDEX(Account!$J$2:$J$131,MATCH($B11,Account!$A$2:$A$131,0))&"-"&$C11&"-"&$D11,'Bill Report Reference'!$I$2:$I$59,0)),"") -> S.Rept.118-62 | H11: 7965000 | I11: budget authority | K11: FALSE | M11: SRC-CRPT-118SRPT62 | N11: 219-220 | O11: Title III, Executive Office of the President, Office of Science and Technology Policy | P11: human-entered | Q11: 1 | R11: human-verified | S11: =IFERROR(""&INDEX('Bill Report Reference'!$G$2:$G$59,MATCH(INDEX(Account!$J$2:$J$131,MATCH($B11,Account!$A$2:$A$131,0))&"-"&$C11&"-"&$D11,'Bill Report Reference'!$I$2:$I$59,0)),"") -> https://www.congress.gov/118/bills/s2321/BILLS-118s2321rs.pdf | T11: =IFERROR(""&INDEX('Bill Report Reference'!$H$2:$H$59,MATCH(INDEX(Account!$J$2:$J$131,MATCH($B11,Account!$A$2:$A$131,0))&"-"&$C11&"-"&$D11,'Bill Report Reference'!$I$2:$I$59,0)),"") -> https://www.congress.gov/118/crpt/srpt62/CRPT-118srpt62.pdf
A12: OBS-0011 | B12: ACC-OSTP | C12: 2024 | D12: House Reported | E12: House | F12: =IFERROR(""&INDEX('Bill Report Reference'!$E$2:$E$59,MATCH(INDEX(Account!$J$2:$J$131,MATCH($B12,Account!$A$2:$A$131,0))&"-"&$C12&"-"&$D12,'Bill Report Reference'!$I$2:$I$59,0)),"") -> H.R.5893 | G12: =IFERROR(""&INDEX('Bill Report Reference'!$F$2:$F$59,MATCH(INDEX(Account!$J$2:$J$131,MATCH($B12,Account!$A$2:$A$131,0))&"-"&$C12&"-"&$D12,'Bill Report Reference'!$I$2:$I$59,0)),"") -> JES_CJS_H.R.5893 | H12: 5544000 | I12: budget authority | K12: FALSE | M12: SRC-EXPL-FY2024-HOUSE | N12: 170-171 | O12: Title III, Executive Office of the President, Office of Science and Technology Policy | P12: human-entered | Q12: 1 | R12: human-verified | S12: =IFERROR(""&INDEX('Bill Report Reference'!$G$2:$G$59,MATCH(INDEX(Account!$J$2:$J$131,MATCH($B12,Account!$A$2:$A$131,0))&"-"&$C12&"-"&$D12,'Bill Report Reference'!$I$2:$I$59,0)),"") -> https://www.congress.gov/118/bills/hr5893/BILLS-118hr5893ih.pdf | T12: =IFERROR(""&INDEX('Bill Report Reference'!$H$2:$H$59,MATCH(INDEX(Account!$J$2:$J$131,MATCH($B12,Account!$A$2:$A$131,0))&"-"&$C12&"-"&$D12,'Bill Report Reference'!$I$2:$I$59,0)),"") -> https://appropriations.house.gov/sites/evo-subsites/republicans-appropriations.house.gov/files/FY24-CJS-Explanatory-Materials.pdf
A13: OBS-0012 | B13: ACC-OSTP | C13: 2024 | D13: President's Budget | E13: N/A | F13: =IFERROR(""&INDEX('Bill Report Reference'!$E$2:$E$59,MATCH(INDEX(Account!$J$2:$J$131,MATCH($B13,Account!$A$2:$A$131,0))&"-"&$C13&"-"&$D13,'Bill Report Reference'!$I$2:$I$59,0)),"") -> PREX 2.8:2024/APP | G13: =IFERROR(""&INDEX('Bill Report Reference'!$F$2:$F$59,MATCH(INDEX(Account!$J$2:$J$131,MATCH($B13,Account!$A$2:$A$131,0))&"-"&$C13&"-"&$D13,'Bill Report Reference'!$I$2:$I$59,0)),"") -> N/A | H13: 8195000 | I13: budget authority | K13: FALSE | M13: SRC-CRPT-118SRPT62 | N13: 219-220 | O13: Title III, Executive Office of the President, Office of Science and Technology Policy | P13: human-entered | Q13: 1 | R13: human-verified | S13: =IFERROR(""&INDEX('Bill Report Reference'!$G$2:$G$59,MATCH(INDEX(Account!$J$2:$J$131,MATCH($B13,Account!$A$2:$A$131,0))&"-"&$C13&"-"&$D13,'Bill Report Reference'!$I$2:$I$59,0)),"") -> https://www.govinfo.gov/content/pkg/BUDGET-2024-APP/pdf/BUDGET-2024-APP.pdf | T13: =IFERROR(""&INDEX('Bill Report Reference'!$H$2:$H$59,MATCH(INDEX(Account!$J$2:$J$131,MATCH($B13,Account!$A$2:$A$131,0))&"-"&$C13&"-"&$D13,'Bill Report Reference'!$I$2:$I$59,0)),"") -> N/A
... A614: OBS-0658 | B614: ACC-NASA-CONSTRUCTION | C614: 2024 | D614: House Reported | E614: House | F614: =IFERROR(""&INDEX('Bill Report Reference'!$E$2:$E$59,MATCH(INDEX(Account!$J$2:$J$131,MATCH($B614,Account!$A$2:$A$131,0))&"-"&$C614&"-"&$D614,'Bill Report Reference'!$I$2:$I$59,0)),"") -> H.R.5893 | G614: =IFERROR(""&INDEX('Bill Report Reference'!$F$2:$F$59,MATCH(INDEX(Account!$J$2:$J$131,MATCH($B614,Account!$A$2:$A$131,0))&"-"&$C614&"-"&$D614,'Bill Report Reference'!$I$2:$I$59,0)),"") -> JES_CJS_H.R.5893 | H614: 0 | I614: supplemental | K614: FALSE | M614: SRC-EXPL-FY2024-HOUSE | N614: 170-171 | O614: Title III, NASA, Construction and Environmental Compliance and Restoration (emergency) | P614: human-entered | Q614: 1 | R614: human-verified | S614: =IFERROR(""&INDEX('Bill Report Reference'!$G$2:$G$59,MATCH(INDEX(Account!$J$2:$J$131,MATCH($B614,Account!$A$2:$A$131,0))&"-"&$C614&"-"&$D614,'Bill Report Reference'!$I$2:$I$59,0)),"") -> https://www.congress.gov/118/bills/hr5893/BILLS-118hr5893ih.pdf | T614: =IFERROR(""&INDEX('Bill Report Reference'!$H$2:$H$59,MATCH(INDEX(Account!$J$2:$J$131,MATCH($B614,Account!$A$2:$A$131,0))&"-"&$C614&"-"&$D614,'Bill Report Reference'!$I$2:$I$59,0)),"") -> https://appropriations.house.gov/sites/evo-subsites/republicans-appropriations.house.gov/files/FY24-CJS-Explanatory-Materials.pdf
A615: OBS-0660 | B615: ACC-NASA-CONSTRUCTION | C615: 2023 | D615: Enacted | E615: N/A | F615: =IFERROR(""&INDEX('Bill Report Reference'!$E$2:$E$59,MATCH(INDEX(Account!$J$2:$J$131,MATCH($B615,Account!$A$2:$A$131,0))&"-"&$C615&"-"&$D615,'Bill Report Reference'!$I$2:$I$59,0)),"") -> P.L.117-328 | G615: =IFERROR(""&INDEX('Bill Report Reference'!$F$2:$F$59,MATCH(INDEX(Account!$J$2:$J$131,MATCH($B615,Account!$A$2:$A$131,0))&"-"&$C615&"-"&$D615,'Bill Report Reference'!$I$2:$I$59,0)),"") -> JES_CJS_P.L.117-328 | H615: 556400000 | I615: supplemental | J615: supplemental_act | K615: FALSE | M615: SRC-CRPT-118SRPT62 | N615: 224 | O615: P.L. 117-328, Division N (Disaster Relief Supplemental Appropriations Act, 2023), Title III, 136 Stat. 5205-5206: two appropriations to "Construction and Environmental Compliance and Restoration", $189,400,000 + $367,000,000 = $556,400,000 (the report prints the sum). | P615: human-entered | Q615: 1 | R615: human-verified | S615: =IFERROR(""&INDEX('Bill Report Reference'!$G$2:$G$59,MATCH(INDEX(Account!$J$2:$J$131,MATCH($B615,Account!$A$2:$A$131,0))&"-"&$C615&"-"&$D615,'Bill Report Reference'!$I$2:$I$59,0)),"") -> https://www.govinfo.gov/content/pkg/PLAW-117publ328/pdf/PLAW-117publ328.pdf | T615: =IFERROR(""&INDEX('Bill Report Reference'!$H$2:$H$59,MATCH(INDEX(Account!$J$2:$J$131,MATCH($B615,Account!$A$2:$A$131,0))&"-"&$C615&"-"&$D615,'Bill Report Reference'!$I$2:$I$59,0)),"") -> https://www.govinfo.gov/content/pkg/CPRT-117HPRT50347/pdf/CPRT-117HPRT50347.pdf
A616: OBS-0661 | B616: ACC-NASA-CONSTRUCTION | C616: 2023 | D616: Senate Reported | E616: Senate | F616: =IFERROR(""&INDEX('Bill Report Reference'!$E$2:$E$59,MATCH(INDEX(Account!$J$2:$J$131,MATCH($B616,Account!$A$2:$A$131,0))&"-"&$C616&"-"&$D616,'Bill Report Reference'!$I$2:$I$59,0)),"") -> S.4664 | G616: =IFERROR(""&INDEX('Bill Report Reference'!$F$2:$F$59,MATCH(INDEX(Account!$J$2:$J$131,MATCH($B616,Account!$A$2:$A$131,0))&"-"&$C616&"-"&$D616,'Bill Report Reference'!$I$2:$I$59,0)),"") -> JES_CJS_S.4664 | H616: 0 | I616: supplemental | K616: FALSE | M616: SRC-EXPL-FY2023-SENATE | N616: 215-216 | O616: Title III, NASA, Construction and Environmental Compliance and Restoration (emergency) | P616: human-entered | Q616: 1 | R616: human-verified | S616: =IFERROR(""&INDEX('Bill Report Reference'!$G$2:$G$59,MATCH(INDEX(Account!$J$2:$J$131,MATCH($B616,Account!$A$2:$A$131,0))&"-"&$C616&"-"&$D616,'Bill Report Reference'!$I$2:$I$59,0)),"") -> https://www.congress.gov/117/bills/s4664/BILLS-117s4664is.pdf | T616: =IFERROR(""&INDEX('Bill Report Reference'!$H$2:$H$59,MATCH(INDEX(Account!$J$2:$J$131,MATCH($B616,Account!$A$2:$A$131,0))&"-"&$C616&"-"&$D616,'Bill Report Reference'!$I$2:$I$59,0)),"") -> https://www.appropriations.senate.gov/imo/media/doc/CJSFY23RPT.PDF
A617: OBS-0664 | B617: ACC-NASA-CONSTRUCTION | C617: 2022 | D617: Enacted | E617: N/A | F617: =IFERROR(""&INDEX('Bill Report Reference'!$E$2:$E$59,MATCH(INDEX(Account!$J$2:$J$131,MATCH($B617,Account!$A$2:$A$131,0))&"-"&$C617&"-"&$D617,'Bill Report Reference'!$I$2:$I$59,0)),"") -> P.L.117-103 | G617: =IFERROR(""&INDEX('Bill Report Reference'!$F$2:$F$59,MATCH(INDEX(Account!$J$2:$J$131,MATCH($B617,Account!$A$2:$A$131,0))&"-"&$C617&"-"&$D617,'Bill Report Reference'!$I$2:$I$59,0)),"") -> JES_CJS_P.L.117-103 | H617: 321400000 | I617: supplemental | J617: supplemental_act | K617: FALSE | M617: SRC-CRPT-117HRPT395 | N617: 224 | O617: P.L. 117-43, Division B (Disaster Relief Supplemental Appropriations Act, 2022), Title III, 135 Stat. 359: 'For an additional amount for "Construction and Environmental Compliance and Restoration" for repair at National Aeronautics and Space Administration facilities damaged by Hurricanes Zeta and Ida ..., $321,400,000'. | P617: human-entered | Q617: 1 | R617: human-verified | S617: =IFERROR(""&INDEX('Bill Report Reference'!$G$2:$G$59,MATCH(INDEX(Account!$J$2:$J$131,MATCH($B617,Account!$A$2:$A$131,0))&"-"&$C617&"-"&$D617,'Bill Report Reference'!$I$2:$I$59,0)),"") -> https://www.congress.gov/117/plaws/publ103/PLAW-117publ103.pdf | T617: =IFERROR(""&INDEX('Bill Report Reference'!$H$2:$H$59,MATCH(INDEX(Account!$J$2:$J$131,MATCH($B617,Account!$A$2:$A$131,0))&"-"&$C617&"-"&$D617,'Bill Report Reference'!$I$2:$I$59,0)),"") -> https://www.govinfo.gov/content/pkg/CPRT-117HPRT47047/pdf/CPRT-117HPRT47047.pdf
A618: OBS-0665 | B618: ACC-NASA-CONSTRUCTION | C618: 2022 | D618: Senate Reported | E618: Senate | F618: =IFERROR(""&INDEX('Bill Report Reference'!$E$2:$E$59,MATCH(INDEX(Account!$J$2:$J$131,MATCH($B618,Account!$A$2:$A$131,0))&"-"&$C618&"-"&$D618,'Bill Report Reference'!$I$2:$I$59,0)),"") -> S.3042 | G618: =IFERROR(""&INDEX('Bill Report Reference'!$F$2:$F$59,MATCH(INDEX(Account!$J$2:$J$131,MATCH($B618,Account!$A$2:$A$131,0))&"-"&$C618&"-"&$D618,'Bill Report Reference'!$I$2:$I$59,0)),"") -> JES_CJS_S.3042 | H618: 0 | I618: supplemental | K618: FALSE | M618: SRC-EXPL-FY2022-SENATE | N618: 207-208 | O618: Title III, NASA, Construction and Environmental Compliance and Restoration (emergency) | P618: human-entered | Q618: 1 | R618: human-verified | S618: =IFERROR(""&INDEX('Bill Report Reference'!$G$2:$G$59,MATCH(INDEX(Account!$J$2:$J$131,MATCH($B618,Account!$A$2:$A$131,0))&"-"&$C618&"-"&$D618,'Bill Report Reference'!$I$2:$I$59,0)),"") -> https://www.congress.gov/117/bills/s3042/BILLS-117s3042is.pdf | T618: =IFERROR(""&INDEX('Bill Report Reference'!$H$2:$H$59,MATCH(INDEX(Account!$J$2:$J$131,MATCH($B618,Account!$A$2:$A$131,0))&"-"&$C618&"-"&$D618,'Bill Report Reference'!$I$2:$I$59,0)),"") -> https://www.appropriations.senate.gov/imo/media/doc/CJSRept_Final.PDF
A619: OBS-0669 | B619: ACC-NASA-CONSTRUCTION | C619: 2021 | D619: Senate Reported | E619: Senate | F619: =IFERROR(""&INDEX('Bill Report Reference'!$E$2:$E$59,MATCH(INDEX(Account!$J$2:$J$131,MATCH($B619,Account!$A$2:$A$131,0))&"-"&$C619&"-"&$D619,'Bill Report Reference'!$I$2:$I$59,0)),"") -> N/A | G619: =IFERROR(""&INDEX('Bill Report Reference'!$F$2:$F$59,MATCH(INDEX(Account!$J$2:$J$131,MATCH($B619,Account!$A$2:$A$131,0))&"-"&$C619&"-"&$D619,'Bill Report Reference'!$I$2:$I$59,0)),"") -> JES_CJS_FY2021-Senate | H619: 0 | I619: supplemental | K619: FALSE | M619: SRC-EXPL-FY2021-SENATE | N619: 197-199 | O619: Title III, NASA, Construction and Environmental Compliance and Restoration (emergency) | P619: human-entered | Q619: 1 | R619: human-verified | S619: =IFERROR(""&INDEX('Bill Report Reference'!$G$2:$G$59,MATCH(INDEX(Account!$J$2:$J$131,MATCH($B619,Account!$A$2:$A$131,0))&"-"&$C619&"-"&$D619,'Bill Report Reference'!$I$2:$I$59,0)),"") -> https://www.appropriations.senate.gov/imo/media/doc/CJSFY2021.pdf | T619: =IFERROR(""&INDEX('Bill Report Reference'!$H$2:$H$59,MATCH(INDEX(Account!$J$2:$J$131,MATCH($B619,Account!$A$2:$A$131,0))&"-"&$C619&"-"&$D619,'Bill Report Reference'!$I$2:$I$59,0)),"") -> https://www.appropriations.senate.gov/imo/media/doc/CJSRept.pdf
A620: OBS-0680 | B620: ACC-NASA-CONSTRUCTION | C620: 2018 | D620: Enacted | E620: N/A | F620: =IFERROR(""&INDEX('Bill Report Reference'!$E$2:$E$59,MATCH(INDEX(Account!$J$2:$J$131,MATCH($B620,Account!$A$2:$A$131,0))&"-"&$C620&"-"&$D620,'Bill Report Reference'!$I$2:$I$59,0)),"") -> P.L.115-141 | G620: =IFERROR(""&INDEX('Bill Report Reference'!$F$2:$F$59,MATCH(INDEX(Account!$J$2:$J$131,MATCH($B620,Account!$A$2:$A$131,0))&"-"&$C620&"-"&$D620,'Bill Report Reference'!$I$2:$I$59,0)),"") -> JES_CJS_P.L.115-141 | H620: 81300000 | I620: supplemental | J620: supplemental_act | K620: FALSE | M620: SRC-CRPT-115HRPT704 | N620: 134 | O620: P.L. 115-123, Division B (Further Additional Supplemental Appropriations for Disaster Relief Requirements Act, 2018), Title III, 132 Stat. 72: 'For an additional amount for "Construction and Environmental Compliance and Restoration" for repairs at National Aeronautics and Space Administration facilities damaged by hurricanes during 2017, $81,300,000' -- designated an emergency requirement. Also S.Rept. 115-275 p.161. | P620: human-entered | Q620: 1 | R620: human-verified | S620: =IFERROR(""&INDEX('Bill Report Reference'!$G$2:$G$59,MATCH(INDEX(Account!$J$2:$J$131,MATCH($B620,Account!$A$2:$A$131,0))&"-"&$C620&"-"&$D620,'Bill Report Reference'!$I$2:$I$59,0)),"") -> https://www.congress.gov/115/plaws/publ141/PLAW-115publ141.pdf | T620: =IFERROR(""&INDEX('Bill Report Reference'!$H$2:$H$59,MATCH(INDEX(Account!$J$2:$J$131,MATCH($B620,Account!$A$2:$A$131,0))&"-"&$C620&"-"&$D620,'Bill Report Reference'!$I$2:$I$59,0)),"") -> https://www.govinfo.gov/content/pkg/CPRT-115HPRT29456/pdf/CPRT-115HPRT29456.pdf
A621: OBS-0684 | B621: ACC-NASA-CONSTRUCTION | C621: 2017 | D621: Enacted | E621: N/A | F621: =IFERROR(""&INDEX('Bill Report Reference'!$E$2:$E$59,MATCH(INDEX(Account!$J$2:$J$131,MATCH($B621,Account!$A$2:$A$131,0))&"-"&$C621&"-"&$D621,'Bill Report Reference'!$I$2:$I$59,0)),"") -> P.L.115-31 | G621: =IFERROR(""&INDEX('Bill Report Reference'!$F$2:$F$59,MATCH(INDEX(Account!$J$2:$J$131,MATCH($B621,Account!$A$2:$A$131,0))&"-"&$C621&"-"&$D621,'Bill Report Reference'!$I$2:$I$59,0)),"") -> JES_CJS_P.L.115-31 | H621: 0 | I621: supplemental | K621: FALSE | M621: SRC-CRPT-115HRPT231 | N621: 120-121 | O621: Title III, NASA, Construction and Environmental Compliance and Restoration (emergency) | P621: human-entered | Q621: 1 | R621: human-verified | S621: =IFERROR(""&INDEX('Bill Report Reference'!$G$2:$G$59,MATCH(INDEX(Account!$J$2:$J$131,MATCH($B621,Account!$A$2:$A$131,0))&"-"&$C621&"-"&$D621,'Bill Report Reference'!$I$2:$I$59,0)),"") -> https://www.govinfo.gov/content/pkg/PLAW-115publ31/pdf/PLAW-115publ31.pdf | T621: =IFERROR(""&INDEX('Bill Report Reference'!$H$2:$H$59,MATCH(INDEX(Account!$J$2:$J$131,MATCH($B621,Account!$A$2:$A$131,0))&"-"&$C621&"-"&$D621,'Bill Report Reference'!$I$2:$I$59,0)),"") -> https://www.govinfo.gov/content/pkg/CPRT-115HPRT25289/pdf/CPRT-115HPRT25289.pdf
A622: OBS-0688 | B622: ACC-NSF-RRA | C622: 2026 | D622: Enacted | E622: N/A | F622: =IFERROR(""&INDEX('Bill Report Reference'!$E$2:$E$59,MATCH(INDEX(Account!$J$2:$J$131,MATCH($B622,Account!$A$2:$A$131,0))&"-"&$C622&"-"&$D622,'Bill Report Reference'!$I$2:$I$59,0)),"") -> P.L.119-74 | G622: =IFERROR(""&INDEX('Bill Report Reference'!$F$2:$F$59,MATCH(INDEX(Account!$J$2:$J$131,MATCH($B622,Account!$A$2:$A$131,0))&"-"&$C622&"-"&$D622,'Bill Report Reference'!$I$2:$I$59,0)),"") -> JES_CJS_P.L.119-74 | H622: 7057700000 | I622: budget authority | K622: FALSE | M622: SRC-EXPL-FY2026-PB | N622: 128-130 | O622: Title III, NSF, Research and Related Activities (base) | P622: human-entered | Q622: 1 | R622: human-verified | S622: =IFERROR(""&INDEX('Bill Report Reference'!$G$2:$G$59,MATCH(INDEX(Account!$J$2:$J$131,MATCH($B622,Account!$A$2:$A$131,0))&"-"&$C622&"-"&$D622,'Bill Report Reference'!$I$2:$I$59,0)),"") -> https://www.govinfo.gov/content/pkg/PLAW-119publ74/pdf/PLAW-119publ74.pdf | T622: =IFERROR(""&INDEX('Bill Report Reference'!$H$2:$H$59,MATCH(INDEX(Account!$J$2:$J$131,MATCH($B622,Account!$A$2:$A$131,0))&"-"&$C622&"-"&$D622,'Bill Report Reference'!$I$2:$I$59,0)),"") -> https://rules.house.gov/sites/evo-subsites/rules.house.gov/files/documents/division-a-commerce-justice-science_0.pdf
A623: OBS-0689 | B623: ACC-NSF-RRA | C623: 2026 | D623: Senate Reported | E623: Senate | F623: =IFERROR(""&INDEX('Bill Report Reference'!$E$2:$E$59,MATCH(INDEX(Account!$J$2:$J$131,MATCH($B623,Account!$A$2:$A$131,0))&"-"&$C623&"-"&$D623,'Bill Report Reference'!$I$2:$I$59,0)),"") -> S.2354 | G623: =IFERROR(""&INDEX('Bill Report Reference'!$F$2:$F$59,MATCH(INDEX(Account!$J$2:$J$131,MATCH($B623,Account!$A$2:$A$131,0))&"-"&$C623&"-"&$D623,'Bill Report Reference'!$I$2:$I$59,0)),"") -> S.Rept.119-44 | H623: 7067190000 | I623: budget authority | K623: FALSE | M623: SRC-CRPT-119SRPT44 | N623: 217-219 | O623: Title III, NSF, Research and Related Activities (base) | P623: human-entered | Q623: 1 | R623: human-verified | S623: =IFERROR(""&INDEX('Bill Report Reference'!$G$2:$G$59,MATCH(INDEX(Account!$J$2:$J$131,MATCH($B623,Account!$A$2:$A$131,0))&"-"&$C623&"-"&$D623,'Bill Report Reference'!$I$2:$I$59,0)),"") -> https://www.congress.gov/119/bills/s2354/BILLS-119s2354rs.pdf | T623: =IFERROR(""&INDEX('Bill Report Reference'!$H$2:$H$59,MATCH(INDEX(Account!$J$2:$J$131,MATCH($B623,Account!$A$2:$A$131,0))&"-"&$C623&"-"&$D623,'Bill Report Reference'!$I$2:$I$59,0)),"") -> https://www.congress.gov/119/crpt/srpt44/CRPT-119srpt44.pdf
A624: OBS-0690 | B624: ACC-NSF-RRA | C624: 2026 | D624: House Reported | E624: House | F624: =IFERROR(""&INDEX('Bill Report Reference'!$E$2:$E$59,MATCH(INDEX(Account!$J$2:$J$131,MATCH($B624,Account!$A$2:$A$131,0))&"-"&$C624&"-"&$D624,'Bill Report Reference'!$I$2:$I$59,0)),"") -> H.R.5342 | G624: =IFERROR(""&INDEX('Bill Report Reference'!$F$2:$F$59,MATCH(INDEX(Account!$J$2:$J$131,MATCH($B624,Account!$A$2:$A$131,0))&"-"&$C624&"-"&$D624,'Bill Report Reference'!$I$2:$I$59,0)),"") -> H.Rept.119-272 | H624: 6263690000 | I624: budget authority | K624: FALSE | M624: SRC-CRPT-119HRPT272 | N624: 256-257 | O624: Title III, NSF, Research and Related Activities (base) | P624: human-entered | Q624: 1 | R624: human-verified | S624: =IFERROR(""&INDEX('Bill Report Reference'!$G$2:$G$59,MATCH(INDEX(Account!$J$2:$J$131,MATCH($B624,Account!$A$2:$A$131,0))&"-"&$C624&"-"&$D624,'Bill Report Reference'!$I$2:$I$59,0)),"") -> https://www.govinfo.gov/content/pkg/BILLS-119hr5342rh/pdf/BILLS-119hr5342rh.pdf | T624: =IFERROR(""&INDEX('Bill Report Reference'!$H$2:$H$59,MATCH(INDEX(Account!$J$2:$J$131,MATCH($B624,Account!$A$2:$A$131,0))&"-"&$C624&"-"&$D624,'Bill Report Reference'!$I$2:$I$59,0)),"") -> https://www.congress.gov/119/crpt/hrpt272/CRPT-119hrpt272.pdf
A625: OBS-0691 | B625: ACC-NSF-RRA | C625: 2026 | D625: President's Budget | E625: N/A | F625: =IFERROR(""&INDEX('Bill Report Reference'!$E$2:$E$59,MATCH(INDEX(Account!$J$2:$J$131,MATCH($B625,Account!$A$2:$A$131,0))&"-"&$C625&"-"&$D625,'Bill Report Reference'!$I$2:$I$59,0)),"") -> PREX 2.8:2026/APP | G625: =IFERROR(""&INDEX('Bill Report Reference'!$F$2:$F$59,MATCH(INDEX(Account!$J$2:$J$131,MATCH($B625,Account!$A$2:$A$131,0))&"-"&$C625&"-"&$D625,'Bill Report Reference'!$I$2:$I$59,0)),"") -> N/A | H625: 3166840000 | I625: budget authority | K625: FALSE | M625: SRC-EXPL-FY2026-PB | N625: 128-130 | O625: Title III, NSF, Research and Related Activities (base) | P625: human-entered | Q625: 1 | R625: human-verified | S625: =IFERROR(""&INDEX('Bill Report Reference'!$G$2:$G$59,MATCH(INDEX(Account!$J$2:$J$131,MATCH($B625,Account!$A$2:$A$131,0))&"-"&$C625&"-"&$D625,'Bill Report Reference'!$I$2:$I$59,0)),"") -> https://www.govinfo.gov/content/pkg/BUDGET-2026-APP/pdf/BUDGET-2026-APP.pdf | T625: =IFERROR(""&INDEX('Bill Report Reference'!$H$2:$H$59,MATCH(INDEX(Account!$J$2:$J$131,MATCH($B625,Account!$A$2:$A$131,0))&"-"&$C625&"-"&$D625,'Bill Report Reference'!$I$2:$I$59,0)),"") -> N/A
A626: OBS-0692 | B626: ACC-NSF-RRA | C626: 2025 | D626: Enacted | E626: N/A | F626: =IFERROR(""&INDEX('Bill Report Reference'!$E$2:$E$59,MATCH(INDEX(Account!$J$2:$J$131,MATCH($B626,Account!$A$2:$A$131,0))&"-"&$C626&"-"&$D626,'Bill Report Reference'!$I$2:$I$59,0)),"") -> P.L.119-4 | G626: =IFERROR(""&INDEX('Bill Report Reference'!$F$2:$F$59,MATCH(INDEX(Account!$J$2:$J$131,MATCH($B626,Account!$A$2:$A$131,0))&"-"&$C626&"-"&$D626,'Bill Report Reference'!$I$2:$I$59,0)),"") -> N/A | H626: 7067190000 | I626: budget authority | K626: FALSE | M626: SRC-CRPT-119HRPT272 | N626: 256-257 | O626: Title III, NSF, Research and Related Activities (base) | P626: human-entered | Q626: 1 | R626: human-verified | S626: =IFERROR(""&INDEX('Bill Report Reference'!$G$2:$G$59,MATCH(INDEX(Account!$J$2:$J$131,MATCH($B626,Account!$A$2:$A$131,0))&"-"&$C626&"-"&$D626,'Bill Report Reference'!$I$2:$I$59,0)),"") -> https://www.govinfo.gov/content/pkg/PLAW-119publ4/pdf/PLAW-119publ4.pdf | T626: =IFERROR(""&INDEX('Bill Report Reference'!$H$2:$H$59,MATCH(INDEX(Account!$J$2:$J$131,MATCH($B626,Account!$A$2:$A$131,0))&"-"&$C626&"-"&$D626,'Bill Report Reference'!$I$2:$I$59,0)),"") -> N/A
A627: OBS-0693 | B627: ACC-NSF-RRA | C627: 2025 | D627: Senate Reported | E627: Senate | F627: =IFERROR(""&INDEX('Bill Report Reference'!$E$2:$E$59,MATCH(INDEX(Account!$J$2:$J$131,MATCH($B627,Account!$A$2:$A$131,0))&"-"&$C627&"-"&$D627,'Bill Report Reference'!$I$2:$I$59,0)),"") -> S.4795 | G627: =IFERROR(""&INDEX('Bill Report Reference'!$F$2:$F$59,MATCH(INDEX(Account!$J$2:$J$131,MATCH($B627,Account!$A$2:$A$131,0))&"-"&$C627&"-"&$D627,'Bill Report Reference'!$I$2:$I$59,0)),"") -> S.Rept.118-198 | H627: 6449280000 | I627: budget authority | K627: FALSE | M627: SRC-CRPT-118SRPT198 | N627: 227-228 | O627: Title III, NSF, Research and Related Activities (base) | P627: human-entered | Q627: 1 | R627: human-verified | S627: =IFERROR(""&INDEX('Bill Report Reference'!$G$2:$G$59,MATCH(INDEX(Account!$J$2:$J$131,MATCH($B627,Account!$A$2:$A$131,0))&"-"&$C627&"-"&$D627,'Bill Report Reference'!$I$2:$I$59,0)),"") -> https://www.congress.gov/118/bills/s4795/BILLS-118s4795rs.pdf | T627: =IFERROR(""&INDEX('Bill Report Reference'!$H$2:$H$59,MATCH(INDEX(Account!$J$2:$J$131,MATCH($B627,Account!$A$2:$A$131,0))&"-"&$C627&"-"&$D627,'Bill Report Reference'!$I$2:$I$59,0)),"") -> https://www.congress.gov/118/crpt/srpt198/CRPT-118srpt198.pdf
A628: OBS-0694 | B628: ACC-NSF-RRA | C628: 2025 | D628: House Reported | E628: House | F628: =IFERROR(""&INDEX('Bill Report Reference'!$E$2:$E$59,MATCH(INDEX(Account!$J$2:$J$131,MATCH($B628,Account!$A$2:$A$131,0))&"-"&$C628&"-"&$D628,'Bill Report Reference'!$I$2:$I$59,0)),"") -> H.R.9026 | G628: =IFERROR(""&INDEX('Bill Report Reference'!$F$2:$F$59,MATCH(INDEX(Account!$J$2:$J$131,MATCH($B628,Account!$A$2:$A$131,0))&"-"&$C628&"-"&$D628,'Bill Report Reference'!$I$2:$I$59,0)),"") -> H.Rept.118-582 | H628: 7437320000 | I628: budget authority | K628: FALSE | M628: SRC-CRPT-118HRPT582 | N628: 247-248 | O628: Title III, NSF, Research and Related Activities (base) | P628: human-entered | Q628: 1 | R628: human-verified | S628: =IFERROR(""&INDEX('Bill Report Reference'!$G$2:$G$59,MATCH(INDEX(Account!$J$2:$J$131,MATCH($B628,Account!$A$2:$A$131,0))&"-"&$C628&"-"&$D628,'Bill Report Reference'!$I$2:$I$59,0)),"") -> https://www.govinfo.gov/content/pkg/BILLS-118hr9026rh/pdf/BILLS-118hr9026rh.pdf | T628: =IFERROR(""&INDEX('Bill Report Reference'!$H$2:$H$59,MATCH(INDEX(Account!$J$2:$J$131,MATCH($B628,Account!$A$2:$A$131,0))&"-"&$C628&"-"&$D628,'Bill Report Reference'!$I$2:$I$59,0)),"") -> https://www.congress.gov/118/crpt/hrpt582/CRPT-118hrpt582.pdf
A629: OBS-0695 | B629: ACC-NSF-RRA | C629: 2025 | D629: President's Budget | E629: N/A | F629: =IFERROR(""&INDEX('Bill Report Reference'!$E$2:$E$59,MATCH(INDEX(Account!$J$2:$J$131,MATCH($B629,Account!$A$2:$A$131,0))&"-"&$C629&"-"&$D629,'Bill Report Reference'!$I$2:$I$59,0)),"") -> PREX 2.8:2025/APP | G629: =IFERROR(""&INDEX('Bill Report Reference'!$F$2:$F$59,MATCH(INDEX(Account!$J$2:$J$131,MATCH($B629,Account!$A$2:$A$131,0))&"-"&$C629&"-"&$D629,'Bill Report Reference'!$I$2:$I$59,0)),"") -> N/A | H629: 7519320000 | I629: budget authority | K629: FALSE | M629: SRC-CRPT-118HRPT582 | N629: 247-248 | O629: Title III, NSF, Research and Related Activities (base) | P629: human-entered | Q629: 1 | R629: human-verified | S629: =IFERROR(""&INDEX('Bill Report Reference'!$G$2:$G$59,MATCH(INDEX(Account!$J$2:$J$131,MATCH($B629,Account!$A$2:$A$131,0))&"-"&$C629&"-"&$D629,'Bill Report Reference'!$I$2:$I$59,0)),"") -> https://www.govinfo.gov/content/pkg/BUDGET-2025-APP/pdf/BUDGET-2025-APP.pdf | T629: =IFERROR(""&INDEX('Bill Report Reference'!$H$2:$H$59,MATCH(INDEX(Account!$J$2:$J$131,MATCH($B629,Account!$A$2:$A$131,0))&"-"&$C629&"-"&$D629,'Bill Report Reference'!$I$2:$I$59,0)),"") -> N/A
A630: OBS-0696 | B630: ACC-NSF-RRA | C630: 2024 | D630: Enacted | E630: N/A | F630: =IFERROR(""&INDEX('Bill Report Reference'!$E$2:$E$59,MATCH(INDEX(Account!$J$2:$J$131,MATCH($B630,Account!$A$2:$A$131,0))&"-"&$C630&"-"&$D630,'Bill Report Reference'!$I$2:$I$59,0)),"") -> P.L.118-42 | G630: =IFERROR(""&INDEX('Bill Report Reference'!$F$2:$F$59,MATCH(INDEX(Account!$J$2:$J$131,MATCH($B630,Account!$A$2:$A$131,0))&"-"&$C630&"-"&$D630,'Bill Report Reference'!$I$2:$I$59,0)),"") -> JES_CJS_P.L.118-42 | H630: 7067190000 | I630: budget authority | K630: FALSE | M630: SRC-CRPT-118HRPT582 | N630: 247-248 | O630: Title III, NSF, Research and Related Activities (base) | P630: human-entered | Q630: 1 | R630: human-verified | S630: =IFERROR(""&INDEX('Bill Report Reference'!$G$2:$G$59,MATCH(INDEX(Account!$J$2:$J$131,MATCH($B630,Account!$A$2:$A$131,0))&"-"&$C630&"-"&$D630,'Bill Report Reference'!$I$2:$I$59,0)),"") -> https://www.govinfo.gov/content/pkg/PLAW-118publ42/pdf/PLAW-118publ42.pdf | T630: =IFERROR(""&INDEX('Bill Report Reference'!$H$2:$H$59,MATCH(INDEX(Account!$J$2:$J$131,MATCH($B630,Account!$A$2:$A$131,0))&"-"&$C630&"-"&$D630,'Bill Report Reference'!$I$2:$I$59,0)),"") -> https://docs.house.gov/billsthisweek/20240304/FY24%20CJS%20Conference%20JES%20scan%203.3.24.pdf
A631: OBS-0697 | B631: ACC-NSF-RRA | C631: 2024 | D631: Senate Reported | E631: Senate | F631: =IFERROR(""&INDEX('Bill Report Reference'!$E$2:$E$59,MATCH(INDEX(Account!$J$2:$J$131,MATCH($B631,Account!$A$2:$A$131,0))&"-"&$C631&"-"&$D631,'Bill Report Reference'!$I$2:$I$59,0)),"") -> S.2321 | G631: =IFERROR(""&INDEX('Bill Report Reference'!$F$2:$F$59,MATCH(INDEX(Account!$J$2:$J$131,MATCH($B631,Account!$A$2:$A$131,0))&"-"&$C631&"-"&$D631,'Bill Report Reference'!$I$2:$I$59,0)),"") -> S.Rept.118-62 | H631: 7086287000 | I631: budget authority | K631: FALSE | M631: SRC-CRPT-118SRPT62 | N631: 219-220 | O631: Title III, NSF, Research and Related Activities (base) | P631: human-entered | Q631: 1 | R631: human-verified | S631: =IFERROR(""&INDEX('Bill Report Reference'!$G$2:$G$59,MATCH(INDEX(Account!$J$2:$J$131,MATCH($B631,Account!$A$2:$A$131,0))&"-"&$C631&"-"&$D631,'Bill Report Reference'!$I$2:$I$59,0)),"") -> https://www.congress.gov/118/bills/s2321/BILLS-118s2321rs.pdf | T631: =IFERROR(""&INDEX('Bill Report Reference'!$H$2:$H$59,MATCH(INDEX(Account!$J$2:$J$131,MATCH($B631,Account!$A$2:$A$131,0))&"-"&$C631&"-"&$D631,'Bill Report Reference'!$I$2:$I$59,0)),"") -> https://www.congress.gov/118/crpt/srpt62/CRPT-118srpt62.pdf
A632: OBS-0698 | B632: ACC-NSF-RRA | C632: 2024 | D632: House Reported | E632: House | F632: =IFERROR(""&INDEX('Bill Report Reference'!$E$2:$E$59,MATCH(INDEX(Account!$J$2:$J$131,MATCH($B632,Account!$A$2:$A$131,0))&"-"&$C632&"-"&$D632,'Bill Report Reference'!$I$2:$I$59,0)),"") -> H.R.5893 | G632: =IFERROR(""&INDEX('Bill Report Reference'!$F$2:$F$59,MATCH(INDEX(Account!$J$2:$J$131,MATCH($B632,Account!$A$2:$A$131,0))&"-"&$C632&"-"&$D632,'Bill Report Reference'!$I$2:$I$59,0)),"") -> JES_CJS_H.R.5893 | H632: 7776762000 | I632: budget authority | K632: FALSE | M632: SRC-EXPL-FY2024-HOUSE | N632: 170-171 | O632: Title III, NSF, Research and Related Activities (base) | P632: human-entered | Q632: 1 | R632: human-verified | S632: =IFERROR(""&INDEX('Bill Report Reference'!$G$2:$G$59,MATCH(INDEX(Account!$J$2:$J$131,MATCH($B632,Account!$A$2:$A$131,0))&"-"&$C632&"-"&$D632,'Bill Report Reference'!$I$2:$I$59,0)),"") -> https://www.congress.gov/118/bills/hr5893/BILLS-118hr5893ih.pdf | T632: =IFERROR(""&INDEX('Bill Report Reference'!$H$2:$H$59,MATCH(INDEX(Account!$J$2:$J$131,MATCH($B632,Account!$A$2:$A$131,0))&"-"&$C632&"-"&$D632,'Bill Report Reference'!$I$2:$I$59,0)),"") -> https://appropriations.house.gov/sites/evo-subsites/republicans-appropriations.house.gov/files/FY24-CJS-Explanatory-Materials.pdf
... A661: OBS-0727 | B661: ACC-NSF-RRA | C661: 2017 | D661: President's Budget | E661: N/A | F661: =IFERROR(""&INDEX('Bill Report Reference'!$E$2:$E$59,MATCH(INDEX(Account!$J$2:$J$131,MATCH($B661,Account!$A$2:$A$131,0))&"-"&$C661&"-"&$D661,'Bill Report Reference'!$I$2:$I$59,0)),"") -> PREX 2.8:2017/APP | G661: =IFERROR(""&INDEX('Bill Report Reference'!$F$2:$F$59,MATCH(INDEX(Account!$J$2:$J$131,MATCH($B661,Account!$A$2:$A$131,0))&"-"&$C661&"-"&$D661,'Bill Report Reference'!$I$2:$I$59,0)),"") -> N/A | H661: 6011910000 | I661: budget authority | K661: FALSE | M661: SRC-CRPT-114HRPT605 | N661: 114-115 | O661: Title III, NSF, Research and Related Activities (base) | P661: human-entered | Q661: 1 | R661: human-verified | S661: =IFERROR(""&INDEX('Bill Report Reference'!$G$2:$G$59,MATCH(INDEX(Account!$J$2:$J$131,MATCH($B661,Account!$A$2:$A$131,0))&"-"&$C661&"-"&$D661,'Bill Report Reference'!$I$2:$I$59,0)),"") -> https://www.govinfo.gov/content/pkg/BUDGET-2017-APP/pdf/BUDGET-2017-APP.pdf | T661: =IFERROR(""&INDEX('Bill Report Reference'!$H$2:$H$59,MATCH(INDEX(Account!$J$2:$J$131,MATCH($B661,Account!$A$2:$A$131,0))&"-"&$C661&"-"&$D661,'Bill Report Reference'!$I$2:$I$59,0)),"") -> N/A
A662: OBS-0728 | B662: ACC-NSF-RRA | C662: 2026 | D662: Enacted | E662: N/A | F662: =IFERROR(""&INDEX('Bill Report Reference'!$E$2:$E$59,MATCH(INDEX(Account!$J$2:$J$131,MATCH($B662,Account!$A$2:$A$131,0))&"-"&$C662&"-"&$D662,'Bill Report Reference'!$I$2:$I$59,0)),"") -> P.L.119-74 | G662: =IFERROR(""&INDEX('Bill Report Reference'!$F$2:$F$59,MATCH(INDEX(Account!$J$2:$J$131,MATCH($B662,Account!$A$2:$A$131,0))&"-"&$C662&"-"&$D662,'Bill Report Reference'!$I$2:$I$59,0)),"") -> JES_CJS_P.L.119-74 | H662: 118800000 | I662: budget authority | J662: defense | K662: FALSE | M662: SRC-EXPL-FY2026-PB | N662: 128-130 | O662: Title III, NSF, Research and Related Activities (defense) | P662: human-entered | Q662: 1 | R662: human-verified | S662: =IFERROR(""&INDEX('Bill Report Reference'!$G$2:$G$59,MATCH(INDEX(Account!$J$2:$J$131,MATCH($B662,Account!$A$2:$A$131,0))&"-"&$C662&"-"&$D662,'Bill Report Reference'!$I$2:$I$59,0)),"") -> https://www.govinfo.gov/content/pkg/PLAW-119publ74/pdf/PLAW-119publ74.pdf | T662: =IFERROR(""&INDEX('Bill Report Reference'!$H$2:$H$59,MATCH(INDEX(Account!$J$2:$J$131,MATCH($B662,Account!$A$2:$A$131,0))&"-"&$C662&"-"&$D662,'Bill Report Reference'!$I$2:$I$59,0)),"") -> https://rules.house.gov/sites/evo-subsites/rules.house.gov/files/documents/division-a-commerce-justice-science_0.pdf
A663: OBS-0729 | B663: ACC-NSF-RRA | C663: 2026 | D663: Senate Reported | E663: Senate | F663: =IFERROR(""&INDEX('Bill Report Reference'!$E$2:$E$59,MATCH(INDEX(Account!$J$2:$J$131,MATCH($B663,Account!$A$2:$A$131,0))&"-"&$C663&"-"&$D663,'Bill Report Reference'!$I$2:$I$59,0)),"") -> S.2354 | G663: =IFERROR(""&INDEX('Bill Report Reference'!$F$2:$F$59,MATCH(INDEX(Account!$J$2:$J$131,MATCH($B663,Account!$A$2:$A$131,0))&"-"&$C663&"-"&$D663,'Bill Report Reference'!$I$2:$I$59,0)),"") -> S.Rept.119-44 | H663: 109310000 | I663: budget authority | J663: defense | K663: FALSE | M663: SRC-CRPT-119SRPT44 | N663: 217-219 | O663: Title III, NSF, Research and Related Activities (defense) | P663: human-entered | Q663: 1 | R663: human-verified | S663: =IFERROR(""&INDEX('Bill Report Reference'!$G$2:$G$59,MATCH(INDEX(Account!$J$2:$J$131,MATCH($B663,Account!$A$2:$A$131,0))&"-"&$C663&"-"&$D663,'Bill Report Reference'!$I$2:$I$59,0)),"") -> https://www.congress.gov/119/bills/s2354/BILLS-119s2354rs.pdf | T663: =IFERROR(""&INDEX('Bill Report Reference'!$H$2:$H$59,MATCH(INDEX(Account!$J$2:$J$131,MATCH($B663,Account!$A$2:$A$131,0))&"-"&$C663&"-"&$D663,'Bill Report Reference'!$I$2:$I$59,0)),"") -> https://www.congress.gov/119/crpt/srpt44/CRPT-119srpt44.pdf
A664: OBS-0730 | B664: ACC-NSF-RRA | C664: 2026 | D664: House Reported | E664: House | F664: =IFERROR(""&INDEX('Bill Report Reference'!$E$2:$E$59,MATCH(INDEX(Account!$J$2:$J$131,MATCH($B664,Account!$A$2:$A$131,0))&"-"&$C664&"-"&$D664,'Bill Report Reference'!$I$2:$I$59,0)),"") -> H.R.5342 | G664: =IFERROR(""&INDEX('Bill Report Reference'!$F$2:$F$59,MATCH(INDEX(Account!$J$2:$J$131,MATCH($B664,Account!$A$2:$A$131,0))&"-"&$C664&"-"&$D664,'Bill Report Reference'!$I$2:$I$59,0)),"") -> H.Rept.119-272 | H664: 109310000 | I664: budget authority | J664: defense | K664: FALSE | M664: SRC-CRPT-119HRPT272 | N664: 256-257 | O664: Title III, NSF, Research and Related Activities (defense) | P664: human-entered | Q664: 1 | R664: human-verified | S664: =IFERROR(""&INDEX('Bill Report Reference'!$G$2:$G$59,MATCH(INDEX(Account!$J$2:$J$131,MATCH($B664,Account!$A$2:$A$131,0))&"-"&$C664&"-"&$D664,'Bill Report Reference'!$I$2:$I$59,0)),"") -> https://www.govinfo.gov/content/pkg/BILLS-119hr5342rh/pdf/BILLS-119hr5342rh.pdf | T664: =IFERROR(""&INDEX('Bill Report Reference'!$H$2:$H$59,MATCH(INDEX(Account!$J$2:$J$131,MATCH($B664,Account!$A$2:$A$131,0))&"-"&$C664&"-"&$D664,'Bill Report Reference'!$I$2:$I$59,0)),"") -> https://www.congress.gov/119/crpt/hrpt272/CRPT-119hrpt272.pdf
A665: OBS-0731 | B665: ACC-NSF-RRA | C665: 2026 | D665: President's Budget | E665: N/A | F665: =IFERROR(""&INDEX('Bill Report Reference'!$E$2:$E$59,MATCH(INDEX(Account!$J$2:$J$131,MATCH($B665,Account!$A$2:$A$131,0))&"-"&$C665&"-"&$D665,'Bill Report Reference'!$I$2:$I$59,0)),"") -> PREX 2.8:2026/APP | G665: =IFERROR(""&INDEX('Bill Report Reference'!$F$2:$F$59,MATCH(INDEX(Account!$J$2:$J$131,MATCH($B665,Account!$A$2:$A$131,0))&"-"&$C665&"-"&$D665,'Bill Report Reference'!$I$2:$I$59,0)),"") -> N/A | H665: 109310000 | I665: budget authority | J665: defense | K665: FALSE | M665: SRC-EXPL-FY2026-PB | N665: 128-130 | O665: Title III, NSF, Research and Related Activities (defense) | P665: human-entered | Q665: 1 | R665: human-verified | S665: =IFERROR(""&INDEX('Bill Report Reference'!$G$2:$G$59,MATCH(INDEX(Account!$J$2:$J$131,MATCH($B665,Account!$A$2:$A$131,0))&"-"&$C665&"-"&$D665,'Bill Report Reference'!$I$2:$I$59,0)),"") -> https://www.govinfo.gov/content/pkg/BUDGET-2026-APP/pdf/BUDGET-2026-APP.pdf | T665: =IFERROR(""&INDEX('Bill Report Reference'!$H$2:$H$59,MATCH(INDEX(Account!$J$2:$J$131,MATCH($B665,Account!$A$2:$A$131,0))&"-"&$C665&"-"&$D665,'Bill Report Reference'!$I$2:$I$59,0)),"") -> N/A
A666: OBS-0732 | B666: ACC-NSF-RRA | C666: 2025 | D666: Enacted | E666: N/A | F666: =IFERROR(""&INDEX('Bill Report Reference'!$E$2:$E$59,MATCH(INDEX(Account!$J$2:$J$131,MATCH($B666,Account!$A$2:$A$131,0))&"-"&$C666&"-"&$D666,'Bill Report Reference'!$I$2:$I$59,0)),"") -> P.L.119-4 | G666: =IFERROR(""&INDEX('Bill Report Reference'!$F$2:$F$59,MATCH(INDEX(Account!$J$2:$J$131,MATCH($B666,Account!$A$2:$A$131,0))&"-"&$C666&"-"&$D666,'Bill Report Reference'!$I$2:$I$59,0)),"") -> N/A | H666: 109310000 | I666: budget authority | J666: defense | K666: FALSE | M666: SRC-CRPT-119HRPT272 | N666: 256-257 | O666: Title III, NSF, Research and Related Activities (defense) | P666: human-entered | Q666: 1 | R666: human-verified | S666: =IFERROR(""&INDEX('Bill Report Reference'!$G$2:$G$59,MATCH(INDEX(Account!$J$2:$J$131,MATCH($B666,Account!$A$2:$A$131,0))&"-"&$C666&"-"&$D666,'Bill Report Reference'!$I$2:$I$59,0)),"") -> https://www.govinfo.gov/content/pkg/PLAW-119publ4/pdf/PLAW-119publ4.pdf | T666: =IFERROR(""&INDEX('Bill Report Reference'!$H$2:$H$59,MATCH(INDEX(Account!$J$2:$J$131,MATCH($B666,Account!$A$2:$A$131,0))&"-"&$C666&"-"&$D666,'Bill Report Reference'!$I$2:$I$59,0)),"") -> N/A
A667: OBS-0733 | B667: ACC-NSF-RRA | C667: 2025 | D667: Senate Reported | E667: Senate | F667: =IFERROR(""&INDEX('Bill Report Reference'!$E$2:$E$59,MATCH(INDEX(Account!$J$2:$J$131,MATCH($B667,Account!$A$2:$A$131,0))&"-"&$C667&"-"&$D667,'Bill Report Reference'!$I$2:$I$59,0)),"") -> S.4795 | G667: =IFERROR(""&INDEX('Bill Report Reference'!$F$2:$F$59,MATCH(INDEX(Account!$J$2:$J$131,MATCH($B667,Account!$A$2:$A$131,0))&"-"&$C667&"-"&$D667,'Bill Report Reference'!$I$2:$I$59,0)),"") -> S.Rept.118-198 | H667: 106000000 | I667: budget authority | J667: defense | K667: FALSE | M667: SRC-CRPT-118SRPT198 | N667: 227-228 | O667: Title III, NSF, Research and Related Activities (defense) | P667: human-entered | Q667: 1 | R667: human-verified | S667: =IFERROR(""&INDEX('Bill Report Reference'!$G$2:$G$59,MATCH(INDEX(Account!$J$2:$J$131,MATCH($B667,Account!$A$2:$A$131,0))&"-"&$C667&"-"&$D667,'Bill Report Reference'!$I$2:$I$59,0)),"") -> https://www.congress.gov/118/bills/s4795/BILLS-118s4795rs.pdf | T667: =IFERROR(""&INDEX('Bill Report Reference'!$H$2:$H$59,MATCH(INDEX(Account!$J$2:$J$131,MATCH($B667,Account!$A$2:$A$131,0))&"-"&$C667&"-"&$D667,'Bill Report Reference'!$I$2:$I$59,0)),"") -> https://www.congress.gov/118/crpt/srpt198/CRPT-118srpt198.pdf
A668: OBS-0734 | B668: ACC-NSF-RRA | C668: 2025 | D668: House Reported | E668: House | F668: =IFERROR(""&INDEX('Bill Report Reference'!$E$2:$E$59,MATCH(INDEX(Account!$J$2:$J$131,MATCH($B668,Account!$A$2:$A$131,0))&"-"&$C668&"-"&$D668,'Bill Report Reference'!$I$2:$I$59,0)),"") -> H.R.9026 | G668: =IFERROR(""&INDEX('Bill Report Reference'!$F$2:$F$59,MATCH(INDEX(Account!$J$2:$J$131,MATCH($B668,Account!$A$2:$A$131,0))&"-"&$C668&"-"&$D668,'Bill Report Reference'!$I$2:$I$59,0)),"") -> H.Rept.118-582 | H668: 109310000 | I668: budget authority | J668: defense | K668: FALSE | M668: SRC-CRPT-118HRPT582 | N668: 247-248 | O668: Title III, NSF, Research and Related Activities (defense) | P668: human-entered | Q668: 1 | R668: human-verified | S668: =IFERROR(""&INDEX('Bill Report Reference'!$G$2:$G$59,MATCH(INDEX(Account!$J$2:$J$131,MATCH($B668,Account!$A$2:$A$131,0))&"-"&$C668&"-"&$D668,'Bill Report Reference'!$I$2:$I$59,0)),"") -> https://www.govinfo.gov/content/pkg/BILLS-118hr9026rh/pdf/BILLS-118hr9026rh.pdf | T668: =IFERROR(""&INDEX('Bill Report Reference'!$H$2:$H$59,MATCH(INDEX(Account!$J$2:$J$131,MATCH($B668,Account!$A$2:$A$131,0))&"-"&$C668&"-"&$D668,'Bill Report Reference'!$I$2:$I$59,0)),"") -> https://www.congress.gov/118/crpt/hrpt582/CRPT-118hrpt582.pdf
A669: OBS-0735 | B669: ACC-NSF-RRA | C669: 2025 | D669: President's Budget | E669: N/A | F669: =IFERROR(""&INDEX('Bill Report Reference'!$E$2:$E$59,MATCH(INDEX(Account!$J$2:$J$131,MATCH($B669,Account!$A$2:$A$131,0))&"-"&$C669&"-"&$D669,'Bill Report Reference'!$I$2:$I$59,0)),"") -> PREX 2.8:2025/APP | G669: =IFERROR(""&INDEX('Bill Report Reference'!$F$2:$F$59,MATCH(INDEX(Account!$J$2:$J$131,MATCH($B669,Account!$A$2:$A$131,0))&"-"&$C669&"-"&$D669,'Bill Report Reference'!$I$2:$I$59,0)),"") -> N/A | H669: 106000000 | I669: budget authority | J669: defense | K669: FALSE | M669: SRC-CRPT-118HRPT582 | N669: 247-248 | O669: Title III, NSF, Research and Related Activities (defense) | P669: human-entered | Q669: 1 | R669: human-verified | S669: =IFERROR(""&INDEX('Bill Report Reference'!$G$2:$G$59,MATCH(INDEX(Account!$J$2:$J$131,MATCH($B669,Account!$A$2:$A$131,0))&"-"&$C669&"-"&$D669,'Bill Report Reference'!$I$2:$I$59,0)),"") -> https://www.govinfo.gov/content/pkg/BUDGET-2025-APP/pdf/BUDGET-2025-APP.pdf | T669: =IFERROR(""&INDEX('Bill Report Reference'!$H$2:$H$59,MATCH(INDEX(Account!$J$2:$J$131,MATCH($B669,Account!$A$2:$A$131,0))&"-"&$C669&"-"&$D669,'Bill Report Reference'!$I$2:$I$59,0)),"") -> N/A
A670: OBS-0736 | B670: ACC-NSF-RRA | C670: 2024 | D670: Enacted | E670: N/A | F670: =IFERROR(""&INDEX('Bill Report Reference'!$E$2:$E$59,MATCH(INDEX(Account!$J$2:$J$131,MATCH($B670,Account!$A$2:$A$131,0))&"-"&$C670&"-"&$D670,'Bill Report Reference'!$I$2:$I$59,0)),"") -> P.L.118-42 | G670: =IFERROR(""&INDEX('Bill Report Reference'!$F$2:$F$59,MATCH(INDEX(Account!$J$2:$J$131,MATCH($B670,Account!$A$2:$A$131,0))&"-"&$C670&"-"&$D670,'Bill Report Reference'!$I$2:$I$59,0)),"") -> JES_CJS_P.L.118-42 | H670: 109310000 | I670: budget authority | J670: defense | K670: FALSE | M670: SRC-CRPT-118HRPT582 | N670: 247-248 | O670: Title III, NSF, Research and Related Activities (defense) | P670: human-entered | Q670: 1 | R670: human-verified | S670: =IFERROR(""&INDEX('Bill Report Reference'!$G$2:$G$59,MATCH(INDEX(Account!$J$2:$J$131,MATCH($B670,Account!$A$2:$A$131,0))&"-"&$C670&"-"&$D670,'Bill Report Reference'!$I$2:$I$59,0)),"") -> https://www.govinfo.gov/content/pkg/PLAW-118publ42/pdf/PLAW-118publ42.pdf | T670: =IFERROR(""&INDEX('Bill Report Reference'!$H$2:$H$59,MATCH(INDEX(Account!$J$2:$J$131,MATCH($B670,Account!$A$2:$A$131,0))&"-"&$C670&"-"&$D670,'Bill Report Reference'!$I$2:$I$59,0)),"") -> https://docs.house.gov/billsthisweek/20240304/FY24%20CJS%20Conference%20JES%20scan%203.3.24.pdf
A671: OBS-0737 | B671: ACC-NSF-RRA | C671: 2024 | D671: Senate Reported | E671: Senate | F671: =IFERROR(""&INDEX('Bill Report Reference'!$E$2:$E$59,MATCH(INDEX(Account!$J$2:$J$131,MATCH($B671,Account!$A$2:$A$131,0))&"-"&$C671&"-"&$D671,'Bill Report Reference'!$I$2:$I$59,0)),"") -> S.2321 | G671: =IFERROR(""&INDEX('Bill Report Reference'!$F$2:$F$59,MATCH(INDEX(Account!$J$2:$J$131,MATCH($B671,Account!$A$2:$A$131,0))&"-"&$C671&"-"&$D671,'Bill Report Reference'!$I$2:$I$59,0)),"") -> S.Rept.118-62 | H671: 102000000 | I671: budget authority | J671: defense | K671: FALSE | M671: SRC-CRPT-118SRPT62 | N671: 219-220 | O671: Title III, NSF, Research and Related Activities (defense) | P671: human-entered | Q671: 1 | R671: human-verified | S671: =IFERROR(""&INDEX('Bill Report Reference'!$G$2:$G$59,MATCH(INDEX(Account!$J$2:$J$131,MATCH($B671,Account!$A$2:$A$131,0))&"-"&$C671&"-"&$D671,'Bill Report Reference'!$I$2:$I$59,0)),"") -> https://www.congress.gov/118/bills/s2321/BILLS-118s2321rs.pdf | T671: =IFERROR(""&INDEX('Bill Report Reference'!$H$2:$H$59,MATCH(INDEX(Account!$J$2:$J$131,MATCH($B671,Account!$A$2:$A$131,0))&"-"&$C671&"-"&$D671,'Bill Report Reference'!$I$2:$I$59,0)),"") -> https://www.congress.gov/118/crpt/srpt62/CRPT-118srpt62.pdf
A672: OBS-0738 | B672: ACC-NSF-RRA | C672: 2024 | D672: House Reported | E672: House | F672: =IFERROR(""&INDEX('Bill Report Reference'!$E$2:$E$59,MATCH(INDEX(Account!$J$2:$J$131,MATCH($B672,Account!$A$2:$A$131,0))&"-"&$C672&"-"&$D672,'Bill Report Reference'!$I$2:$I$59,0)),"") -> H.R.5893 | G672: =IFERROR(""&INDEX('Bill Report Reference'!$F$2:$F$59,MATCH(INDEX(Account!$J$2:$J$131,MATCH($B672,Account!$A$2:$A$131,0))&"-"&$C672&"-"&$D672,'Bill Report Reference'!$I$2:$I$59,0)),"") -> JES_CJS_H.R.5893 | H672: 89884000 | I672: budget authority | J672: defense | K672: FALSE | M672: SRC-EXPL-FY2024-HOUSE | N672: 170-171 | O672: Title III, NSF, Research and Related Activities (defense) | P672: human-entered | Q672: 1 | R672: human-verified | S672: =IFERROR(""&INDEX('Bill Report Reference'!$G$2:$G$59,MATCH(INDEX(Account!$J$2:$J$131,MATCH($B672,Account!$A$2:$A$131,0))&"-"&$C672&"-"&$D672,'Bill Report Reference'!$I$2:$I$59,0)),"") -> https://www.congress.gov/118/bills/hr5893/BILLS-118hr5893ih.pdf | T672: =IFERROR(""&INDEX('Bill Report Reference'!$H$2:$H$59,MATCH(INDEX(Account!$J$2:$J$131,MATCH($B672,Account!$A$2:$A$131,0))&"-"&$C672&"-"&$D672,'Bill Report Reference'!$I$2:$I$59,0)),"") -> https://appropriations.house.gov/sites/evo-subsites/republicans-appropriations.house.gov/files/FY24-CJS-Explanatory-Materials.pdf
A673: OBS-0739 | B673: ACC-NSF-RRA | C673: 2024 | D673: President's Budget | E673: N/A | F673: =IFERROR(""&INDEX('Bill Report Reference'!$E$2:$E$59,MATCH(INDEX(Account!$J$2:$J$131,MATCH($B673,Account!$A$2:$A$131,0))&"-"&$C673&"-"&$D673,'Bill Report Reference'!$I$2:$I$59,0)),"") -> PREX 2.8:2024/APP | G673: =IFERROR(""&INDEX('Bill Report Reference'!$F$2:$F$59,MATCH(INDEX(Account!$J$2:$J$131,MATCH($B673,Account!$A$2:$A$131,0))&"-"&$C673&"-"&$D673,'Bill Report Reference'!$I$2:$I$59,0)),"") -> N/A | H673: 102000000 | I673: budget authority | J673: defense | K673: FALSE | M673: SRC-CRPT-118SRPT62 | N673: 219-220 | O673: Title III, NSF, Research and Related Activities (defense) | P673: human-entered | Q673: 1 | R673: human-verified | S673: =IFERROR(""&INDEX('Bill Report Reference'!$G$2:$G$59,MATCH(INDEX(Account!$J$2:$J$131,MATCH($B673,Account!$A$2:$A$131,0))&"-"&$C673&"-"&$D673,'Bill Report Reference'!$I$2:$I$59,0)),"") -> https://www.govinfo.gov/content/pkg/BUDGET-2024-APP/pdf/BUDGET-2024-APP.pdf | T673: =IFERROR(""&INDEX('Bill Report Reference'!$H$2:$H$59,MATCH(INDEX(Account!$J$2:$J$131,MATCH($B673,Account!$A$2:$A$131,0))&"-"&$C673&"-"&$D673,'Bill Report Reference'!$I$2:$I$59,0)),"") -> N/A
... A701: OBS-0767 | B701: ACC-NSF-RRA | C701: 2017 | D701: President's Budget | E701: N/A | F701: =IFERROR(""&INDEX('Bill Report Reference'!$E$2:$E$59,MATCH(INDEX(Account!$J$2:$J$131,MATCH($B701,Account!$A$2:$A$131,0))&"-"&$C701&"-"&$D701,'Bill Report Reference'!$I$2:$I$59,0)),"") -> PREX 2.8:2017/APP | G701: =IFERROR(""&INDEX('Bill Report Reference'!$F$2:$F$59,MATCH(INDEX(Account!$J$2:$J$131,MATCH($B701,Account!$A$2:$A$131,0))&"-"&$C701&"-"&$D701,'Bill Report Reference'!$I$2:$I$59,0)),"") -> N/A | H701: 67520000 | I701: budget authority | J701: defense | K701: FALSE | M701: SRC-CRPT-114HRPT605 | N701: 114-115 | O701: Title III, NSF, Research and Related Activities (defense) | P701: human-entered | Q701: 1 | R701: human-verified | S701: =IFERROR(""&INDEX('Bill Report Reference'!$G$2:$G$59,MATCH(INDEX(Account!$J$2:$J$131,MATCH($B701,Account!$A$2:$A$131,0))&"-"&$C701&"-"&$D701,'Bill Report Reference'!$I$2:$I$59,0)),"") -> https://www.govinfo.gov/content/pkg/BUDGET-2017-APP/pdf/BUDGET-2017-APP.pdf | T701: =IFERROR(""&INDEX('Bill Report Reference'!$H$2:$H$59,MATCH(INDEX(Account!$J$2:$J$131,MATCH($B701,Account!$A$2:$A$131,0))&"-"&$C701&"-"&$D701,'Bill Report Reference'!$I$2:$I$59,0)),"") -> N/A
A702: OBS-0769 | B702: ACC-NSF-RRA | C702: 2025 | D702: Senate Reported | E702: Senate | F702: =IFERROR(""&INDEX('Bill Report Reference'!$E$2:$E$59,MATCH(INDEX(Account!$J$2:$J$131,MATCH($B702,Account!$A$2:$A$131,0))&"-"&$C702&"-"&$D702,'Bill Report Reference'!$I$2:$I$59,0)),"") -> S.4795 | G702: =IFERROR(""&INDEX('Bill Report Reference'!$F$2:$F$59,MATCH(INDEX(Account!$J$2:$J$131,MATCH($B702,Account!$A$2:$A$131,0))&"-"&$C702&"-"&$D702,'Bill Report Reference'!$I$2:$I$59,0)),"") -> S.Rept.118-198 | H702: 973000000 | I702: supplemental | K702: FALSE | M702: SRC-CRPT-118SRPT198 | N702: 227-228 | O702: Title III, NSF, Research and Related Activities (emergency) | P702: human-entered | Q702: 1 | R702: human-verified | S702: =IFERROR(""&INDEX('Bill Report Reference'!$G$2:$G$59,MATCH(INDEX(Account!$J$2:$J$131,MATCH($B702,Account!$A$2:$A$131,0))&"-"&$C702&"-"&$D702,'Bill Report Reference'!$I$2:$I$59,0)),"") -> https://www.congress.gov/118/bills/s4795/BILLS-118s4795rs.pdf | T702: =IFERROR(""&INDEX('Bill Report Reference'!$H$2:$H$59,MATCH(INDEX(Account!$J$2:$J$131,MATCH($B702,Account!$A$2:$A$131,0))&"-"&$C702&"-"&$D702,'Bill Report Reference'!$I$2:$I$59,0)),"") -> https://www.congress.gov/118/crpt/srpt198/CRPT-118srpt198.pdf
A703: OBS-0771 | B703: ACC-NSF-RRA | C703: 2025 | D703: President's Budget | E703: N/A | F703: =IFERROR(""&INDEX('Bill Report Reference'!$E$2:$E$59,MATCH(INDEX(Account!$J$2:$J$131,MATCH($B703,Account!$A$2:$A$131,0))&"-"&$C703&"-"&$D703,'Bill Report Reference'!$I$2:$I$59,0)),"") -> PREX 2.8:2025/APP | G703: =IFERROR(""&INDEX('Bill Report Reference'!$F$2:$F$59,MATCH(INDEX(Account!$J$2:$J$131,MATCH($B703,Account!$A$2:$A$131,0))&"-"&$C703&"-"&$D703,'Bill Report Reference'!$I$2:$I$59,0)),"") -> N/A | H703: 420000000 | I703: supplemental | K703: FALSE | M703: SRC-CRPT-118HRPT582 | N703: 247-248 | O703: Title III, NSF, Research and Related Activities (emergency) | P703: human-entered | Q703: 1 | R703: human-verified | S703: =IFERROR(""&INDEX('Bill Report Reference'!$G$2:$G$59,MATCH(INDEX(Account!$J$2:$J$131,MATCH($B703,Account!$A$2:$A$131,0))&"-"&$C703&"-"&$D703,'Bill Report Reference'!$I$2:$I$59,0)),"") -> https://www.govinfo.gov/content/pkg/BUDGET-2025-APP/pdf/BUDGET-2025-APP.pdf | T703: =IFERROR(""&INDEX('Bill Report Reference'!$H$2:$H$59,MATCH(INDEX(Account!$J$2:$J$131,MATCH($B703,Account!$A$2:$A$131,0))&"-"&$C703&"-"&$D703,'Bill Report Reference'!$I$2:$I$59,0)),"") -> N/A
A704: OBS-0773 | B704: ACC-NSF-RRA | C704: 2024 | D704: Senate Reported | E704: Senate | F704: =IFERROR(""&INDEX('Bill Report Reference'!$E$2:$E$59,MATCH(INDEX(Account!$J$2:$J$131,MATCH($B704,Account!$A$2:$A$131,0))&"-"&$C704&"-"&$D704,'Bill Report Reference'!$I$2:$I$59,0)),"") -> S.2321 | G704: =IFERROR(""&INDEX('Bill Report Reference'!$F$2:$F$59,MATCH(INDEX(Account!$J$2:$J$131,MATCH($B704,Account!$A$2:$A$131,0))&"-"&$C704&"-"&$D704,'Bill Report Reference'!$I$2:$I$59,0)),"") -> S.Rept.118-62 | H704: 420000000 | I704: supplemental | K704: FALSE | M704: SRC-CRPT-118SRPT62 | N704: 219-220 | O704: Title III, NSF, Research and Related Activities (emergency) | P704: human-entered | Q704: 1 | R704: human-verified | S704: =IFERROR(""&INDEX('Bill Report Reference'!$G$2:$G$59,MATCH(INDEX(Account!$J$2:$J$131,MATCH($B704,Account!$A$2:$A$131,0))&"-"&$C704&"-"&$D704,'Bill Report Reference'!$I$2:$I$59,0)),"") -> https://www.congress.gov/118/bills/s2321/BILLS-118s2321rs.pdf | T704: =IFERROR(""&INDEX('Bill Report Reference'!$H$2:$H$59,MATCH(INDEX(Account!$J$2:$J$131,MATCH($B704,Account!$A$2:$A$131,0))&"-"&$C704&"-"&$D704,'Bill Report Reference'!$I$2:$I$59,0)),"") -> https://www.congress.gov/118/crpt/srpt62/CRPT-118srpt62.pdf
A705: OBS-0774 | B705: ACC-NSF-RRA | C705: 2024 | D705: House Reported | E705: House | F705: =IFERROR(""&INDEX('Bill Report Reference'!$E$2:$E$59,MATCH(INDEX(Account!$J$2:$J$131,MATCH($B705,Account!$A$2:$A$131,0))&"-"&$C705&"-"&$D705,'Bill Report Reference'!$I$2:$I$59,0)),"") -> H.R.5893 | G705: =IFERROR(""&INDEX('Bill Report Reference'!$F$2:$F$59,MATCH(INDEX(Account!$J$2:$J$131,MATCH($B705,Account!$A$2:$A$131,0))&"-"&$C705&"-"&$D705,'Bill Report Reference'!$I$2:$I$59,0)),"") -> JES_CJS_H.R.5893 | H705: 0 | I705: supplemental | K705: FALSE | M705: SRC-EXPL-FY2024-HOUSE | N705: 170-171 | O705: Title III, NSF, Research and Related Activities (emergency) | P705: human-entered | Q705: 1 | R705: human-verified | S705: =IFERROR(""&INDEX('Bill Report Reference'!$G$2:$G$59,MATCH(INDEX(Account!$J$2:$J$131,MATCH($B705,Account!$A$2:$A$131,0))&"-"&$C705&"-"&$D705,'Bill Report Reference'!$I$2:$I$59,0)),"") -> https://www.congress.gov/118/bills/hr5893/BILLS-118hr5893ih.pdf | T705: =IFERROR(""&INDEX('Bill Report Reference'!$H$2:$H$59,MATCH(INDEX(Account!$J$2:$J$131,MATCH($B705,Account!$A$2:$A$131,0))&"-"&$C705&"-"&$D705,'Bill Report Reference'!$I$2:$I$59,0)),"") -> https://appropriations.house.gov/sites/evo-subsites/republicans-appropriations.house.gov/files/FY24-CJS-Explanatory-Materials.pdf
A706: OBS-0776 | B706: ACC-NSF-RRA | C706: 2023 | D706: Enacted | E706: N/A | F706: =IFERROR(""&INDEX('Bill Report Reference'!$E$2:$E$59,MATCH(INDEX(Account!$J$2:$J$131,MATCH($B706,Account!$A$2:$A$131,0))&"-"&$C706&"-"&$D706,'Bill Report Reference'!$I$2:$I$59,0)),"") -> P.L.117-328 | G706: =IFERROR(""&INDEX('Bill Report Reference'!$F$2:$F$59,MATCH(INDEX(Account!$J$2:$J$131,MATCH($B706,Account!$A$2:$A$131,0))&"-"&$C706&"-"&$D706,'Bill Report Reference'!$I$2:$I$59,0)),"") -> JES_CJS_P.L.117-328 | H706: 820662000 | I706: supplemental | J706: supplemental_act | K706: FALSE | M706: SRC-CRPT-118SRPT62 | N706: 224 | O706: P.L. 117-328, Division N, Title III, 136 Stat. 5206: two appropriations to "Research and Related Activities", $2,500,000 + $818,162,000 = $820,662,000 (the report prints the sum). | P706: human-entered | Q706: 1 | R706: human-verified | S706: =IFERROR(""&INDEX('Bill Report Reference'!$G$2:$G$59,MATCH(INDEX(Account!$J$2:$J$131,MATCH($B706,Account!$A$2:$A$131,0))&"-"&$C706&"-"&$D706,'Bill Report Reference'!$I$2:$I$59,0)),"") -> https://www.govinfo.gov/content/pkg/PLAW-117publ328/pdf/PLAW-117publ328.pdf | T706: =IFERROR(""&INDEX('Bill Report Reference'!$H$2:$H$59,MATCH(INDEX(Account!$J$2:$J$131,MATCH($B706,Account!$A$2:$A$131,0))&"-"&$C706&"-"&$D706,'Bill Report Reference'!$I$2:$I$59,0)),"") -> https://www.govinfo.gov/content/pkg/CPRT-117HPRT50347/pdf/CPRT-117HPRT50347.pdf
A707: OBS-0777 | B707: ACC-NSF-RRA | C707: 2023 | D707: Senate Reported | E707: Senate | F707: =IFERROR(""&INDEX('Bill Report Reference'!$E$2:$E$59,MATCH(INDEX(Account!$J$2:$J$131,MATCH($B707,Account!$A$2:$A$131,0))&"-"&$C707&"-"&$D707,'Bill Report Reference'!$I$2:$I$59,0)),"") -> S.4664 | G707: =IFERROR(""&INDEX('Bill Report Reference'!$F$2:$F$59,MATCH(INDEX(Account!$J$2:$J$131,MATCH($B707,Account!$A$2:$A$131,0))&"-"&$C707&"-"&$D707,'Bill Report Reference'!$I$2:$I$59,0)),"") -> JES_CJS_S.4664 | H707: 0 | I707: supplemental | K707: FALSE | M707: SRC-EXPL-FY2023-SENATE | N707: 215-216 | O707: Title III, NSF, Research and Related Activities (emergency) | P707: human-entered | Q707: 1 | R707: human-verified | S707: =IFERROR(""&INDEX('Bill Report Reference'!$G$2:$G$59,MATCH(INDEX(Account!$J$2:$J$131,MATCH($B707,Account!$A$2:$A$131,0))&"-"&$C707&"-"&$D707,'Bill Report Reference'!$I$2:$I$59,0)),"") -> https://www.congress.gov/117/bills/s4664/BILLS-117s4664is.pdf | T707: =IFERROR(""&INDEX('Bill Report Reference'!$H$2:$H$59,MATCH(INDEX(Account!$J$2:$J$131,MATCH($B707,Account!$A$2:$A$131,0))&"-"&$C707&"-"&$D707,'Bill Report Reference'!$I$2:$I$59,0)),"") -> https://www.appropriations.senate.gov/imo/media/doc/CJSFY23RPT.PDF
A708: OBS-0781 | B708: ACC-NSF-RRA | C708: 2022 | D708: Senate Reported | E708: Senate | F708: =IFERROR(""&INDEX('Bill Report Reference'!$E$2:$E$59,MATCH(INDEX(Account!$J$2:$J$131,MATCH($B708,Account!$A$2:$A$131,0))&"-"&$C708&"-"&$D708,'Bill Report Reference'!$I$2:$I$59,0)),"") -> S.3042 | G708: =IFERROR(""&INDEX('Bill Report Reference'!$F$2:$F$59,MATCH(INDEX(Account!$J$2:$J$131,MATCH($B708,Account!$A$2:$A$131,0))&"-"&$C708&"-"&$D708,'Bill Report Reference'!$I$2:$I$59,0)),"") -> JES_CJS_S.3042 | H708: 0 | I708: supplemental | K708: FALSE | M708: SRC-EXPL-FY2022-SENATE | N708: 207-208 | O708: Title III, NSF, Research and Related Activities (emergency) | P708: human-entered | Q708: 1 | R708: human-verified | S708: =IFERROR(""&INDEX('Bill Report Reference'!$G$2:$G$59,MATCH(INDEX(Account!$J$2:$J$131,MATCH($B708,Account!$A$2:$A$131,0))&"-"&$C708&"-"&$D708,'Bill Report Reference'!$I$2:$I$59,0)),"") -> https://www.congress.gov/117/bills/s3042/BILLS-117s3042is.pdf | T708: =IFERROR(""&INDEX('Bill Report Reference'!$H$2:$H$59,MATCH(INDEX(Account!$J$2:$J$131,MATCH($B708,Account!$A$2:$A$131,0))&"-"&$C708&"-"&$D708,'Bill Report Reference'!$I$2:$I$59,0)),"") -> https://www.appropriations.senate.gov/imo/media/doc/CJSRept_Final.PDF
A709: OBS-0785 | B709: ACC-NSF-RRA | C709: 2021 | D709: Senate Reported | E709: Senate | F709: =IFERROR(""&INDEX('Bill Report Reference'!$E$2:$E$59,MATCH(INDEX(Account!$J$2:$J$131,MATCH($B709,Account!$A$2:$A$131,0))&"-"&$C709&"-"&$D709,'Bill Report Reference'!$I$2:$I$59,0)),"") -> N/A | G709: =IFERROR(""&INDEX('Bill Report Reference'!$F$2:$F$59,MATCH(INDEX(Account!$J$2:$J$131,MATCH($B709,Account!$A$2:$A$131,0))&"-"&$C709&"-"&$D709,'Bill Report Reference'!$I$2:$I$59,0)),"") -> JES_CJS_FY2021-Senate | H709: 0 | I709: supplemental | K709: FALSE | M709: SRC-EXPL-FY2021-SENATE | N709: 197-199 | O709: Title III, NSF, Research and Related Activities (emergency) | P709: human-entered | Q709: 1 | R709: human-verified | S709: =IFERROR(""&INDEX('Bill Report Reference'!$G$2:$G$59,MATCH(INDEX(Account!$J$2:$J$131,MATCH($B709,Account!$A$2:$A$131,0))&"-"&$C709&"-"&$D709,'Bill Report Reference'!$I$2:$I$59,0)),"") -> https://www.appropriations.senate.gov/imo/media/doc/CJSFY2021.pdf | T709: =IFERROR(""&INDEX('Bill Report Reference'!$H$2:$H$59,MATCH(INDEX(Account!$J$2:$J$131,MATCH($B709,Account!$A$2:$A$131,0))&"-"&$C709&"-"&$D709,'Bill Report Reference'!$I$2:$I$59,0)),"") -> https://www.appropriations.senate.gov/imo/media/doc/CJSRept.pdf
A710: OBS-0788 | B710: ACC-NSF-RRA | C710: 2020 | D710: Enacted | E710: N/A | F710: =IFERROR(""&INDEX('Bill Report Reference'!$E$2:$E$59,MATCH(INDEX(Account!$J$2:$J$131,MATCH($B710,Account!$A$2:$A$131,0))&"-"&$C710&"-"&$D710,'Bill Report Reference'!$I$2:$I$59,0)),"") -> P.L.116-93 | G710: =IFERROR(""&INDEX('Bill Report Reference'!$F$2:$F$59,MATCH(INDEX(Account!$J$2:$J$131,MATCH($B710,Account!$A$2:$A$131,0))&"-"&$C710&"-"&$D710,'Bill Report Reference'!$I$2:$I$59,0)),"") -> JES_CJS_P.L.116-93 | H710: 75000000 | I710: supplemental | J710: supplemental_act | K710: FALSE | M710: SRC-CRPT-116HRPT455 | N710: 196 | O710: P.L. 116-136 (CARES Act), Division B (Emergency Appropriations for Coronavirus Health Response and Agency Operations), Title III, 134 Stat. 514: 'For an additional amount for "Research and Related Activities", $75,000,000 ... to prevent, prepare for, and respond to coronavirus' -- designated an emergency requirement. | P710: human-entered | Q710: 1 | R710: human-verified | S710: =IFERROR(""&INDEX('Bill Report Reference'!$G$2:$G$59,MATCH(INDEX(Account!$J$2:$J$131,MATCH($B710,Account!$A$2:$A$131,0))&"-"&$C710&"-"&$D710,'Bill Report Reference'!$I$2:$I$59,0)),"") -> https://www.congress.gov/116/plaws/publ93/PLAW-116publ93.pdf | T710: =IFERROR(""&INDEX('Bill Report Reference'!$H$2:$H$59,MATCH(INDEX(Account!$J$2:$J$131,MATCH($B710,Account!$A$2:$A$131,0))&"-"&$C710&"-"&$D710,'Bill Report Reference'!$I$2:$I$59,0)),"") -> https://docs.house.gov/billsthisweek/20191216/BILLS-116HR1158SA-JES-DIVISION-B.pdf
A711: OBS-0796 | B711: ACC-NSF-RRA | C711: 2018 | D711: Enacted | E711: N/A | F711: =IFERROR(""&INDEX('Bill Report Reference'!$E$2:$E$59,MATCH(INDEX(Account!$J$2:$J$131,MATCH($B711,Account!$A$2:$A$131,0))&"-"&$C711&"-"&$D711,'Bill Report Reference'!$I$2:$I$59,0)),"") -> P.L.115-141 | G711: =IFERROR(""&INDEX('Bill Report Reference'!$F$2:$F$59,MATCH(INDEX(Account!$J$2:$J$131,MATCH($B711,Account!$A$2:$A$131,0))&"-"&$C711&"-"&$D711,'Bill Report Reference'!$I$2:$I$59,0)),"") -> JES_CJS_P.L.115-141 | H711: 16300000 | I711: supplemental | J711: supplemental_act | K711: FALSE | M711: SRC-CRPT-115HRPT704 | N711: 134 | O711: P.L. 115-123, Division B, Title III, 132 Stat. 72: 'For an additional amount for "Research and Related Activities" ... to repair National Science Foundation radio observatory facilities damaged by hurricanes that occurred during 2017, $16,300,000' -- designated an emergency requirement. Also S.Rept. 115-275 p.161. | P711: human-entered | Q711: 1 | R711: human-verified | S711: =IFERROR(""&INDEX('Bill Report Reference'!$G$2:$G$59,MATCH(INDEX(Account!$J$2:$J$131,MATCH($B711,Account!$A$2:$A$131,0))&"-"&$C711&"-"&$D711,'Bill Report Reference'!$I$2:$I$59,0)),"") -> https://www.congress.gov/115/plaws/publ141/PLAW-115publ141.pdf | T711: =IFERROR(""&INDEX('Bill Report Reference'!$H$2:$H$59,MATCH(INDEX(Account!$J$2:$J$131,MATCH($B711,Account!$A$2:$A$131,0))&"-"&$C711&"-"&$D711,'Bill Report Reference'!$I$2:$I$59,0)),"") -> https://www.govinfo.gov/content/pkg/CPRT-115HPRT29456/pdf/CPRT-115HPRT29456.pdf
A712: OBS-0804 | B712: ACC-NSF-MREFC | C712: 2026 | D712: Enacted | E712: N/A | F712: =IFERROR(""&INDEX('Bill Report Reference'!$E$2:$E$59,MATCH(INDEX(Account!$J$2:$J$131,MATCH($B712,Account!$A$2:$A$131,0))&"-"&$C712&"-"&$D712,'Bill Report Reference'!$I$2:$I$59,0)),"") -> P.L.119-74 | G712: =IFERROR(""&INDEX('Bill Report Reference'!$F$2:$F$59,MATCH(INDEX(Account!$J$2:$J$131,MATCH($B712,Account!$A$2:$A$131,0))&"-"&$C712&"-"&$D712,'Bill Report Reference'!$I$2:$I$59,0)),"") -> JES_CJS_P.L.119-74 | H712: 251000000 | I712: budget authority | K712: FALSE | M712: SRC-EXPL-FY2026-PB | N712: 128-130 | O712: Title III, NSF, Major Research Equipment and Facilities Construction (base) | P712: human-entered | Q712: 1 | R712: human-verified | S712: =IFERROR(""&INDEX('Bill Report Reference'!$G$2:$G$59,MATCH(INDEX(Account!$J$2:$J$131,MATCH($B712,Account!$A$2:$A$131,0))&"-"&$C712&"-"&$D712,'Bill Report Reference'!$I$2:$I$59,0)),"") -> https://www.govinfo.gov/content/pkg/PLAW-119publ74/pdf/PLAW-119publ74.pdf | T712: =IFERROR(""&INDEX('Bill Report Reference'!$H$2:$H$59,MATCH(INDEX(Account!$J$2:$J$131,MATCH($B712,Account!$A$2:$A$131,0))&"-"&$C712&"-"&$D712,'Bill Report Reference'!$I$2:$I$59,0)),"") -> https://rules.house.gov/sites/evo-subsites/rules.house.gov/files/documents/division-a-commerce-justice-science_0.pdf
A713: OBS-0805 | B713: ACC-NSF-MREFC | C713: 2026 | D713: Senate Reported | E713: Senate | F713: =IFERROR(""&INDEX('Bill Report Reference'!$E$2:$E$59,MATCH(INDEX(Account!$J$2:$J$131,MATCH($B713,Account!$A$2:$A$131,0))&"-"&$C713&"-"&$D713,'Bill Report Reference'!$I$2:$I$59,0)),"") -> S.2354 | G713: =IFERROR(""&INDEX('Bill Report Reference'!$F$2:$F$59,MATCH(INDEX(Account!$J$2:$J$131,MATCH($B713,Account!$A$2:$A$131,0))&"-"&$C713&"-"&$D713,'Bill Report Reference'!$I$2:$I$59,0)),"") -> S.Rept.119-44 | H713: 350000000 | I713: budget authority | K713: FALSE | M713: SRC-CRPT-119SRPT44 | N713: 217-219 | O713: Title III, NSF, Major Research Equipment and Facilities Construction (base) | P713: human-entered | Q713: 1 | R713: human-verified | S713: =IFERROR(""&INDEX('Bill Report Reference'!$G$2:$G$59,MATCH(INDEX(Account!$J$2:$J$131,MATCH($B713,Account!$A$2:$A$131,0))&"-"&$C713&"-"&$D713,'Bill Report Reference'!$I$2:$I$59,0)),"") -> https://www.congress.gov/119/bills/s2354/BILLS-119s2354rs.pdf | T713: =IFERROR(""&INDEX('Bill Report Reference'!$H$2:$H$59,MATCH(INDEX(Account!$J$2:$J$131,MATCH($B713,Account!$A$2:$A$131,0))&"-"&$C713&"-"&$D713,'Bill Report Reference'!$I$2:$I$59,0)),"") -> https://www.congress.gov/119/crpt/srpt44/CRPT-119srpt44.pdf
A714: OBS-0806 | B714: ACC-NSF-MREFC | C714: 2026 | D714: House Reported | E714: House | F714: =IFERROR(""&INDEX('Bill Report Reference'!$E$2:$E$59,MATCH(INDEX(Account!$J$2:$J$131,MATCH($B714,Account!$A$2:$A$131,0))&"-"&$C714&"-"&$D714,'Bill Report Reference'!$I$2:$I$59,0)),"") -> H.R.5342 | G714: =IFERROR(""&INDEX('Bill Report Reference'!$F$2:$F$59,MATCH(INDEX(Account!$J$2:$J$131,MATCH($B714,Account!$A$2:$A$131,0))&"-"&$C714&"-"&$D714,'Bill Report Reference'!$I$2:$I$59,0)),"") -> H.Rept.119-272 | H714: 251000000 | I714: budget authority | K714: FALSE | M714: SRC-CRPT-119HRPT272 | N714: 256-257 | O714: Title III, NSF, Major Research Equipment and Facilities Construction (base) | P714: human-entered | Q714: 1 | R714: human-verified | S714: =IFERROR(""&INDEX('Bill Report Reference'!$G$2:$G$59,MATCH(INDEX(Account!$J$2:$J$131,MATCH($B714,Account!$A$2:$A$131,0))&"-"&$C714&"-"&$D714,'Bill Report Reference'!$I$2:$I$59,0)),"") -> https://www.govinfo.gov/content/pkg/BILLS-119hr5342rh/pdf/BILLS-119hr5342rh.pdf | T714: =IFERROR(""&INDEX('Bill Report Reference'!$H$2:$H$59,MATCH(INDEX(Account!$J$2:$J$131,MATCH($B714,Account!$A$2:$A$131,0))&"-"&$C714&"-"&$D714,'Bill Report Reference'!$I$2:$I$59,0)),"") -> https://www.congress.gov/119/crpt/hrpt272/CRPT-119hrpt272.pdf
A715: OBS-0807 | B715: ACC-NSF-MREFC | C715: 2026 | D715: President's Budget | E715: N/A | F715: =IFERROR(""&INDEX('Bill Report Reference'!$E$2:$E$59,MATCH(INDEX(Account!$J$2:$J$131,MATCH($B715,Account!$A$2:$A$131,0))&"-"&$C715&"-"&$D715,'Bill Report Reference'!$I$2:$I$59,0)),"") -> PREX 2.8:2026/APP | G715: =IFERROR(""&INDEX('Bill Report Reference'!$F$2:$F$59,MATCH(INDEX(Account!$J$2:$J$131,MATCH($B715,Account!$A$2:$A$131,0))&"-"&$C715&"-"&$D715,'Bill Report Reference'!$I$2:$I$59,0)),"") -> N/A | H715: 251000000 | I715: budget authority | K715: FALSE | M715: SRC-EXPL-FY2026-PB | N715: 128-130 | O715: Title III, NSF, Major Research Equipment and Facilities Construction (base) | P715: human-entered | Q715: 1 | R715: human-verified | S715: =IFERROR(""&INDEX('Bill Report Reference'!$G$2:$G$59,MATCH(INDEX(Account!$J$2:$J$131,MATCH($B715,Account!$A$2:$A$131,0))&"-"&$C715&"-"&$D715,'Bill Report Reference'!$I$2:$I$59,0)),"") -> https://www.govinfo.gov/content/pkg/BUDGET-2026-APP/pdf/BUDGET-2026-APP.pdf | T715: =IFERROR(""&INDEX('Bill Report Reference'!$H$2:$H$59,MATCH(INDEX(Account!$J$2:$J$131,MATCH($B715,Account!$A$2:$A$131,0))&"-"&$C715&"-"&$D715,'Bill Report Reference'!$I$2:$I$59,0)),"") -> N/A
A716: OBS-0808 | B716: ACC-NSF-MREFC | C716: 2025 | D716: Enacted | E716: N/A | F716: =IFERROR(""&INDEX('Bill Report Reference'!$E$2:$E$59,MATCH(INDEX(Account!$J$2:$J$131,MATCH($B716,Account!$A$2:$A$131,0))&"-"&$C716&"-"&$D716,'Bill Report Reference'!$I$2:$I$59,0)),"") -> P.L.119-4 | G716: =IFERROR(""&INDEX('Bill Report Reference'!$F$2:$F$59,MATCH(INDEX(Account!$J$2:$J$131,MATCH($B716,Account!$A$2:$A$131,0))&"-"&$C716&"-"&$D716,'Bill Report Reference'!$I$2:$I$59,0)),"") -> N/A | H716: 0 | I716: budget authority | K716: FALSE | M716: SRC-CRPT-119HRPT272 | N716: 256-257 | O716: Title III, NSF, Major Research Equipment and Facilities Construction (base) | P716: human-entered | Q716: 1 | R716: human-verified | S716: =IFERROR(""&INDEX('Bill Report Reference'!$G$2:$G$59,MATCH(INDEX(Account!$J$2:$J$131,MATCH($B716,Account!$A$2:$A$131,0))&"-"&$C716&"-"&$D716,'Bill Report Reference'!$I$2:$I$59,0)),"") -> https://www.govinfo.gov/content/pkg/PLAW-119publ4/pdf/PLAW-119publ4.pdf | T716: =IFERROR(""&INDEX('Bill Report Reference'!$H$2:$H$59,MATCH(INDEX(Account!$J$2:$J$131,MATCH($B716,Account!$A$2:$A$131,0))&"-"&$C716&"-"&$D716,'Bill Report Reference'!$I$2:$I$59,0)),"") -> N/A
A717: OBS-0809 | B717: ACC-NSF-MREFC | C717: 2025 | D717: Senate Reported | E717: Senate | F717: =IFERROR(""&INDEX('Bill Report Reference'!$E$2:$E$59,MATCH(INDEX(Account!$J$2:$J$131,MATCH($B717,Account!$A$2:$A$131,0))&"-"&$C717&"-"&$D717,'Bill Report Reference'!$I$2:$I$59,0)),"") -> S.4795 | G717: =IFERROR(""&INDEX('Bill Report Reference'!$F$2:$F$59,MATCH(INDEX(Account!$J$2:$J$131,MATCH($B717,Account!$A$2:$A$131,0))&"-"&$C717&"-"&$D717,'Bill Report Reference'!$I$2:$I$59,0)),"") -> S.Rept.118-198 | H717: 300000000 | I717: budget authority | K717: FALSE | M717: SRC-CRPT-118SRPT198 | N717: 227-228 | O717: Title III, NSF, Major Research Equipment and Facilities Construction (base) | P717: human-entered | Q717: 1 | R717: human-verified | S717: =IFERROR(""&INDEX('Bill Report Reference'!$G$2:$G$59,MATCH(INDEX(Account!$J$2:$J$131,MATCH($B717,Account!$A$2:$A$131,0))&"-"&$C717&"-"&$D717,'Bill Report Reference'!$I$2:$I$59,0)),"") -> https://www.congress.gov/118/bills/s4795/BILLS-118s4795rs.pdf | T717: =IFERROR(""&INDEX('Bill Report Reference'!$H$2:$H$59,MATCH(INDEX(Account!$J$2:$J$131,MATCH($B717,Account!$A$2:$A$131,0))&"-"&$C717&"-"&$D717,'Bill Report Reference'!$I$2:$I$59,0)),"") -> https://www.congress.gov/118/crpt/srpt198/CRPT-118srpt198.pdf
A718: OBS-0810 | B718: ACC-NSF-MREFC | C718: 2025 | D718: House Reported | E718: House | F718: =IFERROR(""&INDEX('Bill Report Reference'!$E$2:$E$59,MATCH(INDEX(Account!$J$2:$J$131,MATCH($B718,Account!$A$2:$A$131,0))&"-"&$C718&"-"&$D718,'Bill Report Reference'!$I$2:$I$59,0)),"") -> H.R.9026 | G718: =IFERROR(""&INDEX('Bill Report Reference'!$F$2:$F$59,MATCH(INDEX(Account!$J$2:$J$131,MATCH($B718,Account!$A$2:$A$131,0))&"-"&$C718&"-"&$D718,'Bill Report Reference'!$I$2:$I$59,0)),"") -> H.Rept.118-582 | H718: 235000000 | I718: budget authority | K718: FALSE | M718: SRC-CRPT-118HRPT582 | N718: 247-248 | O718: Title III, NSF, Major Research Equipment and Facilities Construction (base) | P718: human-entered | Q718: 1 | R718: human-verified | S718: =IFERROR(""&INDEX('Bill Report Reference'!$G$2:$G$59,MATCH(INDEX(Account!$J$2:$J$131,MATCH($B718,Account!$A$2:$A$131,0))&"-"&$C718&"-"&$D718,'Bill Report Reference'!$I$2:$I$59,0)),"") -> https://www.govinfo.gov/content/pkg/BILLS-118hr9026rh/pdf/BILLS-118hr9026rh.pdf | T718: =IFERROR(""&INDEX('Bill Report Reference'!$H$2:$H$59,MATCH(INDEX(Account!$J$2:$J$131,MATCH($B718,Account!$A$2:$A$131,0))&"-"&$C718&"-"&$D718,'Bill Report Reference'!$I$2:$I$59,0)),"") -> https://www.congress.gov/118/crpt/hrpt582/CRPT-118hrpt582.pdf
A719: OBS-0811 | B719: ACC-NSF-MREFC | C719: 2025 | D719: President's Budget | E719: N/A | F719: =IFERROR(""&INDEX('Bill Report Reference'!$E$2:$E$59,MATCH(INDEX(Account!$J$2:$J$131,MATCH($B719,Account!$A$2:$A$131,0))&"-"&$C719&"-"&$D719,'Bill Report Reference'!$I$2:$I$59,0)),"") -> PREX 2.8:2025/APP | G719: =IFERROR(""&INDEX('Bill Report Reference'!$F$2:$F$59,MATCH(INDEX(Account!$J$2:$J$131,MATCH($B719,Account!$A$2:$A$131,0))&"-"&$C719&"-"&$D719,'Bill Report Reference'!$I$2:$I$59,0)),"") -> N/A | H719: 300000000 | I719: budget authority | K719: FALSE | M719: SRC-CRPT-118HRPT582 | N719: 247-248 | O719: Title III, NSF, Major Research Equipment and Facilities Construction (base) | P719: human-entered | Q719: 1 | R719: human-verified | S719: =IFERROR(""&INDEX('Bill Report Reference'!$G$2:$G$59,MATCH(INDEX(Account!$J$2:$J$131,MATCH($B719,Account!$A$2:$A$131,0))&"-"&$C719&"-"&$D719,'Bill Report Reference'!$I$2:$I$59,0)),"") -> https://www.govinfo.gov/content/pkg/BUDGET-2025-APP/pdf/BUDGET-2025-APP.pdf | T719: =IFERROR(""&INDEX('Bill Report Reference'!$H$2:$H$59,MATCH(INDEX(Account!$J$2:$J$131,MATCH($B719,Account!$A$2:$A$131,0))&"-"&$C719&"-"&$D719,'Bill Report Reference'!$I$2:$I$59,0)),"") -> N/A
A720: OBS-0812 | B720: ACC-NSF-MREFC | C720: 2024 | D720: Enacted | E720: N/A | F720: =IFERROR(""&INDEX('Bill Report Reference'!$E$2:$E$59,MATCH(INDEX(Account!$J$2:$J$131,MATCH($B720,Account!$A$2:$A$131,0))&"-"&$C720&"-"&$D720,'Bill Report Reference'!$I$2:$I$59,0)),"") -> P.L.118-42 | G720: =IFERROR(""&INDEX('Bill Report Reference'!$F$2:$F$59,MATCH(INDEX(Account!$J$2:$J$131,MATCH($B720,Account!$A$2:$A$131,0))&"-"&$C720&"-"&$D720,'Bill Report Reference'!$I$2:$I$59,0)),"") -> JES_CJS_P.L.118-42 | H720: 0 | I720: budget authority | K720: FALSE | M720: SRC-CRPT-118HRPT582 | N720: 247-248 | O720: Title III, NSF, Major Research Equipment and Facilities Construction (base) | P720: human-entered | Q720: 1 | R720: human-verified | S720: =IFERROR(""&INDEX('Bill Report Reference'!$G$2:$G$59,MATCH(INDEX(Account!$J$2:$J$131,MATCH($B720,Account!$A$2:$A$131,0))&"-"&$C720&"-"&$D720,'Bill Report Reference'!$I$2:$I$59,0)),"") -> https://www.govinfo.gov/content/pkg/PLAW-118publ42/pdf/PLAW-118publ42.pdf | T720: =IFERROR(""&INDEX('Bill Report Reference'!$H$2:$H$59,MATCH(INDEX(Account!$J$2:$J$131,MATCH($B720,Account!$A$2:$A$131,0))&"-"&$C720&"-"&$D720,'Bill Report Reference'!$I$2:$I$59,0)),"") -> https://docs.house.gov/billsthisweek/20240304/FY24%20CJS%20Conference%20JES%20scan%203.3.24.pdf
A721: OBS-0813 | B721: ACC-NSF-MREFC | C721: 2024 | D721: Senate Reported | E721: Senate | F721: =IFERROR(""&INDEX('Bill Report Reference'!$E$2:$E$59,MATCH(INDEX(Account!$J$2:$J$131,MATCH($B721,Account!$A$2:$A$131,0))&"-"&$C721&"-"&$D721,'Bill Report Reference'!$I$2:$I$59,0)),"") -> S.2321 | G721: =IFERROR(""&INDEX('Bill Report Reference'!$F$2:$F$59,MATCH(INDEX(Account!$J$2:$J$131,MATCH($B721,Account!$A$2:$A$131,0))&"-"&$C721&"-"&$D721,'Bill Report Reference'!$I$2:$I$59,0)),"") -> S.Rept.118-62 | H721: 187230000 | I721: budget authority | K721: FALSE | M721: SRC-CRPT-118SRPT62 | N721: 219-220 | O721: Title III, NSF, Major Research Equipment and Facilities Construction (base) | P721: human-entered | Q721: 1 | R721: human-verified | S721: =IFERROR(""&INDEX('Bill Report Reference'!$G$2:$G$59,MATCH(INDEX(Account!$J$2:$J$131,MATCH($B721,Account!$A$2:$A$131,0))&"-"&$C721&"-"&$D721,'Bill Report Reference'!$I$2:$I$59,0)),"") -> https://www.congress.gov/118/bills/s2321/BILLS-118s2321rs.pdf | T721: =IFERROR(""&INDEX('Bill Report Reference'!$H$2:$H$59,MATCH(INDEX(Account!$J$2:$J$131,MATCH($B721,Account!$A$2:$A$131,0))&"-"&$C721&"-"&$D721,'Bill Report Reference'!$I$2:$I$59,0)),"") -> https://www.congress.gov/118/crpt/srpt62/CRPT-118srpt62.pdf
A722: OBS-0814 | B722: ACC-NSF-MREFC | C722: 2024 | D722: House Reported | E722: House | F722: =IFERROR(""&INDEX('Bill Report Reference'!$E$2:$E$59,MATCH(INDEX(Account!$J$2:$J$131,MATCH($B722,Account!$A$2:$A$131,0))&"-"&$C722&"-"&$D722,'Bill Report Reference'!$I$2:$I$59,0)),"") -> H.R.5893 | G722: =IFERROR(""&INDEX('Bill Report Reference'!$F$2:$F$59,MATCH(INDEX(Account!$J$2:$J$131,MATCH($B722,Account!$A$2:$A$131,0))&"-"&$C722&"-"&$D722,'Bill Report Reference'!$I$2:$I$59,0)),"") -> JES_CJS_H.R.5893 | H722: 254000000 | I722: budget authority | K722: FALSE | M722: SRC-EXPL-FY2024-HOUSE | N722: 170-171 | O722: Title III, NSF, Major Research Equipment and Facilities Construction (base) | P722: human-entered | Q722: 1 | R722: human-verified | S722: =IFERROR(""&INDEX('Bill Report Reference'!$G$2:$G$59,MATCH(INDEX(Account!$J$2:$J$131,MATCH($B722,Account!$A$2:$A$131,0))&"-"&$C722&"-"&$D722,'Bill Report Reference'!$I$2:$I$59,0)),"") -> https://www.congress.gov/118/bills/hr5893/BILLS-118hr5893ih.pdf | T722: =IFERROR(""&INDEX('Bill Report Reference'!$H$2:$H$59,MATCH(INDEX(Account!$J$2:$J$131,MATCH($B722,Account!$A$2:$A$131,0))&"-"&$C722&"-"&$D722,'Bill Report Reference'!$I$2:$I$59,0)),"") -> https://appropriations.house.gov/sites/evo-subsites/republicans-appropriations.house.gov/files/FY24-CJS-Explanatory-Materials.pdf
A723: OBS-0815 | B723: ACC-NSF-MREFC | C723: 2024 | D723: President's Budget | E723: N/A | F723: =IFERROR(""&INDEX('Bill Report Reference'!$E$2:$E$59,MATCH(INDEX(Account!$J$2:$J$131,MATCH($B723,Account!$A$2:$A$131,0))&"-"&$C723&"-"&$D723,'Bill Report Reference'!$I$2:$I$59,0)),"") -> PREX 2.8:2024/APP | G723: =IFERROR(""&INDEX('Bill Report Reference'!$F$2:$F$59,MATCH(INDEX(Account!$J$2:$J$131,MATCH($B723,Account!$A$2:$A$131,0))&"-"&$C723&"-"&$D723,'Bill Report Reference'!$I$2:$I$59,0)),"") -> N/A | H723: 304670000 | I723: budget authority | K723: FALSE | M723: SRC-CRPT-118SRPT62 | N723: 219-220 | O723: Title III, NSF, Major Research Equipment and Facilities Construction (base) | P723: human-entered | Q723: 1 | R723: human-verified | S723: =IFERROR(""&INDEX('Bill Report Reference'!$G$2:$G$59,MATCH(INDEX(Account!$J$2:$J$131,MATCH($B723,Account!$A$2:$A$131,0))&"-"&$C723&"-"&$D723,'Bill Report Reference'!$I$2:$I$59,0)),"") -> https://www.govinfo.gov/content/pkg/BUDGET-2024-APP/pdf/BUDGET-2024-APP.pdf | T723: =IFERROR(""&INDEX('Bill Report Reference'!$H$2:$H$59,MATCH(INDEX(Account!$J$2:$J$131,MATCH($B723,Account!$A$2:$A$131,0))&"-"&$C723&"-"&$D723,'Bill Report Reference'!$I$2:$I$59,0)),"") -> N/A
... A755: OBS-0857 | B755: ACC-NSF-MREFC | C755: 2023 | D755: Senate Reported | E755: Senate | F755: =IFERROR(""&INDEX('Bill Report Reference'!$E$2:$E$59,MATCH(INDEX(Account!$J$2:$J$131,MATCH($B755,Account!$A$2:$A$131,0))&"-"&$C755&"-"&$D755,'Bill Report Reference'!$I$2:$I$59,0)),"") -> S.4664 | G755: =IFERROR(""&INDEX('Bill Report Reference'!$F$2:$F$59,MATCH(INDEX(Account!$J$2:$J$131,MATCH($B755,Account!$A$2:$A$131,0))&"-"&$C755&"-"&$D755,'Bill Report Reference'!$I$2:$I$59,0)),"") -> JES_CJS_S.4664 | H755: 0 | I755: supplemental | K755: FALSE | M755: SRC-EXPL-FY2023-SENATE | N755: 215-216 | O755: Title III, NSF, Major Research Equipment and Facilities Construction (emergency) | P755: human-entered | Q755: 1 | R755: human-verified | S755: =IFERROR(""&INDEX('Bill Report Reference'!$G$2:$G$59,MATCH(INDEX(Account!$J$2:$J$131,MATCH($B755,Account!$A$2:$A$131,0))&"-"&$C755&"-"&$D755,'Bill Report Reference'!$I$2:$I$59,0)),"") -> https://www.congress.gov/117/bills/s4664/BILLS-117s4664is.pdf | T755: =IFERROR(""&INDEX('Bill Report Reference'!$H$2:$H$59,MATCH(INDEX(Account!$J$2:$J$131,MATCH($B755,Account!$A$2:$A$131,0))&"-"&$C755&"-"&$D755,'Bill Report Reference'!$I$2:$I$59,0)),"") -> https://www.appropriations.senate.gov/imo/media/doc/CJSFY23RPT.PDF
A756: OBS-0860 | B756: ACC-NSF-MREFC | C756: 2022 | D756: Enacted | E756: N/A | F756: =IFERROR(""&INDEX('Bill Report Reference'!$E$2:$E$59,MATCH(INDEX(Account!$J$2:$J$131,MATCH($B756,Account!$A$2:$A$131,0))&"-"&$C756&"-"&$D756,'Bill Report Reference'!$I$2:$I$59,0)),"") -> P.L.117-103 | G756: =IFERROR(""&INDEX('Bill Report Reference'!$F$2:$F$59,MATCH(INDEX(Account!$J$2:$J$131,MATCH($B756,Account!$A$2:$A$131,0))&"-"&$C756&"-"&$D756,'Bill Report Reference'!$I$2:$I$59,0)),"") -> JES_CJS_P.L.117-103 | H756: 25000000 | I756: supplemental | J756: supplemental_act | K756: FALSE | M756: SRC-CRPT-117HRPT395 | N756: 224 | O756: P.L. 117-43, Division B, Title III, 135 Stat. 359: 'For an additional amount for "Major Research Equipment and Facilities Construction" for necessary expenses related to the National Science Foundation Regional Class Research Vessel construction impacted by Hurricane Ida, $25,000,000'. | P756: human-entered | Q756: 1 | R756: human-verified | S756: =IFERROR(""&INDEX('Bill Report Reference'!$G$2:$G$59,MATCH(INDEX(Account!$J$2:$J$131,MATCH($B756,Account!$A$2:$A$131,0))&"-"&$C756&"-"&$D756,'Bill Report Reference'!$I$2:$I$59,0)),"") -> https://www.congress.gov/117/plaws/publ103/PLAW-117publ103.pdf | T756: =IFERROR(""&INDEX('Bill Report Reference'!$H$2:$H$59,MATCH(INDEX(Account!$J$2:$J$131,MATCH($B756,Account!$A$2:$A$131,0))&"-"&$C756&"-"&$D756,'Bill Report Reference'!$I$2:$I$59,0)),"") -> https://www.govinfo.gov/content/pkg/CPRT-117HPRT47047/pdf/CPRT-117HPRT47047.pdf
A757: OBS-0861 | B757: ACC-NSF-MREFC | C757: 2022 | D757: Senate Reported | E757: Senate | F757: =IFERROR(""&INDEX('Bill Report Reference'!$E$2:$E$59,MATCH(INDEX(Account!$J$2:$J$131,MATCH($B757,Account!$A$2:$A$131,0))&"-"&$C757&"-"&$D757,'Bill Report Reference'!$I$2:$I$59,0)),"") -> S.3042 | G757: =IFERROR(""&INDEX('Bill Report Reference'!$F$2:$F$59,MATCH(INDEX(Account!$J$2:$J$131,MATCH($B757,Account!$A$2:$A$131,0))&"-"&$C757&"-"&$D757,'Bill Report Reference'!$I$2:$I$59,0)),"") -> JES_CJS_S.3042 | H757: 0 | I757: supplemental | K757: FALSE | M757: SRC-EXPL-FY2022-SENATE | N757: 207-208 | O757: Title III, NSF, Major Research Equipment and Facilities Construction (emergency) | P757: human-entered | Q757: 1 | R757: human-verified | S757: =IFERROR(""&INDEX('Bill Report Reference'!$G$2:$G$59,MATCH(INDEX(Account!$J$2:$J$131,MATCH($B757,Account!$A$2:$A$131,0))&"-"&$C757&"-"&$D757,'Bill Report Reference'!$I$2:$I$59,0)),"") -> https://www.congress.gov/117/bills/s3042/BILLS-117s3042is.pdf | T757: =IFERROR(""&INDEX('Bill Report Reference'!$H$2:$H$59,MATCH(INDEX(Account!$J$2:$J$131,MATCH($B757,Account!$A$2:$A$131,0))&"-"&$C757&"-"&$D757,'Bill Report Reference'!$I$2:$I$59,0)),"") -> https://www.appropriations.senate.gov/imo/media/doc/CJSRept_Final.PDF
A758: OBS-0865 | B758: ACC-NSF-MREFC | C758: 2021 | D758: Senate Reported | E758: Senate | F758: =IFERROR(""&INDEX('Bill Report Reference'!$E$2:$E$59,MATCH(INDEX(Account!$J$2:$J$131,MATCH($B758,Account!$A$2:$A$131,0))&"-"&$C758&"-"&$D758,'Bill Report Reference'!$I$2:$I$59,0)),"") -> N/A | G758: =IFERROR(""&INDEX('Bill Report Reference'!$F$2:$F$59,MATCH(INDEX(Account!$J$2:$J$131,MATCH($B758,Account!$A$2:$A$131,0))&"-"&$C758&"-"&$D758,'Bill Report Reference'!$I$2:$I$59,0)),"") -> JES_CJS_FY2021-Senate | H758: 0 | I758: supplemental | K758: FALSE | M758: SRC-EXPL-FY2021-SENATE | N758: 197-199 | O758: Title III, NSF, Major Research Equipment and Facilities Construction (emergency) | P758: human-entered | Q758: 1 | R758: human-verified | S758: =IFERROR(""&INDEX('Bill Report Reference'!$G$2:$G$59,MATCH(INDEX(Account!$J$2:$J$131,MATCH($B758,Account!$A$2:$A$131,0))&"-"&$C758&"-"&$D758,'Bill Report Reference'!$I$2:$I$59,0)),"") -> https://www.appropriations.senate.gov/imo/media/doc/CJSFY2021.pdf | T758: =IFERROR(""&INDEX('Bill Report Reference'!$H$2:$H$59,MATCH(INDEX(Account!$J$2:$J$131,MATCH($B758,Account!$A$2:$A$131,0))&"-"&$C758&"-"&$D758,'Bill Report Reference'!$I$2:$I$59,0)),"") -> https://www.appropriations.senate.gov/imo/media/doc/CJSRept.pdf
A759: OBS-0884 | B759: ACC-NASA-TOTAL | C759: 2026 | D759: Enacted | E759: N/A | F759: =IFERROR(""&INDEX('Bill Report Reference'!$E$2:$E$59,MATCH(INDEX(Account!$J$2:$J$131,MATCH($B759,Account!$A$2:$A$131,0))&"-"&$C759&"-"&$D759,'Bill Report Reference'!$I$2:$I$59,0)),"") -> P.L.119-74 | G759: =IFERROR(""&INDEX('Bill Report Reference'!$F$2:$F$59,MATCH(INDEX(Account!$J$2:$J$131,MATCH($B759,Account!$A$2:$A$131,0))&"-"&$C759&"-"&$D759,'Bill Report Reference'!$I$2:$I$59,0)),"") -> JES_CJS_P.L.119-74 | H759: 24438336000 | I759: budget authority | K759: FALSE | M759: SRC-EXPL-FY2026-PB | N759: 128-130 | O759: Agency rollup — sum of NASA's 9 program accounts | P759: human-entered | Q759: 1 | R759: human-verified | S759: =IFERROR(""&INDEX('Bill Report Reference'!$G$2:$G$59,MATCH(INDEX(Account!$J$2:$J$131,MATCH($B759,Account!$A$2:$A$131,0))&"-"&$C759&"-"&$D759,'Bill Report Reference'!$I$2:$I$59,0)),"") -> https://www.govinfo.gov/content/pkg/PLAW-119publ74/pdf/PLAW-119publ74.pdf | T759: =IFERROR(""&INDEX('Bill Report Reference'!$H$2:$H$59,MATCH(INDEX(Account!$J$2:$J$131,MATCH($B759,Account!$A$2:$A$131,0))&"-"&$C759&"-"&$D759,'Bill Report Reference'!$I$2:$I$59,0)),"") -> https://rules.house.gov/sites/evo-subsites/rules.house.gov/files/documents/division-a-commerce-justice-science_0.pdf
A760: OBS-0885 | B760: ACC-NASA-TOTAL | C760: 2026 | D760: Senate Reported | E760: Senate | F760: =IFERROR(""&INDEX('Bill Report Reference'!$E$2:$E$59,MATCH(INDEX(Account!$J$2:$J$131,MATCH($B760,Account!$A$2:$A$131,0))&"-"&$C760&"-"&$D760,'Bill Report Reference'!$I$2:$I$59,0)),"") -> S.2354 | G760: =IFERROR(""&INDEX('Bill Report Reference'!$F$2:$F$59,MATCH(INDEX(Account!$J$2:$J$131,MATCH($B760,Account!$A$2:$A$131,0))&"-"&$C760&"-"&$D760,'Bill Report Reference'!$I$2:$I$59,0)),"") -> S.Rept.119-44 | H760: 24899679000 | I760: budget authority | K760: FALSE | M760: SRC-CRPT-119SRPT44 | N760: 217-219 | O760: Agency rollup — sum of NASA's 9 program accounts | P760: human-entered | Q760: 1 | R760: human-verified | S760: =IFERROR(""&INDEX('Bill Report Reference'!$G$2:$G$59,MATCH(INDEX(Account!$J$2:$J$131,MATCH($B760,Account!$A$2:$A$131,0))&"-"&$C760&"-"&$D760,'Bill Report Reference'!$I$2:$I$59,0)),"") -> https://www.congress.gov/119/bills/s2354/BILLS-119s2354rs.pdf | T760: =IFERROR(""&INDEX('Bill Report Reference'!$H$2:$H$59,MATCH(INDEX(Account!$J$2:$J$131,MATCH($B760,Account!$A$2:$A$131,0))&"-"&$C760&"-"&$D760,'Bill Report Reference'!$I$2:$I$59,0)),"") -> https://www.congress.gov/119/crpt/srpt44/CRPT-119srpt44.pdf
A761: OBS-0886 | B761: ACC-NASA-TOTAL | C761: 2026 | D761: House Reported | E761: House | F761: =IFERROR(""&INDEX('Bill Report Reference'!$E$2:$E$59,MATCH(INDEX(Account!$J$2:$J$131,MATCH($B761,Account!$A$2:$A$131,0))&"-"&$C761&"-"&$D761,'Bill Report Reference'!$I$2:$I$59,0)),"") -> H.R.5342 | G761: =IFERROR(""&INDEX('Bill Report Reference'!$F$2:$F$59,MATCH(INDEX(Account!$J$2:$J$131,MATCH($B761,Account!$A$2:$A$131,0))&"-"&$C761&"-"&$D761,'Bill Report Reference'!$I$2:$I$59,0)),"") -> H.Rept.119-272 | H761: 24838327000 | I761: budget authority | K761: FALSE | M761: SRC-CRPT-119HRPT272 | N761: 256-257 | O761: Agency rollup — sum of NASA's 9 program accounts | P761: human-entered | Q761: 1 | R761: human-verified | S761: =IFERROR(""&INDEX('Bill Report Reference'!$G$2:$G$59,MATCH(INDEX(Account!$J$2:$J$131,MATCH($B761,Account!$A$2:$A$131,0))&"-"&$C761&"-"&$D761,'Bill Report Reference'!$I$2:$I$59,0)),"") -> https://www.govinfo.gov/content/pkg/BILLS-119hr5342rh/pdf/BILLS-119hr5342rh.pdf | T761: =IFERROR(""&INDEX('Bill Report Reference'!$H$2:$H$59,MATCH(INDEX(Account!$J$2:$J$131,MATCH($B761,Account!$A$2:$A$131,0))&"-"&$C761&"-"&$D761,'Bill Report Reference'!$I$2:$I$59,0)),"") -> https://www.congress.gov/119/crpt/hrpt272/CRPT-119hrpt272.pdf
A762: OBS-0887 | B762: ACC-NASA-TOTAL | C762: 2026 | D762: President's Budget | E762: N/A | F762: =IFERROR(""&INDEX('Bill Report Reference'!$E$2:$E$59,MATCH(INDEX(Account!$J$2:$J$131,MATCH($B762,Account!$A$2:$A$131,0))&"-"&$C762&"-"&$D762,'Bill Report Reference'!$I$2:$I$59,0)),"") -> PREX 2.8:2026/APP | G762: =IFERROR(""&INDEX('Bill Report Reference'!$F$2:$F$59,MATCH(INDEX(Account!$J$2:$J$131,MATCH($B762,Account!$A$2:$A$131,0))&"-"&$C762&"-"&$D762,'Bill Report Reference'!$I$2:$I$59,0)),"") -> N/A | H762: 18809100000 | I762: budget authority | K762: FALSE | M762: SRC-EXPL-FY2026-PB | N762: 128-130 | O762: Agency rollup — sum of NASA's 9 program accounts | P762: human-entered | Q762: 1 | R762: human-verified | S762: =IFERROR(""&INDEX('Bill Report Reference'!$G$2:$G$59,MATCH(INDEX(Account!$J$2:$J$131,MATCH($B762,Account!$A$2:$A$131,0))&"-"&$C762&"-"&$D762,'Bill Report Reference'!$I$2:$I$59,0)),"") -> https://www.govinfo.gov/content/pkg/BUDGET-2026-APP/pdf/BUDGET-2026-APP.pdf | T762: =IFERROR(""&INDEX('Bill Report Reference'!$H$2:$H$59,MATCH(INDEX(Account!$J$2:$J$131,MATCH($B762,Account!$A$2:$A$131,0))&"-"&$C762&"-"&$D762,'Bill Report Reference'!$I$2:$I$59,0)),"") -> N/A
A763: OBS-0888 | B763: ACC-NASA-TOTAL | C763: 2025 | D763: Enacted | E763: N/A | F763: =IFERROR(""&INDEX('Bill Report Reference'!$E$2:$E$59,MATCH(INDEX(Account!$J$2:$J$131,MATCH($B763,Account!$A$2:$A$131,0))&"-"&$C763&"-"&$D763,'Bill Report Reference'!$I$2:$I$59,0)),"") -> P.L.119-4 | G763: =IFERROR(""&INDEX('Bill Report Reference'!$F$2:$F$59,MATCH(INDEX(Account!$J$2:$J$131,MATCH($B763,Account!$A$2:$A$131,0))&"-"&$C763&"-"&$D763,'Bill Report Reference'!$I$2:$I$59,0)),"") -> N/A | H763: 24838327000 | I763: budget authority | K763: FALSE | M763: SRC-CRPT-119HRPT272 | N763: 256-257 | O763: Agency rollup — sum of NASA's 9 program accounts | P763: human-entered | Q763: 1 | R763: human-verified | S763: =IFERROR(""&INDEX('Bill Report Reference'!$G$2:$G$59,MATCH(INDEX(Account!$J$2:$J$131,MATCH($B763,Account!$A$2:$A$131,0))&"-"&$C763&"-"&$D763,'Bill Report Reference'!$I$2:$I$59,0)),"") -> https://www.govinfo.gov/content/pkg/PLAW-119publ4/pdf/PLAW-119publ4.pdf | T763: =IFERROR(""&INDEX('Bill Report Reference'!$H$2:$H$59,MATCH(INDEX(Account!$J$2:$J$131,MATCH($B763,Account!$A$2:$A$131,0))&"-"&$C763&"-"&$D763,'Bill Report Reference'!$I$2:$I$59,0)),"") -> N/A
A764: OBS-0889 | B764: ACC-NASA-TOTAL | C764: 2025 | D764: Senate Reported | E764: Senate | F764: =IFERROR(""&INDEX('Bill Report Reference'!$E$2:$E$59,MATCH(INDEX(Account!$J$2:$J$131,MATCH($B764,Account!$A$2:$A$131,0))&"-"&$C764&"-"&$D764,'Bill Report Reference'!$I$2:$I$59,0)),"") -> S.4795 | G764: =IFERROR(""&INDEX('Bill Report Reference'!$F$2:$F$59,MATCH(INDEX(Account!$J$2:$J$131,MATCH($B764,Account!$A$2:$A$131,0))&"-"&$C764&"-"&$D764,'Bill Report Reference'!$I$2:$I$59,0)),"") -> S.Rept.118-198 | H764: 25433700000 | I764: budget authority | K764: FALSE | M764: SRC-CRPT-118SRPT198 | N764: 227-228 | O764: Agency rollup -- this document's own printed NASA total (S.Rept. 118-198 p.227) | P764: human-entered | Q764: 1 | R764: human-verified | S764: =IFERROR(""&INDEX('Bill Report Reference'!$G$2:$G$59,MATCH(INDEX(Account!$J$2:$J$131,MATCH($B764,Account!$A$2:$A$131,0))&"-"&$C764&"-"&$D764,'Bill Report Reference'!$I$2:$I$59,0)),"") -> https://www.congress.gov/118/bills/s4795/BILLS-118s4795rs.pdf | T764: =IFERROR(""&INDEX('Bill Report Reference'!$H$2:$H$59,MATCH(INDEX(Account!$J$2:$J$131,MATCH($B764,Account!$A$2:$A$131,0))&"-"&$C764&"-"&$D764,'Bill Report Reference'!$I$2:$I$59,0)),"") -> https://www.congress.gov/118/crpt/srpt198/CRPT-118srpt198.pdf
A765: OBS-0890 | B765: ACC-NASA-TOTAL | C765: 2025 | D765: House Reported | E765: House | F765: =IFERROR(""&INDEX('Bill Report Reference'!$E$2:$E$59,MATCH(INDEX(Account!$J$2:$J$131,MATCH($B765,Account!$A$2:$A$131,0))&"-"&$C765&"-"&$D765,'Bill Report Reference'!$I$2:$I$59,0)),"") -> H.R.9026 | G765: =IFERROR(""&INDEX('Bill Report Reference'!$F$2:$F$59,MATCH(INDEX(Account!$J$2:$J$131,MATCH($B765,Account!$A$2:$A$131,0))&"-"&$C765&"-"&$D765,'Bill Report Reference'!$I$2:$I$59,0)),"") -> H.Rept.118-582 | H765: 25178640000 | I765: budget authority | K765: FALSE | M765: SRC-CRPT-118HRPT582 | N765: 247-248 | O765: Agency rollup — sum of NASA's 9 program accounts | P765: human-entered | Q765: 1 | R765: human-verified | S765: =IFERROR(""&INDEX('Bill Report Reference'!$G$2:$G$59,MATCH(INDEX(Account!$J$2:$J$131,MATCH($B765,Account!$A$2:$A$131,0))&"-"&$C765&"-"&$D765,'Bill Report Reference'!$I$2:$I$59,0)),"") -> https://www.govinfo.gov/content/pkg/BILLS-118hr9026rh/pdf/BILLS-118hr9026rh.pdf | T765: =IFERROR(""&INDEX('Bill Report Reference'!$H$2:$H$59,MATCH(INDEX(Account!$J$2:$J$131,MATCH($B765,Account!$A$2:$A$131,0))&"-"&$C765&"-"&$D765,'Bill Report Reference'!$I$2:$I$59,0)),"") -> https://www.congress.gov/118/crpt/hrpt582/CRPT-118hrpt582.pdf
A766: OBS-0891 | B766: ACC-NASA-TOTAL | C766: 2025 | D766: President's Budget | E766: N/A | F766: =IFERROR(""&INDEX('Bill Report Reference'!$E$2:$E$59,MATCH(INDEX(Account!$J$2:$J$131,MATCH($B766,Account!$A$2:$A$131,0))&"-"&$C766&"-"&$D766,'Bill Report Reference'!$I$2:$I$59,0)),"") -> PREX 2.8:2025/APP | G766: =IFERROR(""&INDEX('Bill Report Reference'!$F$2:$F$59,MATCH(INDEX(Account!$J$2:$J$131,MATCH($B766,Account!$A$2:$A$131,0))&"-"&$C766&"-"&$D766,'Bill Report Reference'!$I$2:$I$59,0)),"") -> N/A | H766: 25382740000 | I766: budget authority | K766: FALSE | M766: SRC-CRPT-118HRPT582 | N766: 247-248 | O766: Agency rollup — sum of NASA's 9 program accounts | P766: human-entered | Q766: 1 | R766: human-verified | S766: =IFERROR(""&INDEX('Bill Report Reference'!$G$2:$G$59,MATCH(INDEX(Account!$J$2:$J$131,MATCH($B766,Account!$A$2:$A$131,0))&"-"&$C766&"-"&$D766,'Bill Report Reference'!$I$2:$I$59,0)),"") -> https://www.govinfo.gov/content/pkg/BUDGET-2025-APP/pdf/BUDGET-2025-APP.pdf | T766: =IFERROR(""&INDEX('Bill Report Reference'!$H$2:$H$59,MATCH(INDEX(Account!$J$2:$J$131,MATCH($B766,Account!$A$2:$A$131,0))&"-"&$C766&"-"&$D766,'Bill Report Reference'!$I$2:$I$59,0)),"") -> N/A
A767: OBS-0892 | B767: ACC-NASA-TOTAL | C767: 2024 | D767: Enacted | E767: N/A | F767: =IFERROR(""&INDEX('Bill Report Reference'!$E$2:$E$59,MATCH(INDEX(Account!$J$2:$J$131,MATCH($B767,Account!$A$2:$A$131,0))&"-"&$C767&"-"&$D767,'Bill Report Reference'!$I$2:$I$59,0)),"") -> P.L.118-42 | G767: =IFERROR(""&INDEX('Bill Report Reference'!$F$2:$F$59,MATCH(INDEX(Account!$J$2:$J$131,MATCH($B767,Account!$A$2:$A$131,0))&"-"&$C767&"-"&$D767,'Bill Report Reference'!$I$2:$I$59,0)),"") -> JES_CJS_P.L.118-42 | H767: 24875000000 | I767: budget authority | K767: FALSE | M767: SRC-CRPT-118HRPT582 | N767: 247-248 | O767: Agency rollup — sum of NASA's 9 program accounts | P767: human-entered | Q767: 1 | R767: human-verified | S767: =IFERROR(""&INDEX('Bill Report Reference'!$G$2:$G$59,MATCH(INDEX(Account!$J$2:$J$131,MATCH($B767,Account!$A$2:$A$131,0))&"-"&$C767&"-"&$D767,'Bill Report Reference'!$I$2:$I$59,0)),"") -> https://www.govinfo.gov/content/pkg/PLAW-118publ42/pdf/PLAW-118publ42.pdf | T767: =IFERROR(""&INDEX('Bill Report Reference'!$H$2:$H$59,MATCH(INDEX(Account!$J$2:$J$131,MATCH($B767,Account!$A$2:$A$131,0))&"-"&$C767&"-"&$D767,'Bill Report Reference'!$I$2:$I$59,0)),"") -> https://docs.house.gov/billsthisweek/20240304/FY24%20CJS%20Conference%20JES%20scan%203.3.24.pdf
A768: OBS-0893 | B768: ACC-NASA-TOTAL | C768: 2024 | D768: Senate Reported | E768: Senate | F768: =IFERROR(""&INDEX('Bill Report Reference'!$E$2:$E$59,MATCH(INDEX(Account!$J$2:$J$131,MATCH($B768,Account!$A$2:$A$131,0))&"-"&$C768&"-"&$D768,'Bill Report Reference'!$I$2:$I$59,0)),"") -> S.2321 | G768: =IFERROR(""&INDEX('Bill Report Reference'!$F$2:$F$59,MATCH(INDEX(Account!$J$2:$J$131,MATCH($B768,Account!$A$2:$A$131,0))&"-"&$C768&"-"&$D768,'Bill Report Reference'!$I$2:$I$59,0)),"") -> S.Rept.118-62 | H768: 25000320000 | I768: budget authority | K768: FALSE | M768: SRC-CRPT-118SRPT62 | N768: 219-220 | O768: Agency rollup — sum of NASA's 9 program accounts | P768: human-entered | Q768: 1 | R768: human-verified | S768: =IFERROR(""&INDEX('Bill Report Reference'!$G$2:$G$59,MATCH(INDEX(Account!$J$2:$J$131,MATCH($B768,Account!$A$2:$A$131,0))&"-"&$C768&"-"&$D768,'Bill Report Reference'!$I$2:$I$59,0)),"") -> https://www.congress.gov/118/bills/s2321/BILLS-118s2321rs.pdf | T768: =IFERROR(""&INDEX('Bill Report Reference'!$H$2:$H$59,MATCH(INDEX(Account!$J$2:$J$131,MATCH($B768,Account!$A$2:$A$131,0))&"-"&$C768&"-"&$D768,'Bill Report Reference'!$I$2:$I$59,0)),"") -> https://www.congress.gov/118/crpt/srpt62/CRPT-118srpt62.pdf
... A838: OBS-0963 | B838: ACC-NSF-TOTAL | C838: 2017 | D838: President's Budget | E838: N/A | F838: =IFERROR(""&INDEX('Bill Report Reference'!$E$2:$E$59,MATCH(INDEX(Account!$J$2:$J$131,MATCH($B838,Account!$A$2:$A$131,0))&"-"&$C838&"-"&$D838,'Bill Report Reference'!$I$2:$I$59,0)),"") -> PREX 2.8:2017/APP | G838: =IFERROR(""&INDEX('Bill Report Reference'!$F$2:$F$59,MATCH(INDEX(Account!$J$2:$J$131,MATCH($B838,Account!$A$2:$A$131,0))&"-"&$C838&"-"&$D838,'Bill Report Reference'!$I$2:$I$59,0)),"") -> N/A | H838: 7564020000 | I838: budget authority | K838: FALSE | M838: SRC-CRPT-114HRPT605 | N838: 114-115 | O838: Agency rollup — sum of NSF's 6 program accounts | P838: human-entered | Q838: 1 | R838: human-verified | S838: =IFERROR(""&INDEX('Bill Report Reference'!$G$2:$G$59,MATCH(INDEX(Account!$J$2:$J$131,MATCH($B838,Account!$A$2:$A$131,0))&"-"&$C838&"-"&$D838,'Bill Report Reference'!$I$2:$I$59,0)),"") -> https://www.govinfo.gov/content/pkg/BUDGET-2017-APP/pdf/BUDGET-2017-APP.pdf | T838: =IFERROR(""&INDEX('Bill Report Reference'!$H$2:$H$59,MATCH(INDEX(Account!$J$2:$J$131,MATCH($B838,Account!$A$2:$A$131,0))&"-"&$C838&"-"&$D838,'Bill Report Reference'!$I$2:$I$59,0)),"") -> N/A
A839: OBS-0964 | B839: ACC-DOJ-CVF | C839: 2027 | D839: House Reported | E839: House | F839: =IFERROR(""&INDEX('Bill Report Reference'!$E$2:$E$59,MATCH(INDEX(Account!$J$2:$J$131,MATCH($B839,Account!$A$2:$A$131,0))&"-"&$C839&"-"&$D839,'Bill Report Reference'!$I$2:$I$59,0)),"") -> H.R.8845 | G839: =IFERROR(""&INDEX('Bill Report Reference'!$F$2:$F$59,MATCH(INDEX(Account!$J$2:$J$131,MATCH($B839,Account!$A$2:$A$131,0))&"-"&$C839&"-"&$D839,'Bill Report Reference'!$I$2:$I$59,0)),"") -> H.Rept.119-652 | H839: -100000000 | I839: transfer | K839: FALSE | L839: ACC-DOJ-VAWA | M839: SRC-CBO-HR8845-FY2027 | N839: 1-14 | O839: Title II, Transfer to OVW | P839: human-entered | Q839: 1 | R839: human-verified | S839: =IFERROR(""&INDEX('Bill Report Reference'!$G$2:$G$59,MATCH(INDEX(Account!$J$2:$J$131,MATCH($B839,Account!$A$2:$A$131,0))&"-"&$C839&"-"&$D839,'Bill Report Reference'!$I$2:$I$59,0)),"") -> https://www.govinfo.gov/content/pkg/BILLS-119hr8845rh/pdf/BILLS-119hr8845rh.pdf | T839: =IFERROR(""&INDEX('Bill Report Reference'!$H$2:$H$59,MATCH(INDEX(Account!$J$2:$J$131,MATCH($B839,Account!$A$2:$A$131,0))&"-"&$C839&"-"&$D839,'Bill Report Reference'!$I$2:$I$59,0)),"") -> https://www.congress.gov/119/crpt/hrpt652/CRPT-119hrpt652.pdf
A840: OBS-0965 | B840: ACC-DOJ-CVF | C840: 2027 | D840: House Reported | E840: House | F840: =IFERROR(""&INDEX('Bill Report Reference'!$E$2:$E$59,MATCH(INDEX(Account!$J$2:$J$131,MATCH($B840,Account!$A$2:$A$131,0))&"-"&$C840&"-"&$D840,'Bill Report Reference'!$I$2:$I$59,0)),"") -> H.R.8845 | G840: =IFERROR(""&INDEX('Bill Report Reference'!$F$2:$F$59,MATCH(INDEX(Account!$J$2:$J$131,MATCH($B840,Account!$A$2:$A$131,0))&"-"&$C840&"-"&$D840,'Bill Report Reference'!$I$2:$I$59,0)),"") -> H.Rept.119-652 | H840: -10000000 | I840: transfer | K840: FALSE | L840: ACC-DOJ-OIG | M840: SRC-CBO-HR8845-FY2027 | N840: 1-14 | O840: Title V, Transfer to OIG | P840: human-entered | Q840: 1 | R840: human-verified | S840: =IFERROR(""&INDEX('Bill Report Reference'!$G$2:$G$59,MATCH(INDEX(Account!$J$2:$J$131,MATCH($B840,Account!$A$2:$A$131,0))&"-"&$C840&"-"&$D840,'Bill Report Reference'!$I$2:$I$59,0)),"") -> https://www.govinfo.gov/content/pkg/BILLS-119hr8845rh/pdf/BILLS-119hr8845rh.pdf | T840: =IFERROR(""&INDEX('Bill Report Reference'!$H$2:$H$59,MATCH(INDEX(Account!$J$2:$J$131,MATCH($B840,Account!$A$2:$A$131,0))&"-"&$C840&"-"&$D840,'Bill Report Reference'!$I$2:$I$59,0)),"") -> https://www.congress.gov/119/crpt/hrpt652/CRPT-119hrpt652.pdf
A841: OBS-0966 | B841: ACC-DOJ-CVF | C841: 2027 | D841: House Reported | E841: House | F841: =IFERROR(""&INDEX('Bill Report Reference'!$E$2:$E$59,MATCH(INDEX(Account!$J$2:$J$131,MATCH($B841,Account!$A$2:$A$131,0))&"-"&$C841&"-"&$D841,'Bill Report Reference'!$I$2:$I$59,0)),"") -> H.R.8845 | G841: =IFERROR(""&INDEX('Bill Report Reference'!$F$2:$F$59,MATCH(INDEX(Account!$J$2:$J$131,MATCH($B841,Account!$A$2:$A$131,0))&"-"&$C841&"-"&$D841,'Bill Report Reference'!$I$2:$I$59,0)),"") -> H.Rept.119-652 | H841: -2670000000 | I841: rescission | J841: chimp | K841: FALSE | M841: SRC-CBO-HR8845-FY2027 | N841: 1-14 | O841: Title VII, FY27 CHIMP | P841: human-entered | Q841: 1 | R841: human-verified | S841: =IFERROR(""&INDEX('Bill Report Reference'!$G$2:$G$59,MATCH(INDEX(Account!$J$2:$J$131,MATCH($B841,Account!$A$2:$A$131,0))&"-"&$C841&"-"&$D841,'Bill Report Reference'!$I$2:$I$59,0)),"") -> https://www.govinfo.gov/content/pkg/BILLS-119hr8845rh/pdf/BILLS-119hr8845rh.pdf | T841: =IFERROR(""&INDEX('Bill Report Reference'!$H$2:$H$59,MATCH(INDEX(Account!$J$2:$J$131,MATCH($B841,Account!$A$2:$A$131,0))&"-"&$C841&"-"&$D841,'Bill Report Reference'!$I$2:$I$59,0)),"") -> https://www.congress.gov/119/crpt/hrpt652/CRPT-119hrpt652.pdf
A842: OBS-0967 | B842: ACC-DOJ-CVF | C842: 2027 | D842: House Reported | E842: House | F842: =IFERROR(""&INDEX('Bill Report Reference'!$E$2:$E$59,MATCH(INDEX(Account!$J$2:$J$131,MATCH($B842,Account!$A$2:$A$131,0))&"-"&$C842&"-"&$D842,'Bill Report Reference'!$I$2:$I$59,0)),"") -> H.R.8845 | G842: =IFERROR(""&INDEX('Bill Report Reference'!$F$2:$F$59,MATCH(INDEX(Account!$J$2:$J$131,MATCH($B842,Account!$A$2:$A$131,0))&"-"&$C842&"-"&$D842,'Bill Report Reference'!$I$2:$I$59,0)),"") -> H.Rept.119-652 | H842: 0 | I842: rescission | J842: chimp_pop_up | K842: FALSE | M842: SRC-CBO-HR8845-FY2027 | N842: 1-14 | O842: Title VII, FY27 CHIMP Pop-Up | P842: human-entered | Q842: 1 | R842: human-verified | S842: =IFERROR(""&INDEX('Bill Report Reference'!$G$2:$G$59,MATCH(INDEX(Account!$J$2:$J$131,MATCH($B842,Account!$A$2:$A$131,0))&"-"&$C842&"-"&$D842,'Bill Report Reference'!$I$2:$I$59,0)),"") -> https://www.govinfo.gov/content/pkg/BILLS-119hr8845rh/pdf/BILLS-119hr8845rh.pdf | T842: =IFERROR(""&INDEX('Bill Report Reference'!$H$2:$H$59,MATCH(INDEX(Account!$J$2:$J$131,MATCH($B842,Account!$A$2:$A$131,0))&"-"&$C842&"-"&$D842,'Bill Report Reference'!$I$2:$I$59,0)),"") -> https://www.congress.gov/119/crpt/hrpt652/CRPT-119hrpt652.pdf
A843: OBS-0968 | B843: ACC-DOJ-AFF | C843: 2027 | D843: House Reported | E843: House | F843: =IFERROR(""&INDEX('Bill Report Reference'!$E$2:$E$59,MATCH(INDEX(Account!$J$2:$J$131,MATCH($B843,Account!$A$2:$A$131,0))&"-"&$C843&"-"&$D843,'Bill Report Reference'!$I$2:$I$59,0)),"") -> H.R.8845 | G843: =IFERROR(""&INDEX('Bill Report Reference'!$F$2:$F$59,MATCH(INDEX(Account!$J$2:$J$131,MATCH($B843,Account!$A$2:$A$131,0))&"-"&$C843&"-"&$D843,'Bill Report Reference'!$I$2:$I$59,0)),"") -> H.Rept.119-652 | H843: 21000000 | I843: budget authority | K843: FALSE | M843: SRC-CBO-HR8845-FY2027 | N843: 1-14 | O843: Title II | P843: human-entered | Q843: 1 | R843: human-verified | S843: =IFERROR(""&INDEX('Bill Report Reference'!$G$2:$G$59,MATCH(INDEX(Account!$J$2:$J$131,MATCH($B843,Account!$A$2:$A$131,0))&"-"&$C843&"-"&$D843,'Bill Report Reference'!$I$2:$I$59,0)),"") -> https://www.govinfo.gov/content/pkg/BILLS-119hr8845rh/pdf/BILLS-119hr8845rh.pdf | T843: =IFERROR(""&INDEX('Bill Report Reference'!$H$2:$H$59,MATCH(INDEX(Account!$J$2:$J$131,MATCH($B843,Account!$A$2:$A$131,0))&"-"&$C843&"-"&$D843,'Bill Report Reference'!$I$2:$I$59,0)),"") -> https://www.congress.gov/119/crpt/hrpt652/CRPT-119hrpt652.pdf
A844: OBS-0969 | B844: ACC-DOJ-WCF | C844: 2027 | D844: House Reported | E844: House | F844: =IFERROR(""&INDEX('Bill Report Reference'!$E$2:$E$59,MATCH(INDEX(Account!$J$2:$J$131,MATCH($B844,Account!$A$2:$A$131,0))&"-"&$C844&"-"&$D844,'Bill Report Reference'!$I$2:$I$59,0)),"") -> H.R.8845 | G844: =IFERROR(""&INDEX('Bill Report Reference'!$F$2:$F$59,MATCH(INDEX(Account!$J$2:$J$131,MATCH($B844,Account!$A$2:$A$131,0))&"-"&$C844&"-"&$D844,'Bill Report Reference'!$I$2:$I$59,0)),"") -> H.Rept.119-652 | H844: -150000000 | I844: rescission | K844: FALSE | M844: SRC-CBO-HR8845-FY2027 | N844: 1-14 | O844: Title V, Sec. 521(c)(1) | P844: human-entered | Q844: 1 | R844: human-verified | S844: =IFERROR(""&INDEX('Bill Report Reference'!$G$2:$G$59,MATCH(INDEX(Account!$J$2:$J$131,MATCH($B844,Account!$A$2:$A$131,0))&"-"&$C844&"-"&$D844,'Bill Report Reference'!$I$2:$I$59,0)),"") -> https://www.govinfo.gov/content/pkg/BILLS-119hr8845rh/pdf/BILLS-119hr8845rh.pdf | T844: =IFERROR(""&INDEX('Bill Report Reference'!$H$2:$H$59,MATCH(INDEX(Account!$J$2:$J$131,MATCH($B844,Account!$A$2:$A$131,0))&"-"&$C844&"-"&$D844,'Bill Report Reference'!$I$2:$I$59,0)),"") -> https://www.congress.gov/119/crpt/hrpt652/CRPT-119hrpt652.pdf
A845: OBS-0970 | B845: ACC-DOJ-WCF | C845: 2027 | D845: House Reported | E845: House | F845: =IFERROR(""&INDEX('Bill Report Reference'!$E$2:$E$59,MATCH(INDEX(Account!$J$2:$J$131,MATCH($B845,Account!$A$2:$A$131,0))&"-"&$C845&"-"&$D845,'Bill Report Reference'!$I$2:$I$59,0)),"") -> H.R.8845 | G845: =IFERROR(""&INDEX('Bill Report Reference'!$F$2:$F$59,MATCH(INDEX(Account!$J$2:$J$131,MATCH($B845,Account!$A$2:$A$131,0))&"-"&$C845&"-"&$D845,'Bill Report Reference'!$I$2:$I$59,0)),"") -> H.Rept.119-652 | H845: 0 | I845: budget authority | K845: FALSE | M845: SRC-CBO-HR8845-FY2027 | N845: 1-14 | O845: Title V, Sec. 521(c)(1) companion line | P845: human-entered | Q845: 1 | R845: human-verified | S845: =IFERROR(""&INDEX('Bill Report Reference'!$G$2:$G$59,MATCH(INDEX(Account!$J$2:$J$131,MATCH($B845,Account!$A$2:$A$131,0))&"-"&$C845&"-"&$D845,'Bill Report Reference'!$I$2:$I$59,0)),"") -> https://www.govinfo.gov/content/pkg/BILLS-119hr8845rh/pdf/BILLS-119hr8845rh.pdf | T845: =IFERROR(""&INDEX('Bill Report Reference'!$H$2:$H$59,MATCH(INDEX(Account!$J$2:$J$131,MATCH($B845,Account!$A$2:$A$131,0))&"-"&$C845&"-"&$D845,'Bill Report Reference'!$I$2:$I$59,0)),"") -> https://www.congress.gov/119/crpt/hrpt652/CRPT-119hrpt652.pdf
A846: OBS-0971 | B846: ACC-USPTO-SE | C846: 2027 | D846: House Reported | E846: House | F846: =IFERROR(""&INDEX('Bill Report Reference'!$E$2:$E$59,MATCH(INDEX(Account!$J$2:$J$131,MATCH($B846,Account!$A$2:$A$131,0))&"-"&$C846&"-"&$D846,'Bill Report Reference'!$I$2:$I$59,0)),"") -> H.R.8845 | G846: =IFERROR(""&INDEX('Bill Report Reference'!$F$2:$F$59,MATCH(INDEX(Account!$J$2:$J$131,MATCH($B846,Account!$A$2:$A$131,0))&"-"&$C846&"-"&$D846,'Bill Report Reference'!$I$2:$I$59,0)),"") -> H.Rept.119-652 | H846: 5160000000 | I846: budget authority | K846: FALSE | M846: SRC-CBO-HR8845-FY2027 | N846: 1-14 | O846: Title I, Spending | P846: human-entered | Q846: 1 | R846: human-verified | S846: =IFERROR(""&INDEX('Bill Report Reference'!$G$2:$G$59,MATCH(INDEX(Account!$J$2:$J$131,MATCH($B846,Account!$A$2:$A$131,0))&"-"&$C846&"-"&$D846,'Bill Report Reference'!$I$2:$I$59,0)),"") -> https://www.govinfo.gov/content/pkg/BILLS-119hr8845rh/pdf/BILLS-119hr8845rh.pdf | T846: =IFERROR(""&INDEX('Bill Report Reference'!$H$2:$H$59,MATCH(INDEX(Account!$J$2:$J$131,MATCH($B846,Account!$A$2:$A$131,0))&"-"&$C846&"-"&$D846,'Bill Report Reference'!$I$2:$I$59,0)),"") -> https://www.congress.gov/119/crpt/hrpt652/CRPT-119hrpt652.pdf
A847: OBS-0972 | B847: ACC-USPTO-SE | C847: 2027 | D847: House Reported | E847: House | F847: =IFERROR(""&INDEX('Bill Report Reference'!$E$2:$E$59,MATCH(INDEX(Account!$J$2:$J$131,MATCH($B847,Account!$A$2:$A$131,0))&"-"&$C847&"-"&$D847,'Bill Report Reference'!$I$2:$I$59,0)),"") -> H.R.8845 | G847: =IFERROR(""&INDEX('Bill Report Reference'!$F$2:$F$59,MATCH(INDEX(Account!$J$2:$J$131,MATCH($B847,Account!$A$2:$A$131,0))&"-"&$C847&"-"&$D847,'Bill Report Reference'!$I$2:$I$59,0)),"") -> H.Rept.119-652 | H847: -5160000000 | I847: offsetting_collection | K847: TRUE | M847: SRC-CBO-HR8845-FY2027 | N847: 1-14 | O847: Title I, Fee Collections (-) Estimated | P847: human-entered | Q847: 1 | R847: human-verified | S847: =IFERROR(""&INDEX('Bill Report Reference'!$G$2:$G$59,MATCH(INDEX(Account!$J$2:$J$131,MATCH($B847,Account!$A$2:$A$131,0))&"-"&$C847&"-"&$D847,'Bill Report Reference'!$I$2:$I$59,0)),"") -> https://www.govinfo.gov/content/pkg/BILLS-119hr8845rh/pdf/BILLS-119hr8845rh.pdf | T847: =IFERROR(""&INDEX('Bill Report Reference'!$H$2:$H$59,MATCH(INDEX(Account!$J$2:$J$131,MATCH($B847,Account!$A$2:$A$131,0))&"-"&$C847&"-"&$D847,'Bill Report Reference'!$I$2:$I$59,0)),"") -> https://www.congress.gov/119/crpt/hrpt652/CRPT-119hrpt652.pdf
A848: OBS-0973 | B848: ACC-USPTO-SE | C848: 2027 | D848: House Reported | E848: House | F848: =IFERROR(""&INDEX('Bill Report Reference'!$E$2:$E$59,MATCH(INDEX(Account!$J$2:$J$131,MATCH($B848,Account!$A$2:$A$131,0))&"-"&$C848&"-"&$D848,'Bill Report Reference'!$I$2:$I$59,0)),"") -> H.R.8845 | G848: =IFERROR(""&INDEX('Bill Report Reference'!$F$2:$F$59,MATCH(INDEX(Account!$J$2:$J$131,MATCH($B848,Account!$A$2:$A$131,0))&"-"&$C848&"-"&$D848,'Bill Report Reference'!$I$2:$I$59,0)),"") -> H.Rept.119-652 | H848: -2000000 | I848: transfer | K848: FALSE | M848: SRC-CBO-HR8845-FY2027 | N848: 1-14 | O848: Title I, Transfer to OIG | P848: human-entered | Q848: 1 | R848: human-verified | S848: =IFERROR(""&INDEX('Bill Report Reference'!$G$2:$G$59,MATCH(INDEX(Account!$J$2:$J$131,MATCH($B848,Account!$A$2:$A$131,0))&"-"&$C848&"-"&$D848,'Bill Report Reference'!$I$2:$I$59,0)),"") -> https://www.govinfo.gov/content/pkg/BILLS-119hr8845rh/pdf/BILLS-119hr8845rh.pdf | T848: =IFERROR(""&INDEX('Bill Report Reference'!$H$2:$H$59,MATCH(INDEX(Account!$J$2:$J$131,MATCH($B848,Account!$A$2:$A$131,0))&"-"&$C848&"-"&$D848,'Bill Report Reference'!$I$2:$I$59,0)),"") -> https://www.congress.gov/119/crpt/hrpt652/CRPT-119hrpt652.pdf
A849: OBS-0974 | B849: ACC-DOJ-ANTITRUST-SE | C849: 2027 | D849: House Reported | E849: House | F849: =IFERROR(""&INDEX('Bill Report Reference'!$E$2:$E$59,MATCH(INDEX(Account!$J$2:$J$131,MATCH($B849,Account!$A$2:$A$131,0))&"-"&$C849&"-"&$D849,'Bill Report Reference'!$I$2:$I$59,0)),"") -> H.R.8845 | G849: =IFERROR(""&INDEX('Bill Report Reference'!$F$2:$F$59,MATCH(INDEX(Account!$J$2:$J$131,MATCH($B849,Account!$A$2:$A$131,0))&"-"&$C849&"-"&$D849,'Bill Report Reference'!$I$2:$I$59,0)),"") -> H.Rept.119-652 | H849: 313000000 | I849: budget authority | K849: FALSE | M849: SRC-CBO-HR8845-FY2027 | N849: 1-14 | O849: Title II, Salaries and Expenses | P849: human-entered | Q849: 1 | R849: human-verified | S849: =IFERROR(""&INDEX('Bill Report Reference'!$G$2:$G$59,MATCH(INDEX(Account!$J$2:$J$131,MATCH($B849,Account!$A$2:$A$131,0))&"-"&$C849&"-"&$D849,'Bill Report Reference'!$I$2:$I$59,0)),"") -> https://www.govinfo.gov/content/pkg/BILLS-119hr8845rh/pdf/BILLS-119hr8845rh.pdf | T849: =IFERROR(""&INDEX('Bill Report Reference'!$H$2:$H$59,MATCH(INDEX(Account!$J$2:$J$131,MATCH($B849,Account!$A$2:$A$131,0))&"-"&$C849&"-"&$D849,'Bill Report Reference'!$I$2:$I$59,0)),"") -> https://www.congress.gov/119/crpt/hrpt652/CRPT-119hrpt652.pdf
A850: OBS-0975 | B850: ACC-DOJ-ANTITRUST-SE | C850: 2027 | D850: House Reported | E850: House | F850: =IFERROR(""&INDEX('Bill Report Reference'!$E$2:$E$59,MATCH(INDEX(Account!$J$2:$J$131,MATCH($B850,Account!$A$2:$A$131,0))&"-"&$C850&"-"&$D850,'Bill Report Reference'!$I$2:$I$59,0)),"") -> H.R.8845 | G850: =IFERROR(""&INDEX('Bill Report Reference'!$F$2:$F$59,MATCH(INDEX(Account!$J$2:$J$131,MATCH($B850,Account!$A$2:$A$131,0))&"-"&$C850&"-"&$D850,'Bill Report Reference'!$I$2:$I$59,0)),"") -> H.Rept.119-652 | H850: -313000000 | I850: offsetting_collection | K850: TRUE | M850: SRC-CBO-HR8845-FY2027 | N850: 1-14 | O850: Title II, Hart-Scott-Rodino fee collections | P850: human-entered | Q850: 1 | R850: human-verified | S850: =IFERROR(""&INDEX('Bill Report Reference'!$G$2:$G$59,MATCH(INDEX(Account!$J$2:$J$131,MATCH($B850,Account!$A$2:$A$131,0))&"-"&$C850&"-"&$D850,'Bill Report Reference'!$I$2:$I$59,0)),"") -> https://www.govinfo.gov/content/pkg/BILLS-119hr8845rh/pdf/BILLS-119hr8845rh.pdf | T850: =IFERROR(""&INDEX('Bill Report Reference'!$H$2:$H$59,MATCH(INDEX(Account!$J$2:$J$131,MATCH($B850,Account!$A$2:$A$131,0))&"-"&$C850&"-"&$D850,'Bill Report Reference'!$I$2:$I$59,0)),"") -> https://www.congress.gov/119/crpt/hrpt652/CRPT-119hrpt652.pdf
A851: OBS-0976 | B851: ACC-DOJ-USTSF | C851: 2027 | D851: House Reported | E851: House | F851: =IFERROR(""&INDEX('Bill Report Reference'!$E$2:$E$59,MATCH(INDEX(Account!$J$2:$J$131,MATCH($B851,Account!$A$2:$A$131,0))&"-"&$C851&"-"&$D851,'Bill Report Reference'!$I$2:$I$59,0)),"") -> H.R.8845 | G851: =IFERROR(""&INDEX('Bill Report Reference'!$F$2:$F$59,MATCH(INDEX(Account!$J$2:$J$131,MATCH($B851,Account!$A$2:$A$131,0))&"-"&$C851&"-"&$D851,'Bill Report Reference'!$I$2:$I$59,0)),"") -> H.Rept.119-652 | H851: 198000000 | I851: budget authority | K851: FALSE | M851: SRC-CBO-HR8845-FY2027 | N851: 1-14 | O851: Title II, US Trustee System | P851: human-entered | Q851: 1 | R851: human-verified | S851: =IFERROR(""&INDEX('Bill Report Reference'!$G$2:$G$59,MATCH(INDEX(Account!$J$2:$J$131,MATCH($B851,Account!$A$2:$A$131,0))&"-"&$C851&"-"&$D851,'Bill Report Reference'!$I$2:$I$59,0)),"") -> https://www.govinfo.gov/content/pkg/BILLS-119hr8845rh/pdf/BILLS-119hr8845rh.pdf | T851: =IFERROR(""&INDEX('Bill Report Reference'!$H$2:$H$59,MATCH(INDEX(Account!$J$2:$J$131,MATCH($B851,Account!$A$2:$A$131,0))&"-"&$C851&"-"&$D851,'Bill Report Reference'!$I$2:$I$59,0)),"") -> https://www.congress.gov/119/crpt/hrpt652/CRPT-119hrpt652.pdf
A852: OBS-0977 | B852: ACC-DOJ-USTSF | C852: 2027 | D852: House Reported | E852: House | F852: =IFERROR(""&INDEX('Bill Report Reference'!$E$2:$E$59,MATCH(INDEX(Account!$J$2:$J$131,MATCH($B852,Account!$A$2:$A$131,0))&"-"&$C852&"-"&$D852,'Bill Report Reference'!$I$2:$I$59,0)),"") -> H.R.8845 | G852: =IFERROR(""&INDEX('Bill Report Reference'!$F$2:$F$59,MATCH(INDEX(Account!$J$2:$J$131,MATCH($B852,Account!$A$2:$A$131,0))&"-"&$C852&"-"&$D852,'Bill Report Reference'!$I$2:$I$59,0)),"") -> H.Rept.119-652 | H852: -279000000 | I852: offsetting_collection | K852: TRUE | M852: SRC-CBO-HR8845-FY2027 | N852: 1-14 | O852: Title II, USTSF Fee Collections | P852: human-entered | Q852: 1 | R852: human-verified | S852: =IFERROR(""&INDEX('Bill Report Reference'!$G$2:$G$59,MATCH(INDEX(Account!$J$2:$J$131,MATCH($B852,Account!$A$2:$A$131,0))&"-"&$C852&"-"&$D852,'Bill Report Reference'!$I$2:$I$59,0)),"") -> https://www.govinfo.gov/content/pkg/BILLS-119hr8845rh/pdf/BILLS-119hr8845rh.pdf | T852: =IFERROR(""&INDEX('Bill Report Reference'!$H$2:$H$59,MATCH(INDEX(Account!$J$2:$J$131,MATCH($B852,Account!$A$2:$A$131,0))&"-"&$C852&"-"&$D852,'Bill Report Reference'!$I$2:$I$59,0)),"") -> https://www.congress.gov/119/crpt/hrpt652/CRPT-119hrpt652.pdf
A853: OBS-0978 | B853: ACC-NOAA-ORF | C853: 2027 | D853: House Reported | E853: House | F853: =IFERROR(""&INDEX('Bill Report Reference'!$E$2:$E$59,MATCH(INDEX(Account!$J$2:$J$131,MATCH($B853,Account!$A$2:$A$131,0))&"-"&$C853&"-"&$D853,'Bill Report Reference'!$I$2:$I$59,0)),"") -> H.R.8845 | G853: =IFERROR(""&INDEX('Bill Report Reference'!$F$2:$F$59,MATCH(INDEX(Account!$J$2:$J$131,MATCH($B853,Account!$A$2:$A$131,0))&"-"&$C853&"-"&$D853,'Bill Report Reference'!$I$2:$I$59,0)),"") -> H.Rept.119-652 | H853: 4008000000 | I853: budget authority | K853: FALSE | M853: SRC-CBO-HR8845-FY2027 | N853: 1-14 | O853: Title I, Operations, research, and facilities | P853: human-entered | Q853: 1 | R853: human-verified | S853: =IFERROR(""&INDEX('Bill Report Reference'!$G$2:$G$59,MATCH(INDEX(Account!$J$2:$J$131,MATCH($B853,Account!$A$2:$A$131,0))&"-"&$C853&"-"&$D853,'Bill Report Reference'!$I$2:$I$59,0)),"") -> https://www.govinfo.gov/content/pkg/BILLS-119hr8845rh/pdf/BILLS-119hr8845rh.pdf | T853: =IFERROR(""&INDEX('Bill Report Reference'!$H$2:$H$59,MATCH(INDEX(Account!$J$2:$J$131,MATCH($B853,Account!$A$2:$A$131,0))&"-"&$C853&"-"&$D853,'Bill Report Reference'!$I$2:$I$59,0)),"") -> https://www.congress.gov/119/crpt/hrpt652/CRPT-119hrpt652.pdf
A854: OBS-0979 | B854: ACC-NOAA-ORF | C854: 2027 | D854: House Reported | E854: House | F854: =IFERROR(""&INDEX('Bill Report Reference'!$E$2:$E$59,MATCH(INDEX(Account!$J$2:$J$131,MATCH($B854,Account!$A$2:$A$131,0))&"-"&$C854&"-"&$D854,'Bill Report Reference'!$I$2:$I$59,0)),"") -> H.R.8845 | G854: =IFERROR(""&INDEX('Bill Report Reference'!$F$2:$F$59,MATCH(INDEX(Account!$J$2:$J$131,MATCH($B854,Account!$A$2:$A$131,0))&"-"&$C854&"-"&$D854,'Bill Report Reference'!$I$2:$I$59,0)),"") -> H.Rept.119-652 | H854: 659000000 | I854: transfer | K854: FALSE | L854: ACC-NOAA-PDF | M854: SRC-CBO-HR8845-FY2027 | N854: 1-14 | O854: Title I, Transfer from Promote & Dev Fisheries | P854: human-entered | Q854: 1 | R854: human-verified | S854: =IFERROR(""&INDEX('Bill Report Reference'!$G$2:$G$59,MATCH(INDEX(Account!$J$2:$J$131,MATCH($B854,Account!$A$2:$A$131,0))&"-"&$C854&"-"&$D854,'Bill Report Reference'!$I$2:$I$59,0)),"") -> https://www.govinfo.gov/content/pkg/BILLS-119hr8845rh/pdf/BILLS-119hr8845rh.pdf | T854: =IFERROR(""&INDEX('Bill Report Reference'!$H$2:$H$59,MATCH(INDEX(Account!$J$2:$J$131,MATCH($B854,Account!$A$2:$A$131,0))&"-"&$C854&"-"&$D854,'Bill Report Reference'!$I$2:$I$59,0)),"") -> https://www.congress.gov/119/crpt/hrpt652/CRPT-119hrpt652.pdf
A855: OBS-0980 | B855: ACC-NOAA-ORF | C855: 2027 | D855: House Reported | E855: House | F855: =IFERROR(""&INDEX('Bill Report Reference'!$E$2:$E$59,MATCH(INDEX(Account!$J$2:$J$131,MATCH($B855,Account!$A$2:$A$131,0))&"-"&$C855&"-"&$D855,'Bill Report Reference'!$I$2:$I$59,0)),"") -> H.R.8845 | G855: =IFERROR(""&INDEX('Bill Report Reference'!$F$2:$F$59,MATCH(INDEX(Account!$J$2:$J$131,MATCH($B855,Account!$A$2:$A$131,0))&"-"&$C855&"-"&$D855,'Bill Report Reference'!$I$2:$I$59,0)),"") -> H.Rept.119-652 | H855: -75000000 | I855: rescission | K855: FALSE | M855: SRC-CBO-HR8845-FY2027 | N855: 1-14 | O855: Title V, Sec. 521(a)(1) | P855: human-entered | Q855: 1 | R855: human-verified | S855: =IFERROR(""&INDEX('Bill Report Reference'!$G$2:$G$59,MATCH(INDEX(Account!$J$2:$J$131,MATCH($B855,Account!$A$2:$A$131,0))&"-"&$C855&"-"&$D855,'Bill Report Reference'!$I$2:$I$59,0)),"") -> https://www.govinfo.gov/content/pkg/BILLS-119hr8845rh/pdf/BILLS-119hr8845rh.pdf | T855: =IFERROR(""&INDEX('Bill Report Reference'!$H$2:$H$59,MATCH(INDEX(Account!$J$2:$J$131,MATCH($B855,Account!$A$2:$A$131,0))&"-"&$C855&"-"&$D855,'Bill Report Reference'!$I$2:$I$59,0)),"") -> https://www.congress.gov/119/crpt/hrpt652/CRPT-119hrpt652.pdf
...

Sheet Account Relationship
A1: relationship_id | B1: from_account_id | C1: to_account_id | D1: relationship_type | E1: effective_fiscal_year | F1: evidence | G1: confidence | H1: human_reviewed
A2: REL-LHHS-0001 | B2: ACC-HHS-HRSA-TOTAL | C2: ACC-HHS-AHA-TOTAL | D2: consolidated | E2: 2026 | F2: Proposed, not enacted. FY2026 Budget Appendix (BUDGET-2026-APP) pp. 332, 338, 339, 346: 'In 2026 HRSA will be reorganized into the Agency [p.339: Administration] for a Healthy America to improve coordination of health resources for Americans.' Repeated for 2027 in the FY2027 Appendix (BUDGET-2027-APP) pp. 434, 439, 449. P.L. 119-75 keeps HRSA. Also FY2026 AHA Congressional Justification (SRC-CJ-AHA-FY2026) p.11 (PDF p.1), Overview of Budget: 'the AHA Budget consolidates and streamlines chronic care and disease prevention programs across the Office of the Assistant Secretary for Health (OASH), Health Resources and Services Administration (HRSA), Substance Abuse and Mental Health Services Administration (SAMHSA), the National Institute of Environmental Health Sciences (NIEHS), and several centers and programs of the Centers for Disease Control and Prevention (CDC)' -- names HRSA. | G2: 0.9 | H2: FALSE
A3: REL-LHHS-0002 | B3: ACC-HHS-SAMHSA-TOTAL | C3: ACC-HHS-AHA-TOTAL | D3: consolidated | E3: 2026 | F3: Proposed, not enacted. FY2026 Budget Appendix p.360: 'In 2026 SAMHSA will be reorganized into the Agency for a Healthy America to improve coordination of health resources for Americans.' FY2027 Appendix p.464 repeats it for 2027. P.L. 119-75 keeps SAMHSA. Also FY2026 AHA Congressional Justification (SRC-CJ-AHA-FY2026) p.11 (PDF p.1), Overview of Budget: 'the AHA Budget consolidates and streamlines chronic care and disease prevention programs across the Office of the Assistant Secretary for Health (OASH), Health Resources and Services Administration (HRSA), Substance Abuse and Mental Health Services Administration (SAMHSA), the National Institute of Environmental Health Sciences (NIEHS), and several centers and programs of the Centers for Disease Control and Prevention (CDC)' -- names SAMHSA. | G3: 0.9 | H3: FALSE
A4: REL-LHHS-0005 | B4: ACC-HHS-NIH-NIDA | C4: ACC-HHS-NIH-SUBSTANCE-USE | D4: consolidated | E4: 2027 | F4: Proposed, not enacted. FY2027 Budget Appendix (BUDGET-2027-APP, HHS chapter granule PDF p.29): 'The 2027 Budget proposes to ... consolidate the National Institute on Drug Abuse and the National Institute on Alcohol Abuse and Alcoholism into the National Institute of Substance Use and Addiction Research.' | G4: 0.9 | H4: FALSE
A5: REL-LHHS-0006 | B5: ACC-HHS-NIH-NIAAA | C5: ACC-HHS-NIH-SUBSTANCE-USE | D5: consolidated | E5: 2027 | F5: As REL-LHHS-0005. | G5: 0.9 | H5: FALSE
A6: REL-LHHS-0009 | B6: ACC-HHS-ASPR-RDP | C6: ACC-HHS-OS-PHSSEF | D6: uncertain | E6: 2024 | F6: Not confirmed (owner, 2026-10-06). Proposed type, from explicit text: split_from -- FY2024 Budget Appendix (BUDGET-2024-APP, HHS chapter granule BUDGET-2024-APP-1-10, PDF pp. 59 and 64): 'The 2024 Budget requests resources for the Administration for Strategic Preparedness and Response (ASPR) in a new account, separate from PHSSEF where funding has historically been appropriated.' P.L. 117-328 (FY2023) funds the preparedness programs under the Office of the Secretary's 'Public Health and Social Services Emergency Fund' heading (p.419); P.L. 118-47 (FY2024) has no such heading and an 'Administration for Strategic Preparedness and Response' with this heading (p.211). | G6: 0.5 | H6: FALSE
A7: REL-LHHS-0010 | B7: ACC-HHS-ASPR-OPER | C7: ACC-HHS-OS-PHSSEF | D7: uncertain | E7: 2024 | F7: Not confirmed (owner, 2026-10-06). Proposed type, from explicit text: split_from -- FY2024 Budget Appendix (BUDGET-2024-APP, HHS chapter granule BUDGET-2024-APP-1-10, PDF pp. 59 and 64): 'The 2024 Budget requests resources for the Administration for Strategic Preparedness and Response (ASPR) in a new account, separate from PHSSEF where funding has historically been appropriated.' P.L. 117-328 (FY2023) funds the preparedness programs under the Office of the Secretary's 'Public Health and Social Services Emergency Fund' heading (p.419); P.L. 118-47 (FY2024) has no such heading and an 'Administration for Strategic Preparedness and Response' with this heading (p.211). | G7: 0.5 | H7: FALSE
A8: REL-LHHS-0011 | B8: ACC-HHS-NIH-NIEHS | C8: ACC-HHS-AHA-TOTAL | D8: moved_reclassified | E8: 2026 | F8: Proposed, not enacted (FY2026 President's Budget). FY2026 AHA Congressional Justification (SRC-CJ-AHA-FY2026) p.11 (PDF p.1), Overview of Budget: 'the AHA Budget consolidates and streamlines chronic care and disease prevention programs across the Office of the Assistant Secretary for Health (OASH), Health Resources and Services Administration (HRSA), Substance Abuse and Mental Health Services Administration (SAMHSA), the National Institute of Environmental Health Sciences (NIEHS), and several centers and programs of the Centers for Disease Control and Prevention (CDC)'. p.13 (PDF p.3), Environmental Health: 'National Institute of Environmental Health Sciences (NIEHS): $594.1 million'. Amount match: H.Rept. 119-271 p.344 FY 2026 Request, NIEHS 594,086 (thousands) = $594.1M rounded. The FY2027 request instead proposes moving NIEHS into CDC (a placement note on the account, not a relationship). P.L. 119-75 keeps NIEHS under NIH. | G8: 0.9 | H8: FALSE
A9: REL-LHHS-0012 | B9: ACC-HHS-CDC-INJURY-PREVENTION | C9: ACC-HHS-AHA-TOTAL | D9: moved_reclassified | E9: 2026 | F9: Proposed, not enacted (FY2026 President's Budget). FY2026 AHA Congressional Justification (SRC-CJ-AHA-FY2026) p.11 (PDF p.1), Overview of Budget: 'the AHA Budget consolidates and streamlines chronic care and disease prevention programs across the Office of the Assistant Secretary for Health (OASH), Health Resources and Services Administration (HRSA), Substance Abuse and Mental Health Services Administration (SAMHSA), the National Institute of Environmental Health Sciences (NIEHS), and several centers and programs of the Centers for Disease Control and Prevention (CDC)'. p.11 (PDF p.1), Primary Care: 'National Center for Injury Prevention and Control: $550.1 million'. Amount match: H.Rept. 119-271 p.341 FY 2026 Request, Injury Prevention and Control 550,079 (thousands) = $550.1M rounded. P.L. 119-75 keeps it under CDC. | G9: 0.9 | H9: FALSE
A10: REL-LHHS-0013 | B10: ACC-HHS-CDC-BIRTH-DEFECTS | C10: ACC-HHS-AHA-TOTAL | D10: moved_reclassified | E10: 2026 | F10: Proposed, not enacted (FY2026 President's Budget). FY2026 AHA Congressional Justification (SRC-CJ-AHA-FY2026) p.11 (PDF p.1), Overview of Budget: 'the AHA Budget consolidates and streamlines chronic care and disease prevention programs across the Office of the Assistant Secretary for Health (OASH), Health Resources and Services Administration (HRSA), Substance Abuse and Mental Health Services Administration (SAMHSA), the National Institute of Environmental Health Sciences (NIEHS), and several centers and programs of the Centers for Disease Control and Prevention (CDC)'. pp.15-16 (PDF pp.5-6), Maternal and Child Health: 'Birth Defects, Developmental Disabilities, Disability & Health: $157.8 million'. Amount match: H.Rept. 119-271 p.341 FY 2026 Request, Birth Defects, Developmental Disabilities, Disabilities and Health 157,810 (thousands) = $157.8M rounded. P.L. 119-75 keeps it under CDC. | G10: 0.9 | H10: FALSE
A11: REL-LHHS-0014 | B11: ACC-HHS-CDC-NIOSH | C11: ACC-HHS-AHA-TOTAL | D11: moved_reclassified | E11: 2026 | F11: Proposed, not enacted (FY2026 President's Budget). FY2026 AHA Congressional Justification (SRC-CJ-AHA-FY2026) p.11 (PDF p.1), Overview of Budget: 'the AHA Budget consolidates and streamlines chronic care and disease prevention programs across the Office of the Assistant Secretary for Health (OASH), Health Resources and Services Administration (HRSA), Substance Abuse and Mental Health Services Administration (SAMHSA), the National Institute of Environmental Health Sciences (NIEHS), and several centers and programs of the Centers for Disease Control and Prevention (CDC)'. p.13 (PDF p.3), Environmental Health: 'Occupational Safety and Health: $73.2 million ... in discretionary funding to support select programs in worker safety and health, including the National Mesothelioma Registry and Tissue Bank, National Firefighter Registry for Cancer, and Mining Research'. Amount match: H.Rept. 119-271 p.342 FY 2026 Request, National Institute for Occupational Safety and Health 73,200 (thousands) = $73.2M: the whole NIOSH request. P.L. 119-75 keeps NIOSH under CDC. | G11: 0.9 | H11: FALSE
A12: REL-LHHS-0015 | B12: ACC-HHS-CDC-EEOICP | C12: ACC-HHS-AHA-TOTAL | D12: moved_reclassified | E12: 2026 | F12: Proposed, not enacted (FY2026 President's Budget). FY2026 AHA Congressional Justification (SRC-CJ-AHA-FY2026) p.11 (PDF p.1), Overview of Budget: 'the AHA Budget consolidates and streamlines chronic care and disease prevention programs across the Office of the Assistant Secretary for Health (OASH), Health Resources and Services Administration (HRSA), Substance Abuse and Mental Health Services Administration (SAMHSA), the National Institute of Environmental Health Sciences (NIEHS), and several centers and programs of the Centers for Disease Control and Prevention (CDC)'. p.14 (PDF p.4), Environmental Health: 'Energy Employees Occupational Illness Compensation Program Act (EEOICPA): $50.8 million in mandatory funding (post-sequester)'. Amount match, pre- vs post-sequester: H.Rept. 119-271 p.342 FY 2026 Request prints 55,358 (thousands), the appropriation before sequestration; 55,358 - 50,800 = 4,558 (8.2%) sequestered. The FY2026 Budget Appendix (BUDGET-2026-APP p.333), AHA's proposed Environmental Health account (075-0386), appropriates the same '$55,358,000' for EEOICPA and shows, in $ millions for 2026: mandatory appropriation 55, permanently reduced -4, mandatory total 51 (= $50.8M rounded). P.L. 119-75 keeps it under CDC. | G12: 0.9 | H12: FALSE

Sheet Source Document
A1: document_id | B1: source_agency | C1: url_or_identifier | D1: document_type | E1: congress_session | F1: fiscal_year | G1: publication_date | H1: stage | I1: retrieval_timestamp | J1: source_page | K1: also_covers | L1: notes
A2: SRC-CRPT-119HRPT652 | B2: House Committee on Appropriations | C2: https://www.congress.gov/119/crpt/hrpt652/CRPT-119hrpt652.pdf | D2: committee_report | E2: 119-2 | F2: 2027 | G2: 2026-05-15 00:00:00 | H2: House Reported | I2: 2026-09-24 14:18:00 | J2: 169-170 | K2: FY2026 Enacted
A3: SRC-CRPT-119SRPT44 | B3: Senate Committee on Appropriations | C3: https://www.congress.gov/119/crpt/srpt44/CRPT-119srpt44.pdf | D3: committee_report | E3: 119-1 | F3: 2026 | G3: 2025-07-17 00:00:00 | H3: Senate Reported | I3: 2026-09-24 14:18:00 | J3: 217-219
A4: SRC-CRPT-119HRPT272 | B4: House Committee on Appropriations | C4: https://www.congress.gov/119/crpt/hrpt272/CRPT-119hrpt272.pdf | D4: committee_report | E4: 119-1 | F4: 2026 | G4: 2025-09-12 00:00:00 | H4: House Reported | I4: 2026-09-24 14:18:00 | J4: 244-262 | K4: FY2025 Enacted
A5: SRC-EXPL-FY2026-PB | B5: House Committee on Appropriations | C5: https://rules.house.gov/sites/evo-subsites/rules.house.gov/files/documents/division-a-commerce-justice-science_0.pdf | D5: explanatory_statement | E5: 119-2 | F5: 2026 | G5: 2026-01-06 00:00:00 | H5: Enacted | I5: 2026-09-24 14:18:00 | J5: 128-130 | K5: FY2026 President's Budget
A6: SRC-CRPT-118SRPT198 | B6: Senate Committee on Appropriations | C6: https://www.congress.gov/118/crpt/srpt198/CRPT-118srpt198.pdf | D6: committee_report | E6: 118-2 | F6: 2025 | G6: 2024-07-25 00:00:00 | H6: Senate Reported | I6: 2026-09-24 14:18:00 | J6: 220-231
A7: SRC-CRPT-118HRPT582 | B7: House Committee on Appropriations | C7: https://www.congress.gov/118/crpt/hrpt582/CRPT-118hrpt582.pdf | D7: committee_report | E7: 118-2 | F7: 2025 | G7: 2024-07-11 00:00:00 | H7: House Reported | I7: 2026-09-24 14:18:00 | J7: 247-248 | K7: FY2025 President's Budget; FY2024 Enacted
A8: SRC-CRPT-118SRPT62 | B8: Senate Committee on Appropriations | C8: https://www.congress.gov/118/crpt/srpt62/CRPT-118srpt62.pdf | D8: committee_report | E8: 118-1 | F8: 2024 | G8: 2023-07-13 00:00:00 | H8: Senate Reported | I8: 2026-09-24 14:18:00 | J8: 212-225 | K8: FY2024 President's Budget; FY2023 Enacted
A9: SRC-EXPL-FY2024-HOUSE | B9: House Committee on Appropriations | C9: https://appropriations.house.gov/sites/evo-subsites/republicans-appropriations.house.gov/files/FY24-CJS-Explanatory-Materials.pdf | D9: explanatory_statement | E9: 118-1 | F9: 2024 | G9: 2023-10-31 00:00:00 | H9: House Reported | I9: 2026-09-24 14:18:00 | J9: 170-171
A10: SRC-EXPL-FY2023-SENATE | B10: Senate Committee on Appropriations | C10: https://www.appropriations.senate.gov/imo/media/doc/CJSFY23RPT.PDF | D10: explanatory_statement | E10: 117-2 | F10: 2023 | G10: 2022-07-28 00:00:00 | H10: Senate Reported | I10: 2026-09-24 14:18:00 | J10: 215-216
A11: SRC-CRPT-117HRPT395 | B11: House Committee on Appropriations | C11: https://www.govinfo.gov/content/pkg/CRPT-117hrpt395/pdf/CRPT-117hrpt395.pdf | D11: committee_report | E11: 117-2 | F11: 2023 | G11: 2022-06-30 00:00:00 | H11: House Reported | I11: 2026-09-24 14:18:00 | J11: 210-230 | K11: FY2023 President's Budget; FY2022 Enacted
A12: SRC-EXPL-FY2022-SENATE | B12: Senate Committee on Appropriations | C12: https://www.appropriations.senate.gov/imo/media/doc/CJSRept_Final.PDF | D12: explanatory_statement | E12: 117-1 | F12: 2022 | G12: 2021-10-18 00:00:00 | H12: Senate Reported | I12: 2026-09-24 14:18:00 | J12: 207-208
A13: SRC-CRPT-117HRPT97 | B13: House Committee on Appropriations | C13: https://www.govinfo.gov/content/pkg/CRPT-117hrpt97/pdf/CRPT-117hrpt97.pdf | D13: committee_report | E13: 117-1 | F13: 2022 | G13: 2021-07-19 00:00:00 | H13: House Reported | I13: 2026-09-24 14:18:00 | J13: 213-214 | K13: FY2022 President's Budget; FY2021 Enacted
A14: SRC-EXPL-FY2021-SENATE | B14: Senate Committee on Appropriations | C14: https://www.appropriations.senate.gov/imo/media/doc/CJSRept.pdf | D14: explanatory_statement | E14: 116-2 | F14: 2021 | G14: 2020-11-10 00:00:00 | H14: Senate Reported | I14: 2026-09-24 14:18:00 | J14: 197-199
A15: SRC-CRPT-116HRPT455 | B15: House Committee on Appropriations | C15: https://www.govinfo.gov/content/pkg/CRPT-116hrpt455/pdf/CRPT-116hrpt455.pdf | D15: committee_report | E15: 116-2 | F15: 2021 | G15: 2020-07-16 00:00:00 | H15: House Reported | I15: 2026-09-24 14:18:00 | J15: 178-197 | K15: FY2021 President's Budget; FY2020 Enacted
A16: SRC-CRPT-116SRPT127 | B16: Senate Committee on Appropriations | C16: https://www.govinfo.gov/content/pkg/CRPT-116srpt127/pdf/CRPT-116srpt127.pdf | D16: committee_report | E16: 116-1 | F16: 2020 | G16: 2019-09-26 00:00:00 | H16: Senate Reported | I16: 2026-09-24 14:18:00 | J16: 186-195
A17: SRC-CRPT-116HRPT101 | B17: House Committee on Appropriations | C17: https://www.govinfo.gov/content/pkg/CRPT-116hrpt101/pdf/CRPT-116hrpt101.pdf | D17: committee_report | E17: 116-1 | F17: 2020 | G17: 2019-06-03 00:00:00 | H17: House Reported | I17: 2026-09-24 14:18:00 | J17: 139-152 | K17: FY2020 President's Budget; FY2019 Enacted
A18: SRC-CRPT-115SRPT275 | B18: Senate Committee on Appropriations | C18: https://www.govinfo.gov/content/pkg/CRPT-115srpt275/pdf/CRPT-115srpt275.pdf | D18: committee_report | E18: 115-2 | F18: 2019 | G18: 2018-06-14 00:00:00 | H18: Senate Reported | I18: 2026-09-24 14:18:00 | J18: 157-158
A19: SRC-CRPT-115HRPT704 | B19: House Committee on Appropriations | C19: https://www.govinfo.gov/content/pkg/CRPT-115hrpt704/pdf/CRPT-115hrpt704.pdf | D19: committee_report | E19: 115-2 | F19: 2019 | G19: 2018-05-24 00:00:00 | H19: House Reported | I19: 2026-09-24 14:18:00 | J19: 120-135 | K19: FY2019 President's Budget; FY2018 Enacted
A20: SRC-CRPT-115SRPT139 | B20: Senate Committee on Appropriations | C20: https://www.govinfo.gov/content/pkg/CRPT-115srpt139/pdf/CRPT-115srpt139.pdf | D20: committee_report | E20: 115-1 | F20: 2018 | G20: 2017-07-27 00:00:00 | H20: Senate Reported | I20: 2026-09-24 14:18:00 | J20: 140-141
A21: SRC-CRPT-115HRPT231 | B21: House Committee on Appropriations | C21: https://www.govinfo.gov/content/pkg/CRPT-115hrpt231/pdf/CRPT-115hrpt231.pdf | D21: committee_report | E21: 115-1 | F21: 2018 | G21: 2017-07-17 00:00:00 | H21: House Reported | I21: 2026-09-24 14:18:00 | J21: 120-121 | K21: FY2018 President's Budget; FY2017 Enacted
A22: SRC-CRPT-114SRPT239 | B22: Senate Committee on Appropriations | C22: https://www.govinfo.gov/content/pkg/CRPT-114srpt239/pdf/CRPT-114srpt239.pdf | D22: committee_report | E22: 114-2 | F22: 2017 | G22: 2016-04-21 | H22: Senate Reported | I22: 2026-09-24 14:18:00 | J22: 139-140
A23: SRC-CRPT-114HRPT605 | B23: House Committee on Appropriations | C23: https://www.govinfo.gov/content/pkg/CRPT-114hrpt605/pdf/CRPT-114hrpt605.pdf | D23: committee_report | E23: 114-2 | F23: 2017 | G23: 2016-06-07 00:00:00 | H23: House Reported | I23: 2026-09-24 14:18:00 | J23: 114-115 | K23: FY2017 President's Budget
A24: SRC-CBO-HR8845-FY2027 | B24: Congressional Budget Office | C24: https://www.cbo.gov/cost-estimates/hr/8845 | D24: cbo_cost_estimate | E24: 119-2 | F24: 2027 | G24: 2026-05-26 | H24: House Reported | I24: 2026-09-24 | J24: 1-14
A25: SRC-BUDGET-APP-FY2019 | B25: Office of Management and Budget | C25: https://www.govinfo.gov/content/pkg/BUDGET-2019-APP/pdf/BUDGET-2019-APP-1-26.pdf | D25: budget_appendix | F25: 2019 | G25: 2018-02-12 | H25: President's Budget | J25: 1084
A26: SRC-CRPT-118SRPT84 | B26: Senate Committee on Appropriations | C26: https://www.congress.gov/118/crpt/srpt84/CRPT-118srpt84.pdf | D26: committee_report | E26: 118-1 | F26: 2024 | G26: 2023-07-27 00:00:00 | H26: Senate Reported | I26: 2026-09-27 00:00:00 | J26: 366-392; 406 | K26: FY2024 President's Budget; FY2023 Enacted
A27: SRC-CRPT-118SRPT207 | B27: Senate Committee on Appropriations | C27: https://www.congress.gov/118/crpt/srpt207/CRPT-118srpt207.pdf | D27: committee_report | E27: 118-2 | F27: 2025 | G27: 2024-08-01 00:00:00 | H27: Senate Reported | I27: 2026-09-27 00:00:00 | J27: 430-452; 467 | K27: FY2025 President's Budget; FY2024 Enacted
A28: SRC-CRPT-119SRPT55 | B28: Senate Committee on Appropriations | C28: https://www.congress.gov/119/crpt/srpt55/CRPT-119srpt55.pdf | D28: committee_report | E28: 119-1 | F28: 2026 | G28: 2025-08-01 00:00:00 | H28: Senate Reported | I28: 2026-09-27 00:00:00 | J28: 426-442; 450
